Workbook

Sheet Curvas Futuros
C1: LATEST PRICE | T1: AVG. PRICE | W1: $ | Y1: OPEN INTEREST | AP1: Open $ | AQ1: Prev Close $
C2: LC2401 | D2: LC2402 | E2: LC2403 | F2: LC2404 | G2: LC2405 | H2: LC2406 | I2: LC2407 | J2: LC2408 | K2: LC2409 | L2: LC2410 | M2: LC2411 | N2: LC2412 | O2: LC2501 | P2: LC2502 | Q2: LC2503 | R2: LC2504 | S2: AVRG | T2: Battery | U2: Industrial | W2: #VALUE! | X2: {=_FV(W2,"Previous close",TRUE)} -> #VALUE! | Y2: LC2401 | Z2: LC2402 | AA2: LC2403 | AB2: LC2404 | AC2: LC2405 | AD2: LC2406 | AE2: LC2407 | AF2: LC2408 | AG2: LC2409 | AH2: LC2410 | AI2: LC2411 | AJ2: LC2412 | AK2: LC2501 | AL2: LC2502 | AM2: LC2503 | AN2: LC2504 | AO2: TOTAL | AP2: {=_FV(W2,"Open")} -> #VALUE! | AQ2: {=_FV(W2,"Previous close",TRUE)} -> #VALUE!
A3: DATE | B3: 45238 | C3: =+'lc2401'!B2*W3/1000 -> 23.256 | D3: =+'lc2402'!B2*W3/1000 -> 21.76 | E3: =+'lc2403'!B2*W3/1000 -> 21.072 | F3: =+'lc2404'!B2*W3/1000 -> 20.832 | G3: =+'lc2405'!B2*W3/1000 -> 20.536 | H3: =+'lc2406'!B2*W3/1000 -> 20.176 | I3: =+'lc2407'!B2*W3/1000 -> 19.944 | J3: =+'lc2408'!B2*W3/1000 -> 19.68 | K3: =+'lc2409'!B2*W3/1000 -> 19.352 | L3: =+'lc2410'!B2*W3/1000 -> 0 | M3: =+'lc2411'!B2*W3/1000 -> 0 | N3: =+'lc2412'!B2*W3/1000 -> 0 | O3: =+'lc2501'!B2*W3/1000 -> 0 | P3: 0 | Q3: 0 | S3: =+AVERAGE(C3:O3) -> 14.354462 | T3: 0 | U3: 0 | W3: 0.16 | Y3: =+'lc2401'!G2 -> 105467 | Z3: =+'lc2402'!G2 -> 5489 | AA3: =+'lc2403'!G2 -> 3464 | AB3: =+'lc2404'!G2 -> 3424 | AC3: =+'lc2405'!G2 -> 5244 | AD3: =+'lc2406'!G2 -> 3897 | AE3: =+'lc2407'!G2 -> 53080 | AF3: =+'lc2408'!G2 -> 5687 | AG3: =+'lc2409'!G2 -> 10288 | AH3: =+'lc2410'!G2 -> 0 | AI3: =+'lc2411'!G2 -> 0 | AK3: =+'lc2501'!G2 -> 0 | AO3: =+SUM(Y3:AL3) -> 196040 | AP3: 0
B4: 45239 | C4: =+'lc2401'!B3*W4/1000 -> 23.064 | D4: =+'lc2402'!B3*W4/1000 -> 21.712 | E4: =+'lc2403'!B3*W4/1000 -> 21.096 | F4: =+'lc2404'!B3*W4/1000 -> 20.864 | G4: =+'lc2405'!B3*W4/1000 -> 20.576 | H4: =+'lc2406'!B3*W4/1000 -> 20.176 | I4: =+'lc2407'!B3*W4/1000 -> 19.952 | J4: =+'lc2408'!B3*W4/1000 -> 19.656 | K4: =+'lc2409'!B3*W4/1000 -> 19.344 | L4: =+'lc2410'!B3*W4/1000 -> 0 | M4: =+'lc2411'!B3*W4/1000 -> 0 | N4: =+'lc2412'!B3*W4/1000 -> 0 | O4: =+'lc2501'!B3*W4/1000 -> 0 | P4: 0 | Q4: 0 | S4: =+AVERAGE(C4:O4) -> 14.341538 | T4: 0 | U4: 0 | W4: 0.16 | Y4: =+'lc2401'!G3 -> 106948 | Z4: =+'lc2402'!G3 -> 5501 | AA4: =+'lc2403'!G3 -> 3495 | AB4: =+'lc2404'!G3 -> 3565 | AC4: =+'lc2405'!G3 -> 5277 | AD4: =+'lc2406'!G3 -> 3880 | AE4: =+'lc2407'!G3 -> 52858 | AF4: =+'lc2408'!G3 -> 5768 | AG4: =+'lc2409'!G3 -> 10234 | AH4: =+'lc2410'!G3 -> 0 | AI4: =+'lc2411'!G3 -> 0 | AK4: =+'lc2501'!G3 -> 0 | AO4: =+SUM(Y4:AL4) -> 197526 | AP4: =+AO4/AO3-1 -> 0.0075800857
B5: 45240 | C5: =+'lc2401'!B4*W5/1000 -> 23.824 | D5: =+'lc2402'!B4*W5/1000 -> 22.368 | E5: =+'lc2403'!B4*W5/1000 -> 21.68 | F5: =+'lc2404'!B4*W5/1000 -> 21.544 | G5: =+'lc2405'!B4*W5/1000 -> 21.224 | H5: =+'lc2406'!B4*W5/1000 -> 20.888 | I5: =+'lc2407'!B4*W5/1000 -> 20.68 | J5: =+'lc2408'!B4*W5/1000 -> 20.328 | K5: =+'lc2409'!B4*W5/1000 -> 19.968 | L5: =+'lc2410'!B4*W5/1000 -> 0 | M5: =+'lc2411'!B4*W5/1000 -> 0 | N5: =+'lc2412'!B4*W5/1000 -> 0 | O5: =+'lc2501'!B4*W5/1000 -> 0 | P5: 0 | Q5: 0 | S5: =+AVERAGE(C5:O5) -> 14.808 | T5: 0 | U5: 0 | W5: 0.16 | Y5: =+'lc2401'!G4 -> 98275 | Z5: =+'lc2402'!G4 -> 5262 | AA5: =+'lc2403'!G4 -> 3412 | AB5: =+'lc2404'!G4 -> 3891 | AC5: =+'lc2405'!G4 -> 5316 | AD5: =+'lc2406'!G4 -> 3855 | AE5: =+'lc2407'!G4 -> 53766 | AF5: =+'lc2408'!G4 -> 5677 | AG5: =+'lc2409'!G4 -> 9884 | AH5: =+'lc2410'!G4 -> 0 | AI5: =+'lc2411'!G4 -> 0 | AK5: =+'lc2501'!G4 -> 0 | AO5: =+SUM(Y5:AL5) -> 189338 | AP5: =+AO5/AO4-1 -> -0.041452771
B6: 45243 | C6: =+'lc2401'!B5*W6/1000 -> 22.664 | D6: =+'lc2402'!B5*W6/1000 -> 21.528 | E6: =+'lc2403'!B5*W6/1000 -> 21.04 | F6: =+'lc2404'!B5*W6/1000 -> 20.904 | G6: =+'lc2405'!B5*W6/1000 -> 20.672 | H6: =+'lc2406'!B5*W6/1000 -> 20.36 | I6: =+'lc2407'!B5*W6/1000 -> 20.096 | J6: =+'lc2408'!B5*W6/1000 -> 19.832 | K6: =+'lc2409'!B5*W6/1000 -> 19.544 | L6: =+'lc2410'!B5*W6/1000 -> 0 | M6: =+'lc2411'!B5*W6/1000 -> 0 | N6: =+'lc2412'!B5*W6/1000 -> 0 | O6: =+'lc2501'!B5*W6/1000 -> 0 | P6: 0 | Q6: 0 | S6: =+AVERAGE(C6:O6) -> 14.356923 | T6: 0 | U6: 0 | W6: 0.16 | Y6: =+'lc2401'!G5 -> 96195 | Z6: =+'lc2402'!G5 -> 5545 | AA6: =+'lc2403'!G5 -> 3497 | AB6: =+'lc2404'!G5 -> 4076 | AC6: =+'lc2405'!G5 -> 5537 | AD6: =+'lc2406'!G5 -> 3868 | AE6: =+'lc2407'!G5 -> 55395 | AF6: =+'lc2408'!G5 -> 5673 | AG6: =+'lc2409'!G5 -> 9663 | AH6: =+'lc2410'!G5 -> 0 | AI6: =+'lc2411'!G5 -> 0 | AJ6: =+'lc2412'!G5 -> 0 | AK6: =+'lc2501'!G5 -> 0 | AO6: =+SUM(Y6:AL6) -> 189449 | AP6: =+AO6/AO5-1 -> 0.00058625316
B7: 45244 | C7: =+'lc2401'!B6*W7/1000 -> 22.808 | D7: =+'lc2402'!B6*W7/1000 -> 21.8 | E7: =+'lc2403'!B6*W7/1000 -> 21.272 | F7: =+'lc2404'!B6*W7/1000 -> 20.976 | G7: =+'lc2405'!B6*W7/1000 -> 20.664 | H7: =+'lc2406'!B6*W7/1000 -> 20.336 | I7: =+'lc2407'!B6*W7/1000 -> 20.096 | J7: =+'lc2408'!B6*W7/1000 -> 19.872 | K7: =+'lc2409'!B6*W7/1000 -> 19.6 | L7: =+'lc2410'!B6*W7/1000 -> 0 | M7: =+'lc2411'!B6*W7/1000 -> 0 | N7: =+'lc2412'!B6*W7/1000 -> 0 | O7: =+'lc2501'!B6*W7/1000 -> 0 | P7: 0 | Q7: 0 | S7: =+AVERAGE(C7:O7) -> 14.417231 | T7: 0 | U7: 0 | W7: 0.16 | Y7: =+'lc2401'!G6 -> 99509 | Z7: =+'lc2402'!G6 -> 5802 | AA7: =+'lc2403'!G6 -> 3233 | AB7: =+'lc2404'!G6 -> 3965 | AC7: =+'lc2405'!G6 -> 5714 | AD7: =+'lc2406'!G6 -> 3850 | AE7: =+'lc2407'!G6 -> 55084 | AF7: =+'lc2408'!G6 -> 5653 | AG7: =+'lc2409'!G6 -> 9738 | AH7: =+'lc2410'!G6 -> 0 | AI7: =+'lc2411'!G6 -> 0 | AJ7: =+'lc2412'!G6 -> 0 | AK7: =+'lc2501'!G6 -> 0 | AO7: =+SUM(Y7:AL7) -> 192548 | AP7: =+AO7/AO6-1 -> 0.016357964
B8: 45245 | C8: =+'lc2401'!B7*W8/1000 -> 22.816 | D8: =+'lc2402'!B7*W8/1000 -> 21.872 | E8: =+'lc2403'!B7*W8/1000 -> 21.312 | F8: =+'lc2404'!B7*W8/1000 -> 21.072 | G8: =+'lc2405'!B7*W8/1000 -> 20.832 | H8: =+'lc2406'!B7*W8/1000 -> 20.504 | I8: =+'lc2407'!B7*W8/1000 -> 20.32 | J8: =+'lc2408'!B7*W8/1000 -> 20.088 | K8: =+'lc2409'!B7*W8/1000 -> 19.832 | L8: =+'lc2410'!B7*W8/1000 -> 0 | M8: =+'lc2411'!B7*W8/1000 -> 0 | N8: =+'lc2412'!B7*W8/1000 -> 0 | O8: =+'lc2501'!B7*W8/1000 -> 0 | P8: 0 | Q8: 0 | S8: =+AVERAGE(C8:O8) -> 14.511385 | T8: 0 | U8: 0 | W8: 0.16 | Y8: =+'lc2401'!G7 -> 107801 | Z8: =+'lc2402'!G7 -> 6023 | AA8: =+'lc2403'!G7 -> 3227 | AB8: =+'lc2404'!G7 -> 4059 | AC8: =+'lc2405'!G7 -> 5750 | AD8: =+'lc2406'!G7 -> 3864 | AE8: =+'lc2407'!G7 -> 57820 | AF8: =+'lc2408'!G7 -> 5651 | AG8: =+'lc2409'!G7 -> 9647 | AH8: =+'lc2410'!G7 -> 0 | AI8: =+'lc2411'!G7 -> 0 | AJ8: =+'lc2412'!G7 -> 0 | AK8: =+'lc2501'!G7 -> 0 | AO8: =+SUM(Y8:AL8) -> 203842 | AP8: =+AO8/AO7-1 -> 0.058655504
B9: 45246 | C9: =+'lc2401'!B8*W9/1000 -> 22.544 | D9: =+'lc2402'!B8*W9/1000 -> 21.744 | E9: =+'lc2403'!B8*W9/1000 -> 21.216 | F9: =+'lc2404'!B8*W9/1000 -> 21.016 | G9: =+'lc2405'!B8*W9/1000 -> 20.816 | H9: =+'lc2406'!B8*W9/1000 -> 20.504 | I9: =+'lc2407'!B8*W9/1000 -> 20.344 | J9: =+'lc2408'!B8*W9/1000 -> 20.144 | K9: =+'lc2409'!B8*W9/1000 -> 19.944 | L9: =+'lc2410'!B8*W9/1000 -> 0 | M9: =+'lc2411'!B8*W9/1000 -> 0 | N9: =+'lc2412'!B8*W9/1000 -> 0 | O9: =+'lc2501'!B8*W9/1000 -> 0 | P9: 0 | Q9: 0 | S9: =+AVERAGE(C9:O9) -> 14.482462 | T9: 0 | U9: 0 | W9: 0.16 | Y9: =+'lc2401'!G8 -> 113750 | Z9: =+'lc2402'!G8 -> 6118 | AA9: =+'lc2403'!G8 -> 3297 | AB9: =+'lc2404'!G8 -> 4205 | AC9: =+'lc2405'!G8 -> 5748 | AD9: =+'lc2406'!G8 -> 3863 | AE9: =+'lc2407'!G8 -> 59678 | AF9: =+'lc2408'!G8 -> 5684 | AG9: =+'lc2409'!G8 -> 9771 | AH9: =+'lc2410'!G8 -> 0 | AI9: =+'lc2411'!G8 -> 0 | AJ9: =+'lc2412'!G8 -> 0 | AK9: =+'lc2501'!G8 -> 0 | AO9: =+SUM(Y9:AL9) -> 212114 | AP9: =+AO9/AO8-1 -> 0.04058045
B10: 45247 | C10: =+'lc2401'!B9*W10/1000 -> 22.08 | D10: =+'lc2402'!B9*W10/1000 -> 21.344 | E10: =+'lc2403'!B9*W10/1000 -> 21 | F10: =+'lc2404'!B9*W10/1000 -> 20.856 | G10: =+'lc2405'!B9*W10/1000 -> 20.752 | H10: =+'lc2406'!B9*W10/1000 -> 20.464 | I10: =+'lc2407'!B9*W10/1000 -> 20.32 | J10: =+'lc2408'!B9*W10/1000 -> 20.136 | K10: =+'lc2409'!B9*W10/1000 -> 19.888 | L10: =+'lc2410'!B9*W10/1000 -> 0 | M10: =+'lc2411'!B9*W10/1000 -> 0 | N10: =+'lc2412'!B9*W10/1000 -> 0 | O10: =+'lc2501'!B9*W10/1000 -> 0 | P10: 0 | Q10: 0 | S10: =+AVERAGE(C10:O10) -> 14.372308 | T10: 0 | U10: 0 | W10: 0.16 | Y10: =+'lc2401'!G9 -> 113625 | Z10: =+'lc2402'!G9 -> 5920 | AA10: =+'lc2403'!G9 -> 3310 | AB10: =+'lc2404'!G9 -> 4508 | AC10: =+'lc2405'!G9 -> 5846 | AD10: =+'lc2406'!G9 -> 3865 | AE10: =+'lc2407'!G9 -> 60858 | AF10: =+'lc2408'!G9 -> 5686 | AG10: =+'lc2409'!G9 -> 9598 | AH10: =+'lc2410'!G9 -> 0 | AI10: =+'lc2411'!G9 -> 0 | AJ10: =+'lc2412'!G9 -> 0 | AK10: =+'lc2501'!G9 -> 0 | AO10: =+SUM(Y10:AL10) -> 213216 | AP10: =+AO10/AO9-1 -> 0.0051953195
B11: 45250 | C11: =+'lc2401'!B10*W11/1000 -> 21.952 | D11: =+'lc2402'!B10*W11/1000 -> 21.104 | E11: =+'lc2403'!B10*W11/1000 -> 20.584 | F11: =+'lc2404'!B10*W11/1000 -> 20.264 | G11: =+'lc2405'!B10*W11/1000 -> 20 | H11: =+'lc2406'!B10*W11/1000 -> 19.704 | I11: =+'lc2407'!B10*W11/1000 -> 19.584 | J11: =+'lc2408'!B10*W11/1000 -> 19.56 | K11: =+'lc2409'!B10*W11/1000 -> 19.432 | L11: =+'lc2410'!B10*W11/1000 -> 0 | M11: =+'lc2411'!B10*W11/1000 -> 0 | N11: =+'lc2412'!B10*W11/1000 -> 0 | O11: =+'lc2501'!B10*W11/1000 -> 0 | P11: 0 | Q11: 0 | S11: =+AVERAGE(C11:O11) -> 14.014154 | T11: 0 | U11: 0 | W11: 0.16 | Y11: =+'lc2401'!G10 -> 117451 | Z11: =+'lc2402'!G10 -> 5875 | AA11: =+'lc2403'!G10 -> 3393 | AB11: =+'lc2404'!G10 -> 4289 | AC11: =+'lc2405'!G10 -> 6229 | AD11: =+'lc2406'!G10 -> 3844 | AE11: =+'lc2407'!G10 -> 64639 | AF11: =+'lc2408'!G10 -> 5526 | AG11: =+'lc2409'!G10 -> 9550 | AH11: =+'lc2410'!G10 -> 0 | AI11: =+'lc2411'!G10 -> 0 | AJ11: =+'lc2412'!G10 -> 0 | AK11: =+'lc2501'!G10 -> 0 | AO11: =+SUM(Y11:AL11) -> 220796 | AP11: =+AO11/AO10-1 -> 0.035550803
B12: 45251 | C12: =+'lc2401'!B11*W12/1000 -> 21.168 | D12: =+'lc2402'!B11*W12/1000 -> 20.44 | E12: =+'lc2403'!B11*W12/1000 -> 20.064 | F12: =+'lc2404'!B11*W12/1000 -> 19.896 | G12: =+'lc2405'!B11*W12/1000 -> 19.696 | H12: =+'lc2406'!B11*W12/1000 -> 19.48 | I12: =+'lc2407'!B11*W12/1000 -> 19.392 | J12: =+'lc2408'!B11*W12/1000 -> 19.392 | K12: =+'lc2409'!B11*W12/1000 -> 19.28 | L12: =+'lc2410'!B11*W12/1000 -> 0 | M12: =+'lc2411'!B11*W12/1000 -> 0 | N12: =+'lc2412'!B11*W12/1000 -> 0 | O12: =+'lc2501'!B11*W12/1000 -> 0 | P12: 0 | Q12: 0 | S12: =+AVERAGE(C12:O12) -> 13.754462 | T12: 0 | U12: 0 | W12: 0.16 | Y12: =+'lc2401'!G11 -> 119970 | Z12: =+'lc2402'!G11 -> 5781 | AA12: =+'lc2403'!G11 -> 3548 | AB12: =+'lc2404'!G11 -> 4282 | AC12: =+'lc2405'!G11 -> 6303 | AD12: =+'lc2406'!G11 -> 3872 | AE12: =+'lc2407'!G11 -> 67378 | AF12: =+'lc2408'!G11 -> 6065 | AG12: =+'lc2409'!G11 -> 9887 | AH12: =+'lc2410'!G11 -> 0 | AI12: =+'lc2411'!G11 -> 0 | AJ12: =+'lc2412'!G11 -> 0 | AK12: =+'lc2501'!G11 -> 0 | AO12: =+SUM(Y12:AL12) -> 227086 | AP12: =+AO12/AO11-1 -> 0.028487835
B13: 45252 | C13: =+'lc2401'!B12*W13/1000 -> 19.952 | D13: =+'lc2402'!B12*W13/1000 -> 19.184 | E13: =+'lc2403'!B12*W13/1000 -> 18.864 | F13: =+'lc2404'!B12*W13/1000 -> 18.864 | G13: =+'lc2405'!B12*W13/1000 -> 18.664 | H13: =+'lc2406'!B12*W13/1000 -> 18.44 | I13: =+'lc2407'!B12*W13/1000 -> 18.424 | J13: =+'lc2408'!B12*W13/1000 -> 18.4 | K13: =+'lc2409'!B12*W13/1000 -> 18.4 | L13: =+'lc2410'!B12*W13/1000 -> 0 | M13: =+'lc2411'!B12*W13/1000 -> 0 | N13: =+'lc2412'!B12*W13/1000 -> 0 | O13: =+'lc2501'!B12*W13/1000 -> 0 | P13: 0 | Q13: 0 | S13: =+AVERAGE(C13:O13) -> 13.014769 | T13: 0 | U13: 0 | W13: 0.16 | Y13: =+'lc2401'!G12 -> 117807 | Z13: =+'lc2402'!G12 -> 5793 | AA13: =+'lc2403'!G12 -> 3822 | AB13: =+'lc2404'!G12 -> 4137 | AC13: =+'lc2405'!G12 -> 6568 | AD13: =+'lc2406'!G12 -> 4026 | AE13: =+'lc2407'!G12 -> 72059 | AF13: =+'lc2408'!G12 -> 6662 | AG13: =+'lc2409'!G12 -> 10645 | AH13: =+'lc2410'!G12 -> 0 | AI13: =+'lc2411'!G12 -> 0 | AJ13: =+'lc2412'!G12 -> 0 | AK13: =+'lc2501'!G12 -> 0 | AO13: =+SUM(Y13:AL13) -> 231519 | AP13: =+AO13/AO12-1 -> 0.019521239
B14: 45253 | C14: =+'lc2401'!B13*W14/1000 -> 19.968 | D14: =+'lc2402'!B13*W14/1000 -> 19.136 | E14: =+'lc2403'!B13*W14/1000 -> 18.864 | F14: =+'lc2404'!B13*W14/1000 -> 18.64 | G14: =+'lc2405'!B13*W14/1000 -> 18.456 | H14: =+'lc2406'!B13*W14/1000 -> 18.208 | I14: =+'lc2407'!B13*W14/1000 -> 18.208 | J14: =+'lc2408'!B13*W14/1000 -> 18.264 | K14: =+'lc2409'!B13*W14/1000 -> 18.16 | L14: =+'lc2410'!B13*W14/1000 -> 0 | M14: =+'lc2411'!B13*W14/1000 -> 0 | N14: =+'lc2412'!B13*W14/1000 -> 0 | O14: =+'lc2501'!B13*W14/1000 -> 0 | P14: 0 | Q14: 0 | S14: =+AVERAGE(C14:O14) -> 12.915692 | T14: 0 | U14: 0 | W14: 0.16 | Y14: =+'lc2401'!G13 -> 115316 | Z14: =+'lc2402'!G13 -> 6045 | AA14: =+'lc2403'!G13 -> 3830 | AB14: =+'lc2404'!G13 -> 4055 | AC14: =+'lc2405'!G13 -> 6694 | AD14: =+'lc2406'!G13 -> 4060 | AE14: =+'lc2407'!G13 -> 74096 | AF14: =+'lc2408'!G13 -> 6626 | AG14: =+'lc2409'!G13 -> 10959 | AH14: =+'lc2410'!G13 -> 0 | AI14: =+'lc2411'!G13 -> 0 | AJ14: =+'lc2412'!G13 -> 0 | AK14: =+'lc2501'!G13 -> 0 | AO14: =+SUM(Y14:AL14) -> 231681 | AP14: =+AO14/AO13-1 -> 0.00069972659
B15: 45254 | C15: =+'lc2401'!B14*W15/1000 -> 19.848 | D15: =+'lc2402'!B14*W15/1000 -> 19.056 | E15: =+'lc2403'!B14*W15/1000 -> 18.704 | F15: =+'lc2404'!B14*W15/1000 -> 18.68 | G15: =+'lc2405'!B14*W15/1000 -> 18.6 | H15: =+'lc2406'!B14*W15/1000 -> 18.488 | I15: =+'lc2407'!B14*W15/1000 -> 18.376 | J15: =+'lc2408'!B14*W15/1000 -> 18.384 | K15: =+'lc2409'!B14*W15/1000 -> 18.256 | L15: =+'lc2410'!B14*W15/1000 -> 18.104 | M15: =+'lc2411'!B14*W15/1000 -> 17.928 | N15: =+'lc2412'!B14*W15/1000 -> 0 | O15: =+'lc2501'!B14*W15/1000 -> 0 | P15: 0 | Q15: 0 | S15: =+AVERAGE(C15:O15) -> 15.724923 | T15: 0 | U15: 0 | W15: 0.16 | Y15: =+'lc2401'!G14 -> 121691 | Z15: =+'lc2402'!G14 -> 6327 | AA15: =+'lc2403'!G14 -> 4409 | AB15: =+'lc2404'!G14 -> 4498 | AC15: =+'lc2405'!G14 -> 6910 | AD15: =+'lc2406'!G14 -> 4141 | AE15: =+'lc2407'!G14 -> 77344 | AF15: =+'lc2408'!G14 -> 6395 | AG15: =+'lc2409'!G14 -> 10718 | AH15: =+'lc2410'!G14 -> 4499 | AI15: =+'lc2411'!G14 -> 2325 | AJ15: =+'lc2412'!G14 -> 0 | AK15: =+'lc2501'!G14 -> 0 | AO15: =+SUM(Y15:AL15) -> 249257 | AP15: =+AO15/AO14-1 -> 0.075862932
B16: 45257 | C16: =+'lc2401'!B15*W16/1000 -> 18.664 | D16: =+'lc2402'!B15*W16/1000 -> 17.88 | E16: =+'lc2403'!B15*W16/1000 -> 17.584 | F16: =+'lc2404'!B15*W16/1000 -> 17.512 | G16: =+'lc2405'!B15*W16/1000 -> 17.376 | H16: =+'lc2406'!B15*W16/1000 -> 17.32 | I16: =+'lc2407'!B15*W16/1000 -> 17.232 | J16: =+'lc2408'!B15*W16/1000 -> 17.272 | K16: =+'lc2409'!B15*W16/1000 -> 17.168 | L16: =+'lc2410'!B15*W16/1000 -> 16.992 | M16: =+'lc2411'!B15*W16/1000 -> 16.832 | N16: =+'lc2412'!B15*W16/1000 -> 0 | O16: =+'lc2501'!B15*W16/1000 -> 0 | P16: 0 | Q16: 0 | S16: =+AVERAGE(C16:O16) -> 14.756308 | T16: =+#REF!*'Curvas Futuros'!W16/1000 -> #REF! | U16: =+#REF!*'Curvas Futuros'!W16/1000 -> #REF! | W16: 0.16 | Y16: =+'lc2401'!G15 -> 131929 | Z16: =+'lc2402'!G15 -> 6638 | AA16: =+'lc2403'!G15 -> 5833 | AB16: =+'lc2404'!G15 -> 5169 | AC16: =+'lc2405'!G15 -> 7599 | AD16: =+'lc2406'!G15 -> 4057 | AE16: =+'lc2407'!G15 -> 87321 | AF16: =+'lc2408'!G15 -> 6445 | AG16: =+'lc2409'!G15 -> 11526 | AH16: =+'lc2410'!G15 -> 4627 | AI16: =+'lc2411'!G15 -> 2800 | AJ16: =+'lc2412'!G15 -> 0 | AK16: =+'lc2501'!G15 -> 0 | AO16: =+SUM(Y16:AL16) -> 273944 | AP16: =+AO16/AO15-1 -> 0.099042354
B17: 45258 | C17: =+'lc2401'!B16*W17/1000 -> 18.112 | D17: =+'lc2402'!B16*W17/1000 -> 17.52 | E17: =+'lc2403'!B16*W17/1000 -> 17.416 | F17: =+'lc2404'!B16*W17/1000 -> 17.576 | G17: =+'lc2405'!B16*W17/1000 -> 17.608 | H17: =+'lc2406'!B16*W17/1000 -> 17.592 | I17: =+'lc2407'!B16*W17/1000 -> 17.528 | J17: =+'lc2408'!B16*W17/1000 -> 17.528 | K17: =+'lc2409'!B16*W17/1000 -> 17.408 | L17: =+'lc2410'!B16*W17/1000 -> 17.28 | M17: =+'lc2411'!B16*W17/1000 -> 17.088 | N17: =+'lc2412'!B16*W17/1000 -> 0 | O17: =+'lc2501'!B16*W17/1000 -> 0 | P17: 0 | Q17: 0 | S17: =+AVERAGE(C17:O17) -> 14.819692 | T17: =+#REF!*'Curvas Futuros'!W17/1000 -> #REF! | U17: =+#REF!*'Curvas Futuros'!W17/1000 -> #REF! | W17: 0.16 | Y17: =+'lc2401'!G16 -> 122822 | Z17: =+'lc2402'!G16 -> 7186 | AA17: =+'lc2403'!G16 -> 7388 | AB17: =+'lc2404'!G16 -> 6575 | AC17: =+'lc2405'!G16 -> 8773 | AD17: =+'lc2406'!G16 -> 4162 | AE17: =+'lc2407'!G16 -> 93278 | AF17: =+'lc2408'!G16 -> 6471 | AG17: =+'lc2409'!G16 -> 12046 | AH17: =+'lc2410'!G16 -> 4742 | AI17: =+'lc2411'!G16 -> 2937 | AJ17: =+'lc2412'!G16 -> 0 | AK17: =+'lc2501'!G16 -> 0 | AO17: =+SUM(Y17:AL17) -> 276380 | AP17: =+AO17/AO16-1 -> 0.0088923284
B18: 45259 | C18: =+'lc2401'!B17*W18/1000 -> 17.576 | D18: =+'lc2402'!B17*W18/1000 -> 17.368 | E18: =+'lc2403'!B17*W18/1000 -> 17.336 | F18: =+'lc2404'!B17*W18/1000 -> 17.808 | G18: =+'lc2405'!B17*W18/1000 -> 17.824 | H18: =+'lc2406'!B17*W18/1000 -> 17.848 | I18: =+'lc2407'!B17*W18/1000 -> 17.856 | J18: =+'lc2408'!B17*W18/1000 -> 17.8 | K18: =+'lc2409'!B17*W18/1000 -> 17.688 | L18: =+'lc2410'!B17*W18/1000 -> 17.536 | M18: =+'lc2411'!B17*W18/1000 -> 17.416 | N18: =+'lc2412'!B17*W18/1000 -> 0 | O18: =+'lc2501'!B17*W18/1000 -> 0 | P18: 0 | Q18: 0 | S18: =+AVERAGE(C18:O18) -> 14.927385 | T18: =+#REF!*'Curvas Futuros'!W18/1000 -> #REF! | U18: =+#REF!*'Curvas Futuros'!W18/1000 -> #REF! | W18: 0.16 | Y18: =+'lc2401'!G17 -> 140181 | Z18: =+'lc2402'!G17 -> 9534 | AA18: =+'lc2403'!G17 -> 9844 | AB18: =+'lc2404'!G17 -> 9537 | AC18: =+'lc2405'!G17 -> 10466 | AD18: =+'lc2406'!G17 -> 4338 | AE18: =+'lc2407'!G17 -> 105471 | AF18: =+'lc2408'!G17 -> 6213 | AG18: =+'lc2409'!G17 -> 12213 | AH18: =+'lc2410'!G17 -> 4802 | AI18: =+'lc2411'!G17 -> 2894 | AJ18: =+'lc2412'!G17 -> 0 | AK18: =+'lc2501'!G17 -> 0 | AO18: =+SUM(Y18:AL18) -> 315493 | AP18: =+AO18/AO17-1 -> 0.14151892
B19: 45260 | C19: =+'lc2401'!B18*W19/1000 -> 16.992 | D19: =+'lc2402'!B18*W19/1000 -> 16.816 | E19: =+'lc2403'!B18*W19/1000 -> 16.768 | F19: =+'lc2404'!B18*W19/1000 -> 17.264 | G19: =+'lc2405'!B18*W19/1000 -> 17.232 | H19: =+'lc2406'!B18*W19/1000 -> 17.28 | I19: =+'lc2407'!B18*W19/1000 -> 17.224 | J19: =+'lc2408'!B18*W19/1000 -> 17.296 | K19: =+'lc2409'!B18*W19/1000 -> 17.216 | L19: =+'lc2410'!B18*W19/1000 -> 17.12 | M19: =+'lc2411'!B18*W19/1000 -> 16.984 | N19: =+'lc2412'!B18*W19/1000 -> 0 | O19: =+'lc2501'!B18*W19/1000 -> 0 | P19: 0 | Q19: 0 | S19: =+AVERAGE(C19:O19) -> 14.476308 | T19: =+#REF!*'Curvas Futuros'!W19/1000 -> #REF! | U19: =+#REF!*'Curvas Futuros'!W19/1000 -> #REF! | W19: 0.16 | Y19: =+'lc2401'!G18 -> 145373 | Z19: =+'lc2402'!G18 -> 9965 | AA19: =+'lc2403'!G18 -> 10313 | AB19: =+'lc2404'!G18 -> 9975 | AC19: =+'lc2405'!G18 -> 10999 | AD19: =+'lc2406'!G18 -> 4341 | AE19: =+'lc2407'!G18 -> 111186 | AF19: =+'lc2408'!G18 -> 6386 | AG19: =+'lc2409'!G18 -> 12492 | AH19: =+'lc2410'!G18 -> 4777 | AI19: =+'lc2411'!G18 -> 3129 | AJ19: =+'lc2412'!G18 -> 0 | AK19: =+'lc2501'!G18 -> 0 | AO19: =+SUM(Y19:AL19) -> 328936 | AP19: =+AO19/AO18-1 -> 0.042609503
B20: 45261 | C20: =+'lc2401'!B19*W20/1000 -> 16.28 | D20: =+'lc2402'!B19*W20/1000 -> 16.032 | E20: =+'lc2403'!B19*W20/1000 -> 16.016 | F20: =+'lc2404'!B19*W20/1000 -> 16.68 | G20: =+'lc2405'!B19*W20/1000 -> 16.696 | H20: =+'lc2406'!B19*W20/1000 -> 16.688 | I20: =+'lc2407'!B19*W20/1000 -> 16.728 | J20: =+'lc2408'!B19*W20/1000 -> 16.704 | K20: =+'lc2409'!B19*W20/1000 -> 16.672 | L20: =+'lc2410'!B19*W20/1000 -> 16.616 | M20: =+'lc2411'!B19*W20/1000 -> 16.464 | N20: =+'lc2412'!B19*W20/1000 -> 0 | O20: =+'lc2501'!B19*W20/1000 -> 0 | P20: 0 | Q20: 0 | S20: =+AVERAGE(C20:O20) -> 13.967385 | T20: =+#REF!*'Curvas Futuros'!W20/1000 -> #REF! | U20: =+#REF!*'Curvas Futuros'!W20/1000 -> #REF! | W20: 0.16 | Y20: =+'lc2401'!G19 -> 135708 | Z20: =+'lc2402'!G19 -> 12282 | AA20: =+'lc2403'!G19 -> 12749 | AB20: =+'lc2404'!G19 -> 12287 | AC20: =+'lc2405'!G19 -> 12033 | AD20: =+'lc2406'!G19 -> 4607 | AE20: =+'lc2407'!G19 -> 114139 | AF20: =+'lc2408'!G19 -> 6778 | AG20: =+'lc2409'!G19 -> 13157 | AH20: =+'lc2410'!G19 -> 4755 | AI20: =+'lc2411'!G19 -> 3608 | AJ20: =+'lc2412'!G19 -> 0 | AK20: =+'lc2501'!G19 -> 0 | AO20: =+SUM(Y20:AL20) -> 332103 | AP20: =+AO20/AO19-1 -> 0.0096280127
B21: 45264 | C21: =+'lc2401'!B20*W21/1000 -> 15.416 | D21: =+'lc2402'!B20*W21/1000 -> 15.16 | E21: =+'lc2403'!B20*W21/1000 -> 15.128 | F21: =+'lc2404'!B20*W21/1000 -> 15.6 | G21: =+'lc2405'!B20*W21/1000 -> 15.6 | H21: =+'lc2406'!B20*W21/1000 -> 15.6 | I21: =+'lc2407'!B20*W21/1000 -> 15.56 | J21: =+'lc2408'!B20*W21/1000 -> 15.656 | K21: =+'lc2409'!B20*W21/1000 -> 15.568 | L21: =+'lc2410'!B20*W21/1000 -> 15.488 | M21: =+'lc2411'!B20*W21/1000 -> 15.368 | N21: =+'lc2412'!B20*W21/1000 -> 0 | O21: =+'lc2501'!B20*W21/1000 -> 0 | P21: 0 | Q21: 0 | S21: =+AVERAGE(C21:O21) -> 13.088 | T21: =+#REF!*'Curvas Futuros'!W21/1000 -> #REF! | U21: =+#REF!*'Curvas Futuros'!W21/1000 -> #REF! | W21: 0.16 | Y21: =+'lc2401'!G20 -> 145648 | Z21: =+'lc2402'!G20 -> 15204 | AA21: =+'lc2403'!G20 -> 14212 | AB21: =+'lc2404'!G20 -> 16676 | AC21: =+'lc2405'!G20 -> 13121 | AD21: =+'lc2406'!G20 -> 4864 | AE21: =+'lc2407'!G20 -> 128879 | AF21: =+'lc2408'!G20 -> 7433 | AG21: =+'lc2409'!G20 -> 13411 | AH21: =+'lc2410'!G20 -> 4773 | AI21: =+'lc2411'!G20 -> 4562 | AJ21: =+'lc2412'!G20 -> 0 | AK21: =+'lc2501'!G20 -> 0 | AO21: =+SUM(Y21:AL21) -> 368783 | AP21: =+AO21/AO20-1 -> 0.11044766
B22: 45265 | C22: =+'lc2401'!B21*W22/1000 -> 14.888 | D22: =+'lc2402'!B21*W22/1000 -> 14.088 | E22: =+'lc2403'!B21*W22/1000 -> 14.112 | F22: =+'lc2404'!B21*W22/1000 -> 14.656 | G22: =+'lc2405'!B21*W22/1000 -> 14.568 | H22: =+'lc2406'!B21*W22/1000 -> 14.616 | I22: =+'lc2407'!B21*W22/1000 -> 14.528 | J22: =+'lc2408'!B21*W22/1000 -> 14.608 | K22: =+'lc2409'!B21*W22/1000 -> 14.488 | L22: =+'lc2410'!B21*W22/1000 -> 14.384 | M22: =+'lc2411'!B21*W22/1000 -> 14.728 | N22: =+'lc2412'!B21*W22/1000 -> 0 | O22: =+'lc2501'!B21*W22/1000 -> 0 | P22: 0 | Q22: 0 | S22: =+AVERAGE(C22:O22) -> 12.281846 | T22: =+#REF!*'Curvas Futuros'!W22/1000 -> #REF! | U22: =+#REF!*'Curvas Futuros'!W22/1000 -> #REF! | W22: 0.16 | Y22: =+'lc2401'!G21 -> 150052 | Z22: =+'lc2402'!G21 -> 19643 | AA22: =+'lc2403'!G21 -> 14505 | AB22: =+'lc2404'!G21 -> 17394 | AC22: =+'lc2405'!G21 -> 13499 | AD22: =+'lc2406'!G21 -> 5072 | AE22: =+'lc2407'!G21 -> 138614 | AF22: =+'lc2408'!G21 -> 7278 | AG22: =+'lc2409'!G21 -> 13364 | AH22: =+'lc2410'!G21 -> 4956 | AI22: =+'lc2411'!G21 -> 5254 | AJ22: =+'lc2412'!G21 -> 0 | AK22: =+'lc2501'!G21 -> 0 | AO22: =+SUM(Y22:AL22) -> 389631 | AP22: =+AO22/AO21-1 -> 0.05653189
B23: 45266 | C23: =+'lc2401'!B22*W23/1000 -> 14.792 | D23: =+'lc2402'!B22*W23/1000 -> 14.36 | E23: =+'lc2403'!B22*W23/1000 -> 14.416 | F23: =+'lc2404'!B22*W23/1000 -> 14.944 | G23: =+'lc2405'!B22*W23/1000 -> 14.96 | H23: =+'lc2406'!B22*W23/1000 -> 14.904 | I23: =+'lc2407'!B22*W23/1000 -> 14.944 | J23: =+'lc2408'!B22*W23/1000 -> 14.936 | K23: =+'lc2409'!B22*W23/1000 -> 14.88 | L23: =+'lc2410'!B22*W23/1000 -> 14.784 | M23: =+'lc2411'!B22*W23/1000 -> 14.744 | N23: =+'lc2412'!B22*W23/1000 -> 0 | O23: =+'lc2501'!B22*W23/1000 -> 0 | P23: 0 | Q23: 0 | S23: =+AVERAGE(C23:O23) -> 12.512615 | T23: =+#REF!*'Curvas Futuros'!W23/1000 -> #REF! | U23: =+#REF!*'Curvas Futuros'!W23/1000 -> #REF! | W23: 0.16 | Y23: =+'lc2401'!G22 -> 128963 | Z23: =+'lc2402'!G22 -> 21976 | AA23: =+'lc2403'!G22 -> 17531 | AB23: =+'lc2404'!G22 -> 21030 | AC23: =+'lc2405'!G22 -> 14396 | AD23: =+'lc2406'!G22 -> 5136 | AE23: =+'lc2407'!G22 -> 148646 | AF23: =+'lc2408'!G22 -> 7504 | AG23: =+'lc2409'!G22 -> 13289 | AH23: =+'lc2410'!G22 -> 5036 | AI23: =+'lc2411'!G22 -> 5389 | AJ23: =+'lc2412'!G22 -> 0 | AK23: =+'lc2501'!G22 -> 0 | AO23: =+SUM(Y23:AL23) -> 388896 | AP23: =+AO23/AO22-1 -> -0.0018864002
B24: 45267 | C24: =+'lc2401'!B23*W24/1000 -> 15.296 | D24: =+'lc2402'!B23*W24/1000 -> 14.816 | E24: =+'lc2403'!B23*W24/1000 -> 14.808 | F24: =+'lc2404'!B23*W24/1000 -> 15.32 | G24: =+'lc2405'!B23*W24/1000 -> 15.312 | H24: =+'lc2406'!B23*W24/1000 -> 15.328 | I24: =+'lc2407'!B23*W24/1000 -> 15.32 | J24: =+'lc2408'!B23*W24/1000 -> 15.368 | K24: =+'lc2409'!B23*W24/1000 -> 15.24 | L24: =+'lc2410'!B23*W24/1000 -> 15.128 | M24: =+'lc2411'!B23*W24/1000 -> 15.056 | N24: =+'lc2412'!B23*W24/1000 -> 0 | O24: =+'lc2501'!B23*W24/1000 -> 0 | P24: 0 | Q24: 0 | S24: =+AVERAGE(C24:O24) -> 12.845538 | T24: =+#REF!*'Curvas Futuros'!W24/1000 -> #REF! | U24: =+#REF!*'Curvas Futuros'!W24/1000 -> #REF! | W24: 0.16 | Y24: =+'lc2401'!G23 -> 124068 | Z24: =+'lc2402'!G23 -> 25035 | AA24: =+'lc2403'!G23 -> 17452 | AB24: =+'lc2404'!G23 -> 23101 | AC24: =+'lc2405'!G23 -> 14736 | AD24: =+'lc2406'!G23 -> 5178 | AE24: =+'lc2407'!G23 -> 165720 | AF24: =+'lc2408'!G23 -> 7523 | AG24: =+'lc2409'!G23 -> 13362 | AH24: =+'lc2410'!G23 -> 4995 | AI24: =+'lc2411'!G23 -> 5496 | AJ24: =+'lc2412'!G23 -> 0 | AK24: =+'lc2501'!G23 -> 0 | AO24: =+SUM(Y24:AL24) -> 406666 | AP24: =+AO24/AO23-1 -> 0.04569345
B25: 45268 | C25: =+'lc2401'!B24*W25/1000 -> 16.496 | D25: =+'lc2402'!B24*W25/1000 -> 15.864 | E25: =+'lc2403'!B24*W25/1000 -> 15.824 | F25: =+'lc2404'!B24*W25/1000 -> 16.352 | G25: =+'lc2405'!B24*W25/1000 -> 16.352 | H25: =+'lc2406'!B24*W25/1000 -> 16.392 | I25: =+'lc2407'!B24*W25/1000 -> 16.368 | J25: =+'lc2408'!B24*W25/1000 -> 16.504 | K25: =+'lc2409'!B24*W25/1000 -> 16.312 | L25: =+'lc2410'!B24*W25/1000 -> 16.216 | M25: =+'lc2411'!B24*W25/1000 -> 16.136 | N25: =+'lc2412'!B24*W25/1000 -> 0 | O25: =+'lc2501'!B24*W25/1000 -> 0 | P25: 0 | Q25: 0 | S25: =+AVERAGE(C25:O25) -> 13.755077 | T25: =+#REF!*'Curvas Futuros'!W25/1000 -> #REF! | U25: =+#REF!*'Curvas Futuros'!W25/1000 -> #REF! | W25: 0.16 | Y25: =+'lc2401'!G24 -> 126990 | Z25: =+'lc2402'!G24 -> 24010 | AA25: =+'lc2403'!G24 -> 16954 | AB25: =+'lc2404'!G24 -> 22664 | AC25: =+'lc2405'!G24 -> 14000 | AD25: =+'lc2406'!G24 -> 5147 | AE25: =+'lc2407'!G24 -> 158315 | AF25: =+'lc2408'!G24 -> 7468 | AG25: =+'lc2409'!G24 -> 12636 | AH25: =+'lc2410'!G24 -> 4812 | AI25: =+'lc2411'!G24 -> 7421 | AJ25: =+'lc2412'!G24 -> 0 | AK25: =+'lc2501'!G24 -> 0 | AO25: =+SUM(Y25:AL25) -> 400417 | AP25: =+AO25/AO24-1 -> -0.015366419
B26: 45271 | C26: =+'lc2401'!B25*W26/1000 -> 15.832 | D26: =+'lc2402'!B25*W26/1000 -> 15.336 | E26: =+'lc2403'!B25*W26/1000 -> 15.296 | F26: =+'lc2404'!B25*W26/1000 -> 15.704 | G26: =+'lc2405'!B25*W26/1000 -> 15.576 | H26: =+'lc2406'!B25*W26/1000 -> 15.448 | I26: =+'lc2407'!B25*W26/1000 -> 15.488 | J26: =+'lc2408'!B25*W26/1000 -> 15.536 | K26: =+'lc2409'!B25*W26/1000 -> 15.456 | L26: =+'lc2410'!B25*W26/1000 -> 15.36 | M26: =+'lc2411'!B25*W26/1000 -> 15.304 | N26: =+'lc2412'!B25*W26/1000 -> 0 | O26: =+'lc2501'!B25*W26/1000 -> 0 | P26: 0 | Q26: 0 | S26: =+AVERAGE(C26:O26) -> 13.102769 | T26: =+#REF!*'Curvas Futuros'!W26/1000 -> #REF! | U26: =+#REF!*'Curvas Futuros'!W26/1000 -> #REF! | W26: 0.16 | Y26: =+'lc2401'!G25 -> 54850 | Z26: =+'lc2402'!G25 -> 18047 | AA26: =+'lc2403'!G25 -> 15965 | AB26: =+'lc2404'!G25 -> 18423 | AC26: =+'lc2405'!G25 -> 10667 | AD26: =+'lc2406'!G25 -> 4265 | AE26: =+'lc2407'!G25 -> 156695 | AF26: =+'lc2408'!G25 -> 6611 | AG26: =+'lc2409'!G25 -> 11665 | AH26: =+'lc2410'!G25 -> 4359 | AI26: =+'lc2411'!G25 -> 6493 | AJ26: =+'lc2412'!G25 -> 0 | AK26: =+'lc2501'!G25 -> 0 | AO26: =+SUM(Y26:AL26) -> 308040 | AP26: =+AO26/AO25-1 -> -0.23070199
B27: 45272 | C27: =+'lc2401'!B26*W27/1000 -> 15.52 | D27: =+'lc2402'!B26*W27/1000 -> 14.968 | E27: =+'lc2403'!B26*W27/1000 -> 14.744 | F27: =+'lc2404'!B26*W27/1000 -> 15.192 | G27: =+'lc2405'!B26*W27/1000 -> 15.032 | H27: =+'lc2406'!B26*W27/1000 -> 15.16 | I27: =+'lc2407'!B26*W27/1000 -> 14.896 | J27: =+'lc2408'!B26*W27/1000 -> 15.208 | K27: =+'lc2409'!B26*W27/1000 -> 15.04 | L27: =+'lc2410'!B26*W27/1000 -> 14.976 | M27: =+'lc2411'!B26*W27/1000 -> 14.872 | N27: =+'lc2412'!B26*W27/1000 -> 0 | O27: =+'lc2501'!B26*W27/1000 -> 0 | P27: 0 | Q27: 0 | S27: =+AVERAGE(C27:O27) -> 12.739077 | T27: =+#REF!*'Curvas Futuros'!W27/1000 -> #REF! | U27: =+#REF!*'Curvas Futuros'!W27/1000 -> #REF! | W27: 0.16 | Y27: =+'lc2401'!G26 -> 52972 | Z27: =+'lc2402'!G26 -> 18310 | AA27: =+'lc2403'!G26 -> 16581 | AB27: =+'lc2404'!G26 -> 18082 | AC27: =+'lc2405'!G26 -> 9333 | AD27: =+'lc2406'!G26 -> 4987 | AE27: =+'lc2407'!G26 -> 172604 | AF27: =+'lc2408'!G26 -> 6915 | AG27: =+'lc2409'!G26 -> 11917 | AH27: =+'lc2410'!G26 -> 4575 | AI27: =+'lc2411'!G26 -> 7420 | AJ27: =+'lc2412'!G26 -> 0 | AK27: =+'lc2501'!G26 -> 0 | AO27: =+SUM(Y27:AL27) -> 323696 | AP27: =+AO27/AO26-1 -> 0.050824568
B28: 45273 | C28: =+'lc2401'!B27*W28/1000 -> 17.368 | D28: =+'lc2402'!B27*W28/1000 -> 17.064 | E28: =+'lc2403'!B27*W28/1000 -> 16.496 | F28: =+'lc2404'!B27*W28/1000 -> 17.392 | G28: =+'lc2405'!B27*W28/1000 -> 16.808 | H28: =+'lc2406'!B27*W28/1000 -> 17.2 | I28: =+'lc2407'!B27*W28/1000 -> 16.568 | J28: =+'lc2408'!B27*W28/1000 -> 17.328 | K28: =+'lc2409'!B27*W28/1000 -> 16.76 | L28: =+'lc2410'!B27*W28/1000 -> 16.584 | M28: =+'lc2411'!B27*W28/1000 -> 16.432 | N28: =+'lc2412'!B27*W28/1000 -> 0 | O28: =+'lc2501'!B27*W28/1000 -> 0 | P28: =+'lc2501'!C27*X28/1000 -> 0 | Q28: 0 | S28: =+AVERAGE(C28:O28) -> 14.307692 | T28: =+#REF!*'Curvas Futuros'!W28/1000 -> #REF! | U28: =+#REF!*'Curvas Futuros'!W28/1000 -> #REF! | W28: 0.16 | Y28: =+'lc2401'!G27 -> 46331 | Z28: =+'lc2402'!G27 -> 19057 | AA28: =+'lc2403'!G27 -> 18067 | AB28: =+'lc2404'!G27 -> 21630 | AC28: =+'lc2405'!G27 -> 11174 | AD28: =+'lc2406'!G27 -> 4975 | AE28: =+'lc2407'!G27 -> 172000 | AF28: =+'lc2408'!G27 -> 7368 | AG28: =+'lc2409'!G27 -> 11183 | AH28: =+'lc2410'!G27 -> 4503 | AI28: =+'lc2411'!G27 -> 7285 | AJ28: =+'lc2412'!G27 -> 0 | AK28: =+'lc2501'!G27 -> 0 | AO28: =+SUM(Y28:AL28) -> 323573 | AP28: =+AO28/AO27-1 -> -0.00037998616
B29: 45274 | C29: =+'lc2401'!B28*W29/1000 -> 16.152 | D29: =+'lc2402'!B28*W29/1000 -> 15.984 | E29: =+'lc2403'!B28*W29/1000 -> 15.944 | F29: =+'lc2404'!B28*W29/1000 -> 16.464 | G29: =+'lc2405'!B28*W29/1000 -> 16.416 | H29: =+'lc2406'!B28*W29/1000 -> 16.48 | I29: =+'lc2407'!B28*W29/1000 -> 16.408 | J29: =+'lc2408'!B28*W29/1000 -> 16.52 | K29: =+'lc2409'!B28*W29/1000 -> 16.456 | L29: =+'lc2410'!B28*W29/1000 -> 16.344 | M29: =+'lc2411'!B28*W29/1000 -> 16.248 | N29: =+'lc2412'!B28*W29/1000 -> 0 | O29: =+'lc2501'!B28*W29/1000 -> 0 | P29: =+'lc2501'!C28*X29/1000 -> 0 | Q29: 0 | S29: =+AVERAGE(C29:O29) -> 13.801231 | T29: =+#REF!*'Curvas Futuros'!W29/1000 -> #REF! | U29: =+#REF!*'Curvas Futuros'!W29/1000 -> #REF! | W29: 0.16 | Y29: =+'lc2401'!G28 -> 40783 | Z29: =+'lc2402'!G28 -> 18374 | AA29: =+'lc2403'!G28 -> 16647 | AB29: =+'lc2404'!G28 -> 23590 | AC29: =+'lc2405'!G28 -> 10997 | AD29: =+'lc2406'!G28 -> 5521 | AE29: =+'lc2407'!G28 -> 161651 | AF29: =+'lc2408'!G28 -> 7431 | AG29: =+'lc2409'!G28 -> 10785 | AH29: =+'lc2410'!G28 -> 4294 | AI29: =+'lc2411'!G28 -> 7254 | AJ29: =+'lc2412'!G28 -> 0 | AK29: =+'lc2501'!G28 -> 0 | AO29: =+SUM(Y29:AL29) -> 307327 | AP29: =+AO29/AO28-1 -> -0.050208145
B30: 45275 | C30: =+'lc2401'!B29*W30/1000 -> 16.288 | D30: =+'lc2402'!B29*W30/1000 -> 16.152 | E30: =+'lc2403'!B29*W30/1000 -> 16.144 | F30: =+'lc2404'!B29*W30/1000 -> 16.776 | G30: =+'lc2405'!B29*W30/1000 -> 16.768 | H30: =+'lc2406'!B29*W30/1000 -> 16.768 | I30: =+'lc2407'!B29*W30/1000 -> 16.736 | J30: =+'lc2408'!B29*W30/1000 -> 16.848 | K30: =+'lc2409'!B29*W30/1000 -> 16.752 | L30: =+'lc2410'!B29*W30/1000 -> 16.64 | M30: =+'lc2411'!B29*W30/1000 -> 16.552 | N30: =+'lc2412'!B29*W30/1000 -> 16.744 | O30: =+'lc2501'!B29*W30/1000 -> 0 | P30: =+'lc2501'!C29*X30/1000 -> 0 | Q30: 0 | S30: =+AVERAGE(C30:O30) -> 15.320615 | T30: =+#REF!*'Curvas Futuros'!W30/1000 -> #REF! | U30: =+#REF!*'Curvas Futuros'!W30/1000 -> #REF! | W30: 0.16 | Y30: =+'lc2401'!G29 -> 36236 | Z30: =+'lc2402'!G29 -> 18204 | AA30: =+'lc2403'!G29 -> 19115 | AB30: =+'lc2404'!G29 -> 25617 | AC30: =+'lc2405'!G29 -> 11428 | AD30: =+'lc2406'!G29 -> 5583 | AE30: =+'lc2407'!G29 -> 159950 | AF30: =+'lc2408'!G29 -> 7407 | AG30: =+'lc2409'!G29 -> 10446 | AH30: =+'lc2410'!G29 -> 4338 | AI30: =+'lc2411'!G29 -> 7067 | AJ30: =+'lc2412'!G29 -> 70 | AK30: =+'lc2501'!G29 -> 0 | AO30: =+SUM(Y30:AL30) -> 305461 | AP30: =+AO30/AO29-1 -> -0.0060717086
B31: 45278 | C31: =+'lc2401'!B30*W31/1000 -> 16.096 | D31: =+'lc2402'!B30*W31/1000 -> 15.96 | E31: =+'lc2403'!B30*W31/1000 -> 15.96 | F31: =+'lc2404'!B30*W31/1000 -> 16.56 | G31: =+'lc2405'!B30*W31/1000 -> 16.512 | H31: =+'lc2406'!B30*W31/1000 -> 16.44 | I31: =+'lc2407'!B30*W31/1000 -> 16.44 | J31: =+'lc2408'!B30*W31/1000 -> 16.664 | K31: =+'lc2409'!B30*W31/1000 -> 16.592 | L31: =+'lc2410'!B30*W31/1000 -> 16.424 | M31: =+'lc2411'!B30*W31/1000 -> 16.296 | N31: =+'lc2412'!B30*W31/1000 -> 16.4 | O31: =+'lc2501'!B30*W31/1000 -> 0 | P31: =+'lc2501'!C30*X31/1000 -> 0 | Q31: 0 | S31: =+AVERAGE(C31:O31) -> 15.103385 | T31: =+#REF!*'Curvas Futuros'!W31/1000 -> #REF! | U31: =+#REF!*'Curvas Futuros'!W31/1000 -> #REF! | W31: 0.16 | Y31: =+'lc2401'!G30 -> 32722 | Z31: =+'lc2402'!G30 -> 17434 | AA31: =+'lc2403'!G30 -> 19135 | AB31: =+'lc2404'!G30 -> 25079 | AC31: =+'lc2405'!G30 -> 11639 | AD31: =+'lc2406'!G30 -> 5610 | AE31: =+'lc2407'!G30 -> 159746 | AF31: =+'lc2408'!G30 -> 7516 | AG31: =+'lc2409'!G30 -> 10263 | AH31: =+'lc2410'!G30 -> 4205 | AI31: =+'lc2411'!G30 -> 7103 | AJ31: =+'lc2412'!G30 -> 122 | AK31: =+'lc2501'!G30 -> 0 | AO31: =+SUM(Y31:AL31) -> 300574 | AP31: =+AO31/AO30-1 -> -0.015998769
B32: 45279 | C32: =+'lc2401'!B31*W32/1000 -> 15.92 | D32: =+'lc2402'!B31*W32/1000 -> 15.84 | E32: =+'lc2403'!B31*W32/1000 -> 15.856 | F32: =+'lc2404'!B31*W32/1000 -> 16.4 | G32: =+'lc2405'!B31*W32/1000 -> 16.344 | H32: =+'lc2406'!B31*W32/1000 -> 16.32 | I32: =+'lc2407'!B31*W32/1000 -> 16.304 | J32: =+'lc2408'!B31*W32/1000 -> 16.504 | K32: =+'lc2409'!B31*W32/1000 -> 16.4 | L32: =+'lc2410'!B31*W32/1000 -> 16.312 | M32: =+'lc2411'!B31*W32/1000 -> 16.256 | N32: =+'lc2412'!B31*W32/1000 -> 16.216 | O32: =+'lc2501'!B31*W32/1000 -> 0 | P32: =+'lc2501'!C31*X32/1000 -> 0 | Q32: 0 | S32: =+AVERAGE(C32:O32) -> 14.974769 | T32: =+#REF!*'Curvas Futuros'!W32/1000 -> #REF! | U32: =+#REF!*'Curvas Futuros'!W32/1000 -> #REF! | W32: 0.16 | Y32: =+'lc2401'!G31 -> 30452 | Z32: =+'lc2402'!G31 -> 16308 | AA32: =+'lc2403'!G31 -> 18696 | AB32: =+'lc2404'!G31 -> 24580 | AC32: =+'lc2405'!G31 -> 11403 | AD32: =+'lc2406'!G31 -> 5552 | AE32: =+'lc2407'!G31 -> 159563 | AF32: =+'lc2408'!G31 -> 7674 | AG32: =+'lc2409'!G31 -> 10164 | AH32: =+'lc2410'!G31 -> 4185 | AI32: =+'lc2411'!G31 -> 7171 | AJ32: =+'lc2412'!G31 -> 137 | AK32: =+'lc2501'!G31 -> 0 | AO32: =+SUM(Y32:AL32) -> 295885 | AP32: =+AO32/AO31-1 -> -0.015600152
B33: 45280 | C33: =+'lc2401'!B32*W33/1000 -> 15.6 | D33: =+'lc2402'!B32*W33/1000 -> 15.608 | E33: =+'lc2403'!B32*W33/1000 -> 15.68 | F33: =+'lc2404'!B32*W33/1000 -> 16.184 | G33: =+'lc2405'!B32*W33/1000 -> 16.208 | H33: =+'lc2406'!B32*W33/1000 -> 16.176 | I33: =+'lc2407'!B32*W33/1000 -> 16.128 | J33: =+'lc2408'!B32*W33/1000 -> 16.456 | K33: =+'lc2409'!B32*W33/1000 -> 16.376 | L33: =+'lc2410'!B32*W33/1000 -> 16.344 | M33: =+'lc2411'!B32*W33/1000 -> 16.272 | N33: =+'lc2412'!B32*W33/1000 -> 16.224 | O33: =+'lc2501'!B32*W33/1000 -> 0 | P33: =+'lc2501'!C32*X33/1000 -> 0 | Q33: 0 | S33: =+AVERAGE(C33:O33) -> 14.865846 | T33: =+#REF!*'Curvas Futuros'!W33/1000 -> #REF! | U33: =+#REF!*'Curvas Futuros'!W33/1000 -> #REF! | W33: 0.16 | Y33: =+'lc2401'!G32 -> 26757 | Z33: =+'lc2402'!G32 -> 15620 | AA33: =+'lc2403'!G32 -> 18476 | AB33: =+'lc2404'!G32 -> 24470 | AC33: =+'lc2405'!G32 -> 11307 | AD33: =+'lc2406'!G32 -> 5488 | AE33: =+'lc2407'!G32 -> 162654 | AF33: =+'lc2408'!G32 -> 7841 | AG33: =+'lc2409'!G32 -> 10089 | AH33: =+'lc2410'!G32 -> 4214 | AI33: =+'lc2411'!G32 -> 7043 | AJ33: =+'lc2412'!G32 -> 160 | AK33: =+'lc2501'!G32 -> 0 | AO33: =+SUM(Y33:AL33) -> 294119 | AP33: =+AO33/AO32-1 -> -0.0059685351
B34: 45281 | C34: =+'lc2401'!B33*W34/1000 -> 15.096 | D34: =+'lc2402'!B33*W34/1000 -> 15.112 | E34: =+'lc2403'!B33*W34/1000 -> 15.16 | F34: =+'lc2404'!B33*W34/1000 -> 15.72 | G34: =+'lc2405'!B33*W34/1000 -> 15.68 | H34: =+'lc2406'!B33*W34/1000 -> 15.688 | I34: =+'lc2407'!B33*W34/1000 -> 15.616 | J34: =+'lc2408'!B33*W34/1000 -> 16.04 | K34: =+'lc2409'!B33*W34/1000 -> 15.952 | L34: =+'lc2410'!B33*W34/1000 -> 15.912 | M34: =+'lc2411'!B33*W34/1000 -> 15.888 | N34: =+'lc2412'!B33*W34/1000 -> 15.76 | O34: =+'lc2501'!B33*W34/1000 -> 0 | P34: =+'lc2501'!C33*X34/1000 -> 0 | Q34: 0 | S34: =+AVERAGE(C34:O34) -> 14.432615 | T34: =+#REF!*'Curvas Futuros'!W34/1000 -> #REF! | U34: =+#REF!*'Curvas Futuros'!W34/1000 -> #REF! | W34: 0.16 | Y34: =+'lc2401'!G33 -> 24583 | Z34: =+'lc2402'!G33 -> 15099 | AA34: =+'lc2403'!G33 -> 19003 | AB34: =+'lc2404'!G33 -> 24746 | AC34: =+'lc2405'!G33 -> 11508 | AD34: =+'lc2406'!G33 -> 5448 | AE34: =+'lc2407'!G33 -> 158076 | AF34: =+'lc2408'!G33 -> 8132 | AG34: =+'lc2409'!G33 -> 10150 | AH34: =+'lc2410'!G33 -> 4218 | AI34: =+'lc2411'!G33 -> 7249 | AJ34: =+'lc2412'!G33 -> 197 | AK34: =+'lc2501'!G33 -> 0 | AO34: =+SUM(Y34:AL34) -> 288409 | AP34: =+AO34/AO33-1 -> -0.019413911
B35: 45282 | C35: =+'lc2401'!B34*W35/1000 -> 15.44 | D35: =+'lc2402'!B34*W35/1000 -> 15.504 | E35: =+'lc2403'!B34*W35/1000 -> 15.528 | F35: =+'lc2404'!B34*W35/1000 -> 16.176 | G35: =+'lc2405'!B34*W35/1000 -> 16.168 | H35: =+'lc2406'!B34*W35/1000 -> 16.184 | I35: =+'lc2407'!B34*W35/1000 -> 16.128 | J35: =+'lc2408'!B34*W35/1000 -> 16.488 | K35: =+'lc2409'!B34*W35/1000 -> 16.48 | L35: =+'lc2410'!B34*W35/1000 -> 16.32 | M35: =+'lc2411'!B34*W35/1000 -> 16.224 | N35: =+'lc2412'!B34*W35/1000 -> 16.512 | O35: =+'lc2501'!B34*W35/1000 -> 0 | P35: =+'lc2501'!C34*X35/1000 -> 0 | Q35: 0 | S35: =+AVERAGE(C35:O35) -> 14.857846 | W35: 0.16 | Y35: =+'lc2401'!G34 -> 21532 | Z35: =+'lc2402'!G34 -> 15802 | AA35: =+'lc2403'!G34 -> 20661 | AB35: =+'lc2404'!G34 -> 28223 | AC35: =+'lc2405'!G34 -> 11776 | AD35: =+'lc2406'!G34 -> 5387 | AE35: =+'lc2407'!G34 -> 155842 | AF35: =+'lc2408'!G34 -> 8643 | AG35: =+'lc2409'!G34 -> 9902 | AH35: =+'lc2410'!G34 -> 4169 | AI35: =+'lc2411'!G34 -> 7103 | AJ35: =+'lc2412'!G34 -> 216 | AK35: =+'lc2501'!G34 -> 0 | AO35: =+SUM(Y35:AL35) -> 289256 | AP35: =+AO35/AO34-1 -> 0.0029368016
B36: 45285 | C36: =+'lc2401'!B35*W36/1000 -> 15.656 | D36: =+'lc2402'!B35*W36/1000 -> 15.76 | E36: =+'lc2403'!B35*W36/1000 -> 15.792 | F36: =+'lc2404'!B35*W36/1000 -> 16.464 | G36: =+'lc2405'!B35*W36/1000 -> 16.504 | H36: =+'lc2406'!B35*W36/1000 -> 16.48 | I36: =+'lc2407'!B35*W36/1000 -> 16.456 | J36: =+'lc2408'!B35*W36/1000 -> 16.776 | K36: =+'lc2409'!B35*W36/1000 -> 16.696 | L36: =+'lc2410'!B35*W36/1000 -> 16.584 | M36: =+'lc2411'!B35*W36/1000 -> 16.472 | N36: =+'lc2412'!B35*W36/1000 -> 16.712 | O36: =+'lc2501'!B35*W36/1000 -> 0 | P36: =+'lc2501'!C35*X36/1000 -> 0 | Q36: 0 | S36: =+AVERAGE(C36:O36) -> 15.104 | W36: 0.16 | Y36: =+'lc2401'!G35 -> 19970 | Z36: =+'lc2402'!G35 -> 15931 | AA36: =+'lc2403'!G35 -> 22201 | AB36: =+'lc2404'!G35 -> 28995 | AC36: =+'lc2405'!G35 -> 11739 | AD36: =+'lc2406'!G35 -> 5440 | AE36: =+'lc2407'!G35 -> 159077 | AF36: =+'lc2408'!G35 -> 8610 | AG36: =+'lc2409'!G35 -> 9669 | AH36: =+'lc2410'!G35 -> 4122 | AI36: =+'lc2411'!G35 -> 6851 | AJ36: =+'lc2412'!G35 -> 209 | AK36: =+'lc2501'!G35 -> 0 | AO36: =+SUM(Y36:AL36) -> 292814 | AP36: =+AO36/AO35-1 -> 0.012300523
B37: 45286 | C37: =+'lc2401'!B36*W37/1000 -> 16.432 | D37: =+'lc2402'!B36*W37/1000 -> 16.48 | E37: =+'lc2403'!B36*W37/1000 -> 16.576 | F37: =+'lc2404'!B36*W37/1000 -> 17.152 | G37: =+'lc2405'!B36*W37/1000 -> 17.096 | H37: =+'lc2406'!B36*W37/1000 -> 17.168 | I37: =+'lc2407'!B36*W37/1000 -> 17.136 | J37: =+'lc2408'!B36*W37/1000 -> 17.344 | K37: =+'lc2409'!B36*W37/1000 -> 17.256 | L37: =+'lc2410'!B36*W37/1000 -> 17.088 | M37: =+'lc2411'!B36*W37/1000 -> 17 | N37: =+'lc2412'!B36*W37/1000 -> 17.216 | O37: =+'lc2501'!B36*W37/1000 -> 0 | P37: =+'lc2501'!C36*X37/1000 -> 0 | Q37: 0 | S37: =+AVERAGE(C37:O37) -> 15.688 | W37: 0.16 | Y37: =+'lc2401'!G36 -> 17115 | Z37: =+'lc2402'!G36 -> 15024 | AA37: =+'lc2403'!G36 -> 21176 | AB37: =+'lc2404'!G36 -> 28863 | AC37: =+'lc2405'!G36 -> 12787 | AD37: =+'lc2406'!G36 -> 6300 | AE37: =+'lc2407'!G36 -> 155209 | AF37: =+'lc2408'!G36 -> 8489 | AG37: =+'lc2409'!G36 -> 9161 | AH37: =+'lc2410'!G36 -> 4077 | AI37: =+'lc2411'!G36 -> 6612 | AJ37: =+'lc2412'!G36 -> 275 | AK37: =+'lc2501'!G36 -> 0 | AO37: =+SUM(Y37:AL37) -> 285088 | AP37: =+AO37/AO36-1 -> -0.02638535
B38: 45287 | C38: =+'lc2401'!B37*W38/1000 -> 16.256 | D38: =+'lc2402'!B37*W38/1000 -> 16.304 | E38: =+'lc2403'!B37*W38/1000 -> 16.336 | F38: =+'lc2404'!B37*W38/1000 -> 16.904 | G38: =+'lc2405'!B37*W38/1000 -> 16.864 | H38: =+'lc2406'!B37*W38/1000 -> 16.936 | I38: =+'lc2407'!B37*W38/1000 -> 16.912 | J38: =+'lc2408'!B37*W38/1000 -> 17.184 | K38: =+'lc2409'!B37*W38/1000 -> 17.168 | L38: =+'lc2410'!B37*W38/1000 -> 17 | M38: =+'lc2411'!B37*W38/1000 -> 16.976 | N38: =+'lc2412'!B37*W38/1000 -> 17.224 | O38: =+'lc2501'!B37*W38/1000 -> 0 | P38: =+'lc2501'!C37*X38/1000 -> 0 | Q38: 0 | S38: =+AVERAGE(C38:O38) -> 15.543385 | W38: 0.16 | Y38: =+'lc2401'!G37 -> 14190 | Z38: =+'lc2402'!G37 -> 14291 | AA38: =+'lc2403'!G37 -> 21009 | AB38: =+'lc2404'!G37 -> 29652 | AC38: =+'lc2405'!G37 -> 13450 | AD38: =+'lc2406'!G37 -> 6359 | AE38: =+'lc2407'!G37 -> 150793 | AF38: =+'lc2408'!G37 -> 8574 | AG38: =+'lc2409'!G37 -> 9070 | AH38: =+'lc2410'!G37 -> 4107 | AI38: =+'lc2411'!G37 -> 6452 | AJ38: =+'lc2412'!G37 -> 259 | AK38: =+'lc2501'!G37 -> 0 | AO38: =+SUM(Y38:AL38) -> 278206 | AP38: =+AO38/AO37-1 -> -0.024139915
B39: 45288 | C39: =+'lc2401'!B38*W39/1000 -> 16.192 | D39: =+'lc2402'!B38*W39/1000 -> 16.256 | E39: =+'lc2403'!B38*W39/1000 -> 16.352 | F39: =+'lc2404'!B38*W39/1000 -> 17 | G39: =+'lc2405'!B38*W39/1000 -> 17 | H39: =+'lc2406'!B38*W39/1000 -> 17.056 | I39: =+'lc2407'!B38*W39/1000 -> 17.048 | J39: =+'lc2408'!B38*W39/1000 -> 17.424 | K39: =+'lc2409'!B38*W39/1000 -> 17.272 | L39: =+'lc2410'!B38*W39/1000 -> 17.224 | M39: =+'lc2411'!B38*W39/1000 -> 17.224 | N39: =+'lc2412'!B38*W39/1000 -> 17.376 | O39: =+'lc2501'!B38*W39/1000 -> 0 | P39: =+'lc2501'!C38*X39/1000 -> 0 | Q39: 0 | S39: =+AVERAGE(C39:O39) -> 15.648 | W39: 0.16 | Y39: =+'lc2401'!G38 -> 13033 | Z39: =+'lc2402'!G38 -> 14530 | AA39: =+'lc2403'!G38 -> 21913 | AB39: =+'lc2404'!G38 -> 30141 | AC39: =+'lc2405'!G38 -> 13459 | AD39: =+'lc2406'!G38 -> 6411 | AE39: =+'lc2407'!G38 -> 152061 | AF39: =+'lc2408'!G38 -> 8656 | AG39: =+'lc2409'!G38 -> 9035 | AH39: =+'lc2410'!G38 -> 4109 | AI39: =+'lc2411'!G38 -> 6434 | AJ39: =+'lc2412'!G38 -> 260 | AK39: =+'lc2501'!G38 -> 0 | AO39: =+SUM(Y39:AL39) -> 280042 | AP39: =+AO39/AO38-1 -> 0.0065994263
B40: 45289 | C40: =+'lc2401'!B39*W40/1000 -> 16.176 | D40: =+'lc2402'!B39*W40/1000 -> 16.264 | E40: =+'lc2403'!B39*W40/1000 -> 16.376 | F40: =+'lc2404'!B39*W40/1000 -> 17.152 | G40: =+'lc2405'!B39*W40/1000 -> 17.136 | H40: =+'lc2406'!B39*W40/1000 -> 17.16 | I40: =+'lc2407'!B39*W40/1000 -> 17.232 | J40: =+'lc2408'!B39*W40/1000 -> 17.504 | K40: =+'lc2409'!B39*W40/1000 -> 17.416 | L40: =+'lc2410'!B39*W40/1000 -> 17.272 | M40: =+'lc2411'!B39*W40/1000 -> 17.176 | N40: =+'lc2412'!B39*W40/1000 -> 17.6 | O40: =+'lc2501'!B39*W40/1000 -> 0 | P40: =+'lc2501'!C39*X40/1000 -> 0 | Q40: 0 | S40: =+AVERAGE(C40:O40) -> 15.728 | W40: 0.16 | Y40: =+'lc2401'!G39 -> 11852 | Z40: =+'lc2402'!G39 -> 14973 | AA40: =+'lc2403'!G39 -> 23839 | AB40: =+'lc2404'!G39 -> 33648 | AC40: =+'lc2405'!G39 -> 13685 | AD40: =+'lc2406'!G39 -> 6621 | AE40: =+'lc2407'!G39 -> 142958 | AF40: =+'lc2408'!G39 -> 8526 | AG40: =+'lc2409'!G39 -> 8780 | AH40: =+'lc2410'!G39 -> 4102 | AI40: =+'lc2411'!G39 -> 6364 | AJ40: =+'lc2412'!G39 -> 260 | AK40: =+'lc2501'!G39 -> 0 | AO40: =+SUM(Y40:AL40) -> 275608 | AP40: =+AO40/AO39-1 -> -0.015833339
B41: 45293 | C41: =+'lc2401'!B40*W41/1000 -> 16.392 | D41: =+'lc2402'!B40*W41/1000 -> 16.456 | E41: =+'lc2403'!B40*W41/1000 -> 16.56 | F41: =+'lc2404'!B40*W41/1000 -> 17.224 | G41: =+'lc2405'!B40*W41/1000 -> 17.272 | H41: =+'lc2406'!B40*W41/1000 -> 17.32 | I41: =+'lc2407'!B40*W41/1000 -> 17.336 | J41: =+'lc2408'!B40*W41/1000 -> 17.664 | K41: =+'lc2409'!B40*W41/1000 -> 17.568 | L41: =+'lc2410'!B40*W41/1000 -> 17.456 | M41: =+'lc2411'!B40*W41/1000 -> 17.336 | N41: =+'lc2412'!B40*W41/1000 -> 17.632 | O41: =+'lc2501'!B40*W41/1000 -> 0 | P41: =+'lc2501'!C40*X41/1000 -> 0 | Q41: 0 | S41: =+AVERAGE(C41:O41) -> 15.862769 | W41: 0.16 | Y41: =+'lc2401'!G40 -> 10143 | Z41: =+'lc2402'!G40 -> 14375 | AA41: =+'lc2403'!G40 -> 22409 | AB41: =+'lc2404'!G40 -> 31697 | AC41: =+'lc2405'!G40 -> 11830 | AD41: =+'lc2406'!G40 -> 6125 | AE41: =+'lc2407'!G40 -> 145602 | AF41: =+'lc2408'!G40 -> 8570 | AG41: =+'lc2409'!G40 -> 8620 | AH41: =+'lc2410'!G40 -> 4088 | AI41: =+'lc2411'!G40 -> 6269 | AJ41: =+'lc2412'!G40 -> 283 | AK41: =+'lc2501'!G40 -> 0 | AO41: =+SUM(Y41:AL41) -> 270011 | AP41: =+AO41/AO40-1 -> -0.020307829
B42: 45294 | C42: =+'lc2401'!B41*W42/1000 -> 16.416 | D42: =+'lc2402'!B41*W42/1000 -> 16.328 | E42: =+'lc2403'!B41*W42/1000 -> 16.376 | F42: =+'lc2404'!B41*W42/1000 -> 16.992 | G42: =+'lc2405'!B41*W42/1000 -> 16.968 | H42: =+'lc2406'!B41*W42/1000 -> 17.056 | I42: =+'lc2407'!B41*W42/1000 -> 17.056 | J42: =+'lc2408'!B41*W42/1000 -> 17.384 | K42: =+'lc2409'!B41*W42/1000 -> 17.312 | L42: =+'lc2410'!B41*W42/1000 -> 17.144 | M42: =+'lc2411'!B41*W42/1000 -> 17.112 | N42: =+'lc2412'!B41*W42/1000 -> 17.328 | O42: =+'lc2501'!B41*W42/1000 -> 0 | P42: =+'lc2501'!C41*X42/1000 -> 0 | Q42: 0 | S42: =+AVERAGE(C42:O42) -> 15.651692 | W42: 0.16 | Y42: =+'lc2401'!G41 -> 7370 | Z42: =+'lc2402'!G41 -> 13850 | AA42: =+'lc2403'!G41 -> 21900 | AB42: =+'lc2404'!G41 -> 31634 | AC42: =+'lc2405'!G41 -> 11654 | AD42: =+'lc2406'!G41 -> 6158 | AE42: =+'lc2407'!G41 -> 141743 | AF42: =+'lc2408'!G41 -> 8551 | AG42: =+'lc2409'!G41 -> 8575 | AH42: =+'lc2410'!G41 -> 4070 | AI42: =+'lc2411'!G41 -> 6277 | AJ42: =+'lc2412'!G41 -> 306 | AK42: =+'lc2501'!G41 -> 0 | AO42: =+SUM(Y42:AL42) -> 262088 | AP42: =+AO42/AO41-1 -> -0.029343249
B43: 45295 | C43: =+'lc2401'!B42*W43/1000 -> 15.384 | D43: =+'lc2402'!B42*W43/1000 -> 15.496 | E43: =+'lc2403'!B42*W43/1000 -> 15.568 | F43: =+'lc2404'!B42*W43/1000 -> 16.08 | G43: =+'lc2405'!B42*W43/1000 -> 16.08 | H43: =+'lc2406'!B42*W43/1000 -> 15.896 | I43: =+'lc2407'!B42*W43/1000 -> 16.072 | J43: =+'lc2408'!B42*W43/1000 -> 16.48 | K43: =+'lc2409'!B42*W43/1000 -> 16.416 | L43: =+'lc2410'!B42*W43/1000 -> 16.272 | M43: =+'lc2411'!B42*W43/1000 -> 16.264 | N43: =+'lc2412'!B42*W43/1000 -> 16.424 | O43: =+'lc2501'!B42*W43/1000 -> 0 | P43: =+'lc2501'!C42*X43/1000 -> 0 | Q43: 0 | S43: =+AVERAGE(C43:O43) -> 14.802462 | W43: 0.16 | Y43: =+'lc2401'!G42 -> 6519 | Z43: =+'lc2402'!G42 -> 12917 | AA43: =+'lc2403'!G42 -> 20332 | AB43: =+'lc2404'!G42 -> 29473 | AC43: =+'lc2405'!G42 -> 11210 | AD43: =+'lc2406'!G42 -> 6089 | AE43: =+'lc2407'!G42 -> 148982 | AF43: =+'lc2408'!G42 -> 8428 | AG43: =+'lc2409'!G42 -> 8500 | AH43: =+'lc2410'!G42 -> 4084 | AI43: =+'lc2411'!G42 -> 6486 | AJ43: =+'lc2412'!G42 -> 412 | AK43: =+'lc2501'!G42 -> 0 | AO43: =+SUM(Y43:AL43) -> 263432 | AP43: =+AO43/AO42-1 -> 0.0051280486
B44: 45296 | C44: =+'lc2401'!B43*W44/1000 -> 14.96 | D44: =+'lc2402'!B43*W44/1000 -> 14.992 | E44: =+'lc2403'!B43*W44/1000 -> 15.072 | F44: =+'lc2404'!B43*W44/1000 -> 15.76 | G44: =+'lc2405'!B43*W44/1000 -> 15.744 | H44: =+'lc2406'!B43*W44/1000 -> 15.904 | I44: =+'lc2407'!B43*W44/1000 -> 15.784 | J44: =+'lc2408'!B43*W44/1000 -> 16.248 | K44: =+'lc2409'!B43*W44/1000 -> 16.184 | L44: =+'lc2410'!B43*W44/1000 -> 16.16 | M44: =+'lc2411'!B43*W44/1000 -> 16.08 | N44: =+'lc2412'!B43*W44/1000 -> 16.112 | O44: =+'lc2501'!B43*W44/1000 -> 0 | P44: =+'lc2501'!C43*X44/1000 -> 0 | Q44: 0 | S44: =+AVERAGE(C44:O44) -> 14.538462 | W44: 0.16 | Y44: =+'lc2401'!G43 -> 4831 | Z44: =+'lc2402'!G43 -> 11782 | AA44: =+'lc2403'!G43 -> 19658 | AB44: =+'lc2404'!G43 -> 28050 | AC44: =+'lc2405'!G43 -> 10736 | AD44: =+'lc2406'!G43 -> 6040 | AE44: =+'lc2407'!G43 -> 154263 | AF44: =+'lc2408'!G43 -> 8380 | AG44: =+'lc2409'!G43 -> 8522 | AH44: =+'lc2410'!G43 -> 4199 | AI44: =+'lc2411'!G43 -> 6695 | AJ44: =+'lc2412'!G43 -> 421 | AK44: =+'lc2501'!G43 -> 0 | AO44: =+SUM(Y44:AL44) -> 263577 | AP44: =+AO44/AO43-1 -> 0.00055042668
B45: 45299 | C45: =+'lc2401'!B44*W45/1000 -> 14.624 | D45: =+'lc2402'!B44*W45/1000 -> 14.688 | E45: =+'lc2403'!B44*W45/1000 -> 14.752 | F45: =+'lc2404'!B44*W45/1000 -> 15.424 | G45: =+'lc2405'!B44*W45/1000 -> 15.448 | H45: =+'lc2406'!B44*W45/1000 -> 15.512 | I45: =+'lc2407'!B44*W45/1000 -> 15.552 | J45: =+'lc2408'!B44*W45/1000 -> 15.992 | K45: =+'lc2409'!B44*W45/1000 -> 15.864 | L45: =+'lc2410'!B44*W45/1000 -> 15.768 | M45: =+'lc2411'!B44*W45/1000 -> 15.784 | N45: =+'lc2412'!B44*W45/1000 -> 15.904 | O45: =+'lc2501'!B44*W45/1000 -> 0 | P45: =+'lc2501'!C44*X45/1000 -> 0 | Q45: 0 | S45: =+AVERAGE(C45:O45) -> 14.254769 | W45: 0.16 | Y45: =+'lc2401'!G44 -> 3097 | Z45: =+'lc2402'!G44 -> 11843 | AA45: =+'lc2403'!G44 -> 20615 | AB45: =+'lc2404'!G44 -> 31041 | AC45: =+'lc2405'!G44 -> 11073 | AD45: =+'lc2406'!G44 -> 6124 | AE45: =+'lc2407'!G44 -> 157724 | AF45: =+'lc2408'!G44 -> 8410 | AG45: =+'lc2409'!G44 -> 8478 | AH45: =+'lc2410'!G44 -> 4164 | AI45: =+'lc2411'!G44 -> 6914 | AJ45: =+'lc2412'!G44 -> 428 | AK45: =+'lc2501'!G44 -> 0 | AO45: =+SUM(Y45:AL45) -> 269911 | AP45: =+AO45/AO44-1 -> 0.024030928
B46: 45300 | C46: =+'lc2401'!B45*W46/1000 -> 15.072 | D46: =+'lc2402'!B45*W46/1000 -> 14.984 | E46: =+'lc2403'!B45*W46/1000 -> 15.024 | F46: =+'lc2404'!B45*W46/1000 -> 15.728 | G46: =+'lc2405'!B45*W46/1000 -> 15.744 | H46: =+'lc2406'!B45*W46/1000 -> 15.8 | I46: =+'lc2407'!B45*W46/1000 -> 15.832 | J46: =+'lc2408'!B45*W46/1000 -> 16.056 | K46: =+'lc2409'!B45*W46/1000 -> 16.016 | L46: =+'lc2410'!B45*W46/1000 -> 15.912 | M46: =+'lc2411'!B45*W46/1000 -> 15.864 | N46: =+'lc2412'!B45*W46/1000 -> 16.04 | O46: =+'lc2501'!B45*W46/1000 -> 0 | P46: =+'lc2501'!C45*X46/1000 -> 0 | Q46: 0 | S46: =+AVERAGE(C46:O46) -> 14.467077 | W46: 0.16 | Y46: =+'lc2401'!G45 -> 2565 | Z46: =+'lc2402'!G45 -> 9956 | AA46: =+'lc2403'!G45 -> 21067 | AB46: =+'lc2404'!G45 -> 33938 | AC46: =+'lc2405'!G45 -> 11179 | AD46: =+'lc2406'!G45 -> 5936 | AE46: =+'lc2407'!G45 -> 162038 | AF46: =+'lc2408'!G45 -> 8890 | AG46: =+'lc2409'!G45 -> 8293 | AH46: =+'lc2410'!G45 -> 4109 | AI46: =+'lc2411'!G45 -> 6735 | AJ46: =+'lc2412'!G45 -> 453 | AK46: =+'lc2501'!G45 -> 0 | AO46: =+SUM(Y46:AL46) -> 275159 | AP46: =+AO46/AO45-1 -> 0.019443446
... B51: 45307 | C51: =+'lc2401'!B50*W51/1000 -> 0 | D51: =+'lc2402'!B50*W51/1000 -> 15.744 | E51: =+'lc2403'!B50*W51/1000 -> 15.832 | F51: =+'lc2404'!B50*W51/1000 -> 16.496 | G51: =+'lc2405'!B50*W51/1000 -> 16.56 | H51: =+'lc2406'!B50*W51/1000 -> 16.576 | I51: =+'lc2407'!B50*W51/1000 -> 16.664 | J51: =+'lc2408'!B50*W51/1000 -> 16.824 | K51: =+'lc2409'!B50*W51/1000 -> 16.816 | L51: =+'lc2410'!B50*W51/1000 -> 16.72 | M51: =+'lc2411'!B50*W51/1000 -> 16.704 | N51: =+'lc2412'!B50*W51/1000 -> 16.864 | O51: =+'lc2501'!B50*W51/1000 -> 16.896 | P51: =+'lc2501'!C50*X51/1000 -> 0 | Q51: 0 | S51: =+AVERAGE(C51:O51) -> 15.284308 | W51: 0.16 | Y51: =+'lc2401'!G50 -> 0 | Z51: =+'lc2402'!G50 -> 8362 | AA51: =+'lc2403'!G50 -> 19141 | AB51: =+'lc2404'!G50 -> 37852 | AC51: =+'lc2405'!G50 -> 11499 | AD51: =+'lc2406'!G50 -> 6084 | AE51: =+'lc2407'!G50 -> 159478 | AF51: =+'lc2408'!G50 -> 9707 | AG51: =+'lc2409'!G50 -> 8055 | AH51: =+'lc2410'!G50 -> 4118 | AI51: =+'lc2411'!G50 -> 6501 | AJ51: =+'lc2412'!G50 -> 527 | AK51: =+'lc2501'!G50 -> 26 | AO51: =+SUM(Y51:AL51) -> 271350 | AP51: =+AO51/AO50-1 -> 0.018531378
B52: 45308 | D52: =+'lc2402'!B51*W52/1000 -> 15.52 | E52: =+'lc2403'!B51*W52/1000 -> 15.552 | F52: =+'lc2404'!B51*W52/1000 -> 16.208 | G52: =+'lc2405'!B51*W52/1000 -> 16.24 | H52: =+'lc2406'!B51*W52/1000 -> 16.272 | I52: =+'lc2407'!B51*W52/1000 -> 16.28 | J52: =+'lc2408'!B51*W52/1000 -> 16.536 | K52: =+'lc2409'!B51*W52/1000 -> 16.48 | L52: =+'lc2410'!B51*W52/1000 -> 16.432 | M52: =+'lc2411'!B51*W52/1000 -> 16.424 | N52: =+'lc2412'!B51*W52/1000 -> 16.6 | O52: =+'lc2501'!B51*W52/1000 -> 16.608 | P52: =+'lc2501'!C51*X52/1000 -> 0 | Q52: 0 | S52: =+AVERAGE(C52:O52) -> 16.262667 | W52: 0.16 | Z52: =+'lc2402'!G51 -> 8217 | AA52: =+'lc2403'!G51 -> 18585 | AB52: =+'lc2404'!G51 -> 37745 | AC52: =+'lc2405'!G51 -> 11342 | AD52: =+'lc2406'!G51 -> 6160 | AE52: =+'lc2407'!G51 -> 156573 | AF52: =+'lc2408'!G51 -> 9784 | AG52: =+'lc2409'!G51 -> 8084 | AH52: =+'lc2410'!G51 -> 4177 | AI52: =+'lc2411'!G51 -> 6627 | AJ52: =+'lc2412'!G51 -> 599 | AK52: =+'lc2501'!G51 -> 56 | AO52: =+SUM(Y52:AL52) -> 267949 | AP52: =+AO52/AO51-1 -> -0.012533628
B53: 45309 | D53: =+'lc2402'!B52*W53/1000 -> 15.608 | E53: =+'lc2403'!B52*W53/1000 -> 15.608 | F53: =+'lc2404'!B52*W53/1000 -> 16.24 | G53: =+'lc2405'!B52*W53/1000 -> 16.28 | H53: =+'lc2406'!B52*W53/1000 -> 16.296 | I53: =+'lc2407'!B52*W53/1000 -> 16.384 | J53: =+'lc2408'!B52*W53/1000 -> 16.552 | K53: =+'lc2409'!B52*W53/1000 -> 16.512 | L53: =+'lc2410'!B52*W53/1000 -> 16.488 | M53: =+'lc2411'!B52*W53/1000 -> 16.456 | N53: =+'lc2412'!B52*W53/1000 -> 16.656 | O53: =+'lc2501'!B52*W53/1000 -> 16.672 | P53: =+'lc2501'!C52*X53/1000 -> 0 | Q53: 0 | S53: =+AVERAGE(C53:O53) -> 16.312667 | W53: 0.16 | Z53: =+'lc2402'!G52 -> 7725 | AA53: =+'lc2403'!G52 -> 17723 | AB53: =+'lc2404'!G52 -> 38260 | AC53: =+'lc2405'!G52 -> 11525 | AD53: =+'lc2406'!G52 -> 6150 | AE53: =+'lc2407'!G52 -> 154594 | AF53: =+'lc2408'!G52 -> 9740 | AG53: =+'lc2409'!G52 -> 7964 | AH53: =+'lc2410'!G52 -> 4158 | AI53: =+'lc2411'!G52 -> 6651 | AJ53: =+'lc2412'!G52 -> 603 | AK53: =+'lc2501'!G52 -> 62 | AO53: =+SUM(Y53:AL53) -> 265155 | AP53: =+AO53/AO52-1 -> -0.010427357
B54: 45310 | D54: =+'lc2402'!B53*W54/1000 -> 15.44 | E54: =+'lc2403'!B53*W54/1000 -> 15.504 | F54: =+'lc2404'!B53*W54/1000 -> 16.128 | G54: =+'lc2405'!B53*W54/1000 -> 16.152 | H54: =+'lc2406'!B53*W54/1000 -> 16.216 | I54: =+'lc2407'!B53*W54/1000 -> 16.224 | J54: =+'lc2408'!B53*W54/1000 -> 16.472 | K54: =+'lc2409'!B53*W54/1000 -> 16.432 | L54: =+'lc2410'!B53*W54/1000 -> 16.376 | M54: =+'lc2411'!B53*W54/1000 -> 16.352 | N54: =+'lc2412'!B53*W54/1000 -> 16.496 | O54: =+'lc2501'!B53*W54/1000 -> 16.488 | P54: =+'lc2501'!C53*X54/1000 -> 0 | Q54: 0 | S54: =+AVERAGE(C54:O54) -> 16.19 | W54: 0.16 | Z54: =+'lc2402'!G53 -> 7553 | AA54: =+'lc2403'!G53 -> 17277 | AB54: =+'lc2404'!G53 -> 37825 | AC54: =+'lc2405'!G53 -> 11357 | AD54: =+'lc2406'!G53 -> 6135 | AE54: =+'lc2407'!G53 -> 155078 | AF54: =+'lc2408'!G53 -> 9805 | AG54: =+'lc2409'!G53 -> 7952 | AH54: =+'lc2410'!G53 -> 4174 | AI54: =+'lc2411'!G53 -> 6732 | AJ54: =+'lc2412'!G53 -> 611 | AK54: =+'lc2501'!G53 -> 68 | AO54: =+SUM(Y54:AL54) -> 264567 | AP54: =+AO54/AO53-1 -> -0.0022175709
B55: 45313 | D55: =+'lc2402'!B54*W55/1000 -> 15.2 | E55: =+'lc2403'!B54*W55/1000 -> 15.232 | F55: =+'lc2404'!B54*W55/1000 -> 15.84 | G55: =+'lc2405'!B54*W55/1000 -> 15.872 | H55: =+'lc2406'!B54*W55/1000 -> 15.976 | I55: =+'lc2407'!B54*W55/1000 -> 15.976 | J55: =+'lc2408'!B54*W55/1000 -> 16.256 | K55: =+'lc2409'!B54*W55/1000 -> 16.28 | L55: =+'lc2410'!B54*W55/1000 -> 16.184 | M55: =+'lc2411'!B54*W55/1000 -> 16.12 | N55: =+'lc2412'!B54*W55/1000 -> 16.224 | O55: =+'lc2501'!B54*W55/1000 -> 16.312 | P55: =+'lc2501'!C54*X55/1000 -> 0 | Q55: 0 | S55: =+AVERAGE(C55:O55) -> 15.956 | W55: 0.16 | Z55: =+'lc2402'!G54 -> 7188 | AA55: =+'lc2403'!G54 -> 16033 | AB55: =+'lc2404'!G54 -> 36090 | AC55: =+'lc2405'!G54 -> 11159 | AD55: =+'lc2406'!G54 -> 6142 | AE55: =+'lc2407'!G54 -> 152252 | AF55: =+'lc2408'!G54 -> 9776 | AG55: =+'lc2409'!G54 -> 8022 | AH55: =+'lc2410'!G54 -> 4107 | AI55: =+'lc2411'!G54 -> 6741 | AJ55: =+'lc2412'!G54 -> 614 | AK55: =+'lc2501'!G54 -> 87 | AO55: =+SUM(Y55:AL55) -> 258211 | AP55: =+AO55/AO54-1 -> -0.02402416
B56: 45314 | D56: =+'lc2402'!B55*W56/1000 -> 15.6 | E56: =+'lc2403'!B55*W56/1000 -> 15.68 | F56: =+'lc2404'!B55*W56/1000 -> 16.208 | G56: =+'lc2405'!B55*W56/1000 -> 16.256 | H56: =+'lc2406'!B55*W56/1000 -> 16.264 | I56: =+'lc2407'!B55*W56/1000 -> 16.32 | J56: =+'lc2408'!B55*W56/1000 -> 16.568 | K56: =+'lc2409'!B55*W56/1000 -> 16.536 | L56: =+'lc2410'!B55*W56/1000 -> 16.48 | M56: =+'lc2411'!B55*W56/1000 -> 16.488 | N56: =+'lc2412'!B55*W56/1000 -> 16.544 | O56: =+'lc2501'!B55*W56/1000 -> 16.552 | P56: =+'lc2501'!C55*X56/1000 -> 0 | Q56: 0 | S56: =+AVERAGE(C56:O56) -> 16.291333 | W56: 0.16 | Z56: =+'lc2402'!G55 -> 7057 | AA56: =+'lc2403'!G55 -> 16079 | AB56: =+'lc2404'!G55 -> 36259 | AC56: =+'lc2405'!G55 -> 11333 | AD56: =+'lc2406'!G55 -> 6141 | AE56: =+'lc2407'!G55 -> 148288 | AF56: =+'lc2408'!G55 -> 9703 | AG56: =+'lc2409'!G55 -> 7818 | AH56: =+'lc2410'!G55 -> 4094 | AI56: =+'lc2411'!G55 -> 6788 | AJ56: =+'lc2412'!G55 -> 622 | AK56: =+'lc2501'!G55 -> 94 | AO56: =+SUM(Y56:AL56) -> 254276 | AP56: =+AO56/AO55-1 -> -0.015239475
B57: 45315 | D57: =+'lc2402'!B56*W57/1000 -> 15.624 | E57: =+'lc2403'!B56*W57/1000 -> 15.664 | F57: =+'lc2404'!B56*W57/1000 -> 16.248 | G57: =+'lc2405'!B56*W57/1000 -> 16.256 | H57: =+'lc2406'!B56*W57/1000 -> 16.344 | I57: =+'lc2407'!B56*W57/1000 -> 16.376 | J57: =+'lc2408'!B56*W57/1000 -> 16.592 | K57: =+'lc2409'!B56*W57/1000 -> 16.64 | L57: =+'lc2410'!B56*W57/1000 -> 16.6 | M57: =+'lc2411'!B56*W57/1000 -> 16.6 | N57: =+'lc2412'!B56*W57/1000 -> 16.728 | O57: =+'lc2501'!B56*W57/1000 -> 16.672 | P57: =+'lc2501'!C56*X57/1000 -> 0 | Q57: 0 | S57: =+AVERAGE(C57:O57) -> 16.362 | W57: 0.16 | Z57: =+'lc2402'!G56 -> 6548 | AA57: =+'lc2403'!G56 -> 15988 | AB57: =+'lc2404'!G56 -> 38056 | AC57: =+'lc2405'!G56 -> 11894 | AD57: =+'lc2406'!G56 -> 6205 | AE57: =+'lc2407'!G56 -> 148399 | AF57: =+'lc2408'!G56 -> 9641 | AG57: =+'lc2409'!G56 -> 7854 | AH57: =+'lc2410'!G56 -> 4121 | AI57: =+'lc2411'!G56 -> 6898 | AJ57: =+'lc2412'!G56 -> 637 | AK57: =+'lc2501'!G56 -> 110 | AO57: =+SUM(Y57:AL57) -> 256351 | AP57: =+AO57/AO56-1 -> 0.0081604241
B58: 45316 | D58: =+'lc2402'!B57*W58/1000 -> 15.584 | E58: =+'lc2403'!B57*W58/1000 -> 15.568 | F58: =+'lc2404'!B57*W58/1000 -> 16.072 | G58: =+'lc2405'!B57*W58/1000 -> 16.12 | H58: =+'lc2406'!B57*W58/1000 -> 16.128 | I58: =+'lc2407'!B57*W58/1000 -> 16.216 | J58: =+'lc2408'!B57*W58/1000 -> 16.536 | K58: =+'lc2409'!B57*W58/1000 -> 16.456 | L58: =+'lc2410'!B57*W58/1000 -> 16.432 | M58: =+'lc2411'!B57*W58/1000 -> 16.424 | N58: =+'lc2412'!B57*W58/1000 -> 16.544 | O58: =+'lc2501'!B57*W58/1000 -> 16.472 | P58: =+'lc2501'!C57*X58/1000 -> 0 | Q58: 0 | S58: =+AVERAGE(C58:O58) -> 16.212667 | W58: 0.16 | Z58: =+'lc2402'!G57 -> 6291 | AA58: =+'lc2403'!G57 -> 15832 | AB58: =+'lc2404'!G57 -> 37748 | AC58: =+'lc2405'!G57 -> 12400 | AD58: =+'lc2406'!G57 -> 6264 | AE58: =+'lc2407'!G57 -> 149167 | AF58: =+'lc2408'!G57 -> 9639 | AG58: =+'lc2409'!G57 -> 7875 | AH58: =+'lc2410'!G57 -> 4134 | AI58: =+'lc2411'!G57 -> 7016 | AJ58: =+'lc2412'!G57 -> 665 | AK58: =+'lc2501'!G57 -> 112 | AO58: =+SUM(Y58:AL58) -> 257143 | AP58: =+AO58/AO57-1 -> 0.003089514
B59: 45317 | D59: =+'lc2402'!B58*W59/1000 -> 15.44 | E59: =+'lc2403'!B58*W59/1000 -> 15.48 | F59: =+'lc2404'!B58*W59/1000 -> 15.976 | G59: =+'lc2405'!B58*W59/1000 -> 16.016 | H59: =+'lc2406'!B58*W59/1000 -> 16.016 | I59: =+'lc2407'!B58*W59/1000 -> 16.104 | J59: =+'lc2408'!B58*W59/1000 -> 16.416 | K59: =+'lc2409'!B58*W59/1000 -> 16.408 | L59: =+'lc2410'!B58*W59/1000 -> 16.312 | M59: =+'lc2411'!B58*W59/1000 -> 16.368 | N59: =+'lc2412'!B58*W59/1000 -> 16.568 | O59: =+'lc2501'!B58*W59/1000 -> 16.56 | P59: =+'lc2501'!C58*X59/1000 -> 0 | Q59: 0 | S59: =+AVERAGE(C59:O59) -> 16.138667 | W59: 0.16 | Z59: =+'lc2402'!G58 -> 6112 | AA59: =+'lc2403'!G58 -> 15665 | AB59: =+'lc2404'!G58 -> 37577 | AC59: =+'lc2405'!G58 -> 12461 | AD59: =+'lc2406'!G58 -> 6279 | AE59: =+'lc2407'!G58 -> 148248 | AF59: =+'lc2408'!G58 -> 9573 | AG59: =+'lc2409'!G58 -> 7787 | AH59: =+'lc2410'!G58 -> 4139 | AI59: =+'lc2411'!G58 -> 7078 | AJ59: =+'lc2412'!G58 -> 680 | AK59: =+'lc2501'!G58 -> 121 | AO59: =+SUM(Y59:AL59) -> 255720 | AP59: =+AO59/AO58-1 -> -0.0055338858
B60: 45320 | D60: =+'lc2402'!B59*W60/1000 -> 15.6 | E60: =+'lc2403'!B59*W60/1000 -> 15.656 | F60: =+'lc2404'!B59*W60/1000 -> 16.176 | G60: =+'lc2405'!B59*W60/1000 -> 16.224 | H60: =+'lc2406'!B59*W60/1000 -> 16.312 | I60: =+'lc2407'!B59*W60/1000 -> 16.312 | J60: =+'lc2408'!B59*W60/1000 -> 16.552 | K60: =+'lc2409'!B59*W60/1000 -> 16.576 | L60: =+'lc2410'!B59*W60/1000 -> 16.568 | M60: =+'lc2411'!B59*W60/1000 -> 16.552 | N60: =+'lc2412'!B59*W60/1000 -> 16.624 | O60: =+'lc2501'!B59*W60/1000 -> 16.664 | P60: =+'lc2501'!C59*X60/1000 -> 0 | Q60: 0 | S60: =+AVERAGE(C60:O60) -> 16.318 | W60: 0.16 | Z60: =+'lc2402'!G59 -> 5378 | AA60: =+'lc2403'!G59 -> 15395 | AB60: =+'lc2404'!G59 -> 37606 | AC60: =+'lc2405'!G59 -> 12429 | AD60: =+'lc2406'!G59 -> 6260 | AE60: =+'lc2407'!G59 -> 144728 | AF60: =+'lc2408'!G59 -> 9542 | AG60: =+'lc2409'!G59 -> 7755 | AH60: =+'lc2410'!G59 -> 4130 | AI60: =+'lc2411'!G59 -> 7142 | AJ60: =+'lc2412'!G59 -> 707 | AK60: =+'lc2501'!G59 -> 128 | AO60: =+SUM(Y60:AL60) -> 251200 | AP60: =+AO60/AO59-1 -> -0.017675583
B61: 45321 | D61: =+'lc2402'!B60*W61/1000 -> 15.528 | E61: =+'lc2403'!B60*W61/1000 -> 15.544 | F61: =+'lc2404'!B60*W61/1000 -> 16.064 | G61: =+'lc2405'!B60*W61/1000 -> 16.08 | H61: =+'lc2406'!B60*W61/1000 -> 16.096 | I61: =+'lc2407'!B60*W61/1000 -> 16.16 | J61: =+'lc2408'!B60*W61/1000 -> 16.456 | K61: =+'lc2409'!B60*W61/1000 -> 16.48 | L61: =+'lc2410'!B60*W61/1000 -> 16.384 | M61: =+'lc2411'!B60*W61/1000 -> 16.448 | N61: =+'lc2412'!B60*W61/1000 -> 16.56 | O61: =+'lc2501'!B60*W61/1000 -> 16.616 | P61: =+'lc2501'!C60*X61/1000 -> 0 | Q61: 0 | S61: =+AVERAGE(C61:O61) -> 16.201333 | W61: 0.16 | Z61: =+'lc2402'!G60 -> 4981 | AA61: =+'lc2403'!G60 -> 15074 | AB61: =+'lc2404'!G60 -> 36633 | AC61: =+'lc2405'!G60 -> 12247 | AD61: =+'lc2406'!G60 -> 6250 | AE61: =+'lc2407'!G60 -> 141118 | AF61: =+'lc2408'!G60 -> 9523 | AG61: =+'lc2409'!G60 -> 7703 | AH61: =+'lc2410'!G60 -> 4113 | AI61: =+'lc2411'!G60 -> 7130 | AJ61: =+'lc2412'!G60 -> 708 | AK61: =+'lc2501'!G60 -> 136 | AO61: =+SUM(Y61:AL61) -> 245616 | AP61: =+AO61/AO60-1 -> -0.022229299
B62: 45322 | D62: =+'lc2402'!B61*W62/1000 -> 15.28 | E62: =+'lc2403'!B61*W62/1000 -> 15.36 | F62: =+'lc2404'!B61*W62/1000 -> 15.784 | G62: =+'lc2405'!B61*W62/1000 -> 15.84 | H62: =+'lc2406'!B61*W62/1000 -> 15.864 | I62: =+'lc2407'!B61*W62/1000 -> 15.864 | J62: =+'lc2408'!B61*W62/1000 -> 16.184 | K62: =+'lc2409'!B61*W62/1000 -> 16.168 | L62: =+'lc2410'!B61*W62/1000 -> 16.28 | M62: =+'lc2411'!B61*W62/1000 -> 16.168 | N62: =+'lc2412'!B61*W62/1000 -> 16.456 | O62: =+'lc2501'!B61*W62/1000 -> 16.328 | P62: =+'lc2501'!C61*X62/1000 -> 0 | Q62: 0 | S62: =+AVERAGE(C62:O62) -> 15.964667 | W62: 0.16 | Z62: =+'lc2402'!G61 -> 4862 | AA62: =+'lc2403'!G61 -> 14864 | AB62: =+'lc2404'!G61 -> 35147 | AC62: =+'lc2405'!G61 -> 11947 | AD62: =+'lc2406'!G61 -> 6205 | AE62: =+'lc2407'!G61 -> 150388 | AF62: =+'lc2408'!G61 -> 9357 | AG62: =+'lc2409'!G61 -> 7595 | AH62: =+'lc2410'!G61 -> 4125 | AI62: =+'lc2411'!G61 -> 7204 | AJ62: =+'lc2412'!G61 -> 685 | AK62: =+'lc2501'!G61 -> 158 | AO62: =+SUM(Y62:AL62) -> 252537 | AP62: =+AO62/AO61-1 -> 0.028178132
B63: 45323 | D63: =+'lc2402'!B62*W63/1000 -> 15.36 | E63: =+'lc2403'!B62*W63/1000 -> 15.4 | F63: =+'lc2404'!B62*W63/1000 -> 15.84 | G63: =+'lc2405'!B62*W63/1000 -> 15.864 | H63: =+'lc2406'!B62*W63/1000 -> 15.912 | I63: =+'lc2407'!B62*W63/1000 -> 15.936 | J63: =+'lc2408'!B62*W63/1000 -> 16.216 | K63: =+'lc2409'!B62*W63/1000 -> 16.264 | L63: =+'lc2410'!B62*W63/1000 -> 16.24 | M63: =+'lc2411'!B62*W63/1000 -> 16.224 | N63: =+'lc2412'!B62*W63/1000 -> 16.352 | O63: =+'lc2501'!B62*W63/1000 -> 16.488 | P63: =+'lc2501'!C62*X63/1000 -> 0 | Q63: 0 | S63: =+AVERAGE(C63:O63) -> 16.008 | W63: 0.16 | Z63: =+'lc2402'!G62 -> 2240 | AA63: =+'lc2403'!G62 -> 14894 | AB63: =+'lc2404'!G62 -> 33934 | AC63: =+'lc2405'!G62 -> 11701 | AD63: =+'lc2406'!G62 -> 6201 | AE63: =+'lc2407'!G62 -> 145032 | AF63: =+'lc2408'!G62 -> 9362 | AG63: =+'lc2409'!G62 -> 7558 | AH63: =+'lc2410'!G62 -> 4117 | AI63: =+'lc2411'!G62 -> 7139 | AJ63: =+'lc2412'!G62 -> 679 | AK63: =+'lc2501'!G62 -> 168 | AO63: =+SUM(Y63:AL63) -> 243025 | AP63: =+AO63/AO62-1 -> -0.037665768
... B70: 45342 | D70: =+'lc2402'!B69*W70/1000 -> 14.4 | E70: =+'lc2403'!B69*W70/1000 -> 14.424 | F70: =+'lc2404'!B69*W70/1000 -> 14.768 | G70: =+'lc2405'!B69*W70/1000 -> 14.824 | H70: =+'lc2406'!B69*W70/1000 -> 14.84 | I70: =+'lc2407'!B69*W70/1000 -> 14.848 | J70: =+'lc2408'!B69*W70/1000 -> 15.16 | K70: =+'lc2409'!B69*W70/1000 -> 15.224 | L70: =+'lc2410'!B69*W70/1000 -> 15.264 | M70: =+'lc2411'!B69*W70/1000 -> 15.28 | N70: =+'lc2412'!B69*W70/1000 -> 15.728 | O70: =+'lc2501'!B69*W70/1000 -> 15.768 | P70: =+'lc2501'!C69*X70/1000 -> 0 | Q70: 0 | S70: =+AVERAGE(C70:O70) -> 15.044 | W70: 0.16 | Z70: =+'lc2402'!G69 -> 375 | AA70: =+'lc2403'!G69 -> 14129 | AB70: =+'lc2404'!G69 -> 29588 | AC70: =+'lc2405'!G69 -> 11730 | AD70: =+'lc2406'!G69 -> 6382 | AE70: =+'lc2407'!G69 -> 173155 | AF70: =+'lc2408'!G69 -> 9822 | AG70: =+'lc2409'!G69 -> 7284 | AH70: =+'lc2410'!G69 -> 4205 | AI70: =+'lc2411'!G69 -> 7514 | AJ70: =+'lc2412'!G69 -> 864 | AK70: =+'lc2501'!G69 -> 400 | AO70: =+SUM(Y70:AL70) -> 265448 | AP70: =+AO70/AO69-1 -> 0.10449624
B71: 45370 | D71: =+'lc2402'!B70*W71/1000 -> 15.88 | E71: =+'lc2403'!B70*W71/1000 -> 14.992 | F71: =+'lc2404'!B70*W71/1000 -> 15.408 | G71: =+'lc2405'!B70*W71/1000 -> 15.44 | H71: =+'lc2406'!B70*W71/1000 -> 15.512 | I71: =+'lc2407'!B70*W71/1000 -> 15.504 | J71: =+'lc2408'!B70*W71/1000 -> 15.776 | K71: =+'lc2409'!B70*W71/1000 -> 15.824 | L71: =+'lc2410'!B70*W71/1000 -> 15.792 | M71: =+'lc2411'!B70*W71/1000 -> 15.84 | N71: =+'lc2412'!B70*W71/1000 -> 16.024 | O71: =+'lc2501'!B70*W71/1000 -> 16.008 | P71: =+'lc2502'!B70*W71/1000 -> 18.296 | Q71: =+'lc2503'!B70*W71/1000 -> 18.408 | S71: =+AVERAGE(C71:O71) -> 15.666667 | W71: 0.16 | Z71: =+'lc2402'!G70 -> 351 | AA71: =+'lc2403'!G70 -> 13102 | AB71: =+'lc2404'!G70 -> 30244 | AC71: =+'lc2405'!G70 -> 11836 | AD71: =+'lc2406'!G70 -> 6339 | AE71: =+'lc2407'!G70 -> 165643 | AF71: =+'lc2408'!G70 -> 9702 | AG71: =+'lc2409'!G70 -> 7161 | AH71: =+'lc2410'!G70 -> 4127 | AI71: =+'lc2411'!G70 -> 7487 | AJ71: =+'lc2412'!G70 -> 1106 | AK71: =+'lc2501'!G70 -> 486 | AL71: =+'lc2502'!G70 -> 409 | AM71: =+'lc2503'!G70 -> 582050 | AO71: =+SUM(Y71:AL71) -> 257993 | AP71: =+AO71/AO70-1 -> -0.028084597
B72: 45376 | D72: =+'lc2402'!B71*W72/1000 -> 0 | E72: =+'lc2403'!B71*W72/1000 -> 0 | F72: =+'lc2404'!B71*W72/1000 -> 18.24 | G72: =+'lc2405'!B71*W72/1000 -> 18.328 | H72: =+'lc2406'!B71*W72/1000 -> 18.336 | I72: =+'lc2407'!B71*W72/1000 -> 18.392 | J72: =+'lc2408'!B71*W72/1000 -> 18.36 | K72: =+'lc2409'!B71*W72/1000 -> 18.408 | L72: =+'lc2410'!B71*W72/1000 -> 18.32 | M72: =+'lc2411'!B71*W72/1000 -> 18.264 | N72: =+'lc2412'!B71*W72/1000 -> 18.304 | O72: =+'lc2501'!B71*W72/1000 -> 18.344 | P72: =+'lc2502'!B72*W72/1000 -> 17.28 | Q72: =+'lc2503'!B73*W72/1000 -> 17.32 | S72: =+AVERAGE(C72:O72) -> 15.274667 | W72: 0.16 | Z72: =+'lc2402'!G71 -> 0 | AA72: =+'lc2403'!G71 -> 0 | AB72: =+'lc2404'!G71 -> 21570 | AC72: =+'lc2405'!G71 -> 18145 | AD72: =+'lc2406'!G71 -> 11954 | AE72: =+'lc2407'!G71 -> 202175 | AF72: =+'lc2408'!G71 -> 16209 | AG72: =+'lc2409'!G71 -> 7512 | AH72: =+'lc2410'!G71 -> 5283 | AI72: =+'lc2411'!G71 -> 15028 | AJ72: =+'lc2412'!G71 -> 4505 | AK72: =+'lc2501'!G71 -> 5163 | AL72: =+'lc2502'!G72 -> 553 | AM72: =+'lc2503'!G73 -> 110 | AO72: =+SUM(Y72:AL72) -> 308097 | AP72: =+AO72/AO71-1 -> 0.19420682
B73: 45379 | D73: =+'lc2402'!B72*W73/1000 -> 0 | E73: =+'lc2403'!B72*W73/1000 -> 0 | F73: =+'lc2404'!B72*W73/1000 -> 18.37125 | G73: =+'lc2405'!B72*W73/1000 -> 18.448875 | H73: =+'lc2406'!B72*W73/1000 -> 18.4575 | I73: =+'lc2407'!B72*W73/1000 -> 18.5265 | J73: =+'lc2408'!B72*W73/1000 -> 18.552375 | K73: =+'lc2409'!B72*W73/1000 -> 18.552375 | L73: =+'lc2410'!B72*W73/1000 -> 18.569625 | M73: =+'lc2411'!B72*W73/1000 -> 18.54375 | N73: =+'lc2412'!B72*W73/1000 -> 18.673125 | O73: =+'lc2501'!B72*W73/1000 -> 18.6645 | P73: =+'lc2502'!B73*W73/1000 -> 18.862875 | Q73: =+'lc2503'!B74*W73/1000 -> 18.85425 | S73: =+AVERAGE(C73:O73) -> 15.446656 | W73: 0.1725 | Z73: =+'lc2402'!G72 -> 0 | AA73: =+'lc2403'!G72 -> 0 | AB73: =+'lc2404'!G72 -> 14716 | AC73: =+'lc2405'!G72 -> 18692 | AD73: =+'lc2406'!G72 -> 11706 | AE73: =+'lc2407'!G72 -> 206188 | AF73: =+'lc2408'!G72 -> 17959 | AG73: =+'lc2409'!G72 -> 8805 | AH73: =+'lc2410'!G72 -> 5280 | AI73: =+'lc2411'!G72 -> 15228 | AJ73: =+'lc2412'!G72 -> 4825 | AK73: =+'lc2501'!G72 -> 5859 | AL73: =+'lc2502'!G73 -> 564 | AM73: =+'lc2503'!G74 -> 122 | AO73: =+SUM(Y73:AL73) -> 309822 | AP73: =+AO73/AO72-1 -> 0.0055988861
B74: 45380 | D74: =+'lc2402'!B73*W74/1000 -> 0 | E74: =+'lc2403'!B73*W74/1000 -> 0 | F74: =+'lc2404'!B73*W74/1000 -> 18.23652 | G74: =+'lc2405'!B73*W74/1000 -> 18.28746 | H74: =+'lc2406'!B73*W74/1000 -> 18.36387 | I74: =+'lc2407'!B73*W74/1000 -> 18.4233 | J74: =+'lc2408'!B73*W74/1000 -> 18.49122 | K74: =+'lc2409'!B73*W74/1000 -> 18.52518 | L74: =+'lc2410'!B73*W74/1000 -> 18.51669 | M74: =+'lc2411'!B73*W74/1000 -> 18.49971 | N74: =+'lc2412'!B73*W74/1000 -> 18.5931 | O74: =+'lc2501'!B73*W74/1000 -> 18.58461 | P74: =+'lc2502'!B74*W74/1000 -> 18.44877 | Q74: =+'lc2503'!B75*W74/1000 -> 18.36387 | S74: =+AVERAGE(C74:O74) -> 15.376805 | W74: 0.1698 | Z74: =+'lc2402'!G73 -> 0 | AA74: =+'lc2403'!G73 -> 0 | AB74: =+'lc2404'!G73 -> 11962 | AC74: =+'lc2405'!G73 -> 22881 | AD74: =+'lc2406'!G73 -> 12016 | AE74: =+'lc2407'!G73 -> 199818 | AF74: =+'lc2408'!G73 -> 17332 | AG74: =+'lc2409'!G73 -> 8344 | AH74: =+'lc2410'!G73 -> 5236 | AI74: =+'lc2411'!G73 -> 15431 | AJ74: =+'lc2412'!G73 -> 4871 | AK74: =+'lc2501'!G73 -> 6104 | AL74: =+'lc2502'!G74 -> 573 | AM74: =+'lc2503'!G75 -> 139 | AO74: =+SUM(Y74:AL74) -> 304568 | AP74: =+AO74/AO73-1 -> -0.016958124
B75: 45383 | D75: =+'lc2402'!B74*W75/1000 -> 0 | E75: =+'lc2403'!B74*W75/1000 -> 0 | F75: =+'lc2404'!B74*W75/1000 -> 17.87994 | G75: =+'lc2405'!B74*W75/1000 -> 18.07521 | H75: =+'lc2406'!B74*W75/1000 -> 18.09219 | I75: =+'lc2407'!B74*W75/1000 -> 18.17709 | J75: =+'lc2408'!B74*W75/1000 -> 18.34689 | K75: =+'lc2409'!B74*W75/1000 -> 18.3384 | L75: =+'lc2410'!B74*W75/1000 -> 18.36387 | M75: =+'lc2411'!B74*W75/1000 -> 18.36387 | N75: =+'lc2412'!B74*W75/1000 -> 18.5082 | O75: =+'lc2501'!B74*W75/1000 -> 18.49971 | P75: =+'lc2502'!B75*W75/1000 -> 19.11948 | Q75: =+'lc2503'!B76*W75/1000 -> 19.14495 | S75: =+AVERAGE(C75:O75) -> 15.220448 | W75: 0.1698 | Z75: =+'lc2402'!G74 -> 0 | AA75: =+'lc2403'!G74 -> 0 | AB75: =+'lc2404'!G74 -> 11167 | AC75: =+'lc2405'!G74 -> 22828 | AD75: =+'lc2406'!G74 -> 12094 | AE75: =+'lc2407'!G74 -> 196813 | AF75: =+'lc2408'!G74 -> 17271 | AG75: =+'lc2409'!G74 -> 8431 | AH75: =+'lc2410'!G74 -> 5228 | AI75: =+'lc2411'!G74 -> 15439 | AJ75: =+'lc2412'!G74 -> 4997 | AK75: =+'lc2501'!G74 -> 6084 | AL75: =+'lc2502'!G75 -> 558 | AM75: =+'lc2503'!G76 -> 165 | AO75: =+SUM(Y75:AL75) -> 300910 | AP75: =+AO75/AO74-1 -> -0.012010454
B76: 45384 | D76: =+'lc2402'!B75*W76/1000 -> 0 | E76: =+'lc2403'!B75*W76/1000 -> 0 | F76: =+'lc2404'!B75*W76/1000 -> 18.66102 | G76: =+'lc2405'!B75*W76/1000 -> 19.00062 | H76: =+'lc2406'!B75*W76/1000 -> 19.05156 | I76: =+'lc2407'!B75*W76/1000 -> 19.11948 | J76: =+'lc2408'!B75*W76/1000 -> 19.23834 | K76: =+'lc2409'!B75*W76/1000 -> 19.13646 | L76: =+'lc2410'!B75*W76/1000 -> 19.1025 | M76: =+'lc2411'!B75*W76/1000 -> 19.17042 | N76: =+'lc2412'!B75*W76/1000 -> 19.16193 | O76: =+'lc2501'!B75*W76/1000 -> 19.11099 | P76: =+'lc2502'!B76*W76/1000 -> 19.06854 | Q76: =+'lc2503'!B77*W76/1000 -> 19.07703 | S76: =+AVERAGE(C76:O76) -> 15.89611 | W76: 0.1698 | Z76: =+'lc2402'!G75 -> 0 | AA76: =+'lc2403'!G75 -> 0 | AB76: =+'lc2404'!G75 -> 10165 | AC76: =+'lc2405'!G75 -> 22472 | AD76: =+'lc2406'!G75 -> 12203 | AE76: =+'lc2407'!G75 -> 200099 | AF76: =+'lc2408'!G75 -> 17333 | AG76: =+'lc2409'!G75 -> 8119 | AH76: =+'lc2410'!G75 -> 5253 | AI76: =+'lc2411'!G75 -> 15231 | AJ76: =+'lc2412'!G75 -> 4938 | AK76: =+'lc2501'!G75 -> 6029 | AL76: =+'lc2502'!G76 -> 563 | AM76: =+'lc2503'!G77 -> 170 | AO76: =+SUM(Y76:AL76) -> 302405 | AP76: =+AO76/AO75-1 -> 0.0049682629
B77: 45385 | D77: =+'lc2402'!B76*W77/1000 -> 0 | E77: =+'lc2403'!B76*W77/1000 -> 0 | F77: =+'lc2404'!B76*W77/1000 -> 18.678 | G77: =+'lc2405'!B76*W77/1000 -> 18.72894 | H77: =+'lc2406'!B76*W77/1000 -> 18.82233 | I77: =+'lc2407'!B76*W77/1000 -> 18.8478 | J77: =+'lc2408'!B76*W77/1000 -> 18.99213 | K77: =+'lc2409'!B76*W77/1000 -> 18.98364 | L77: =+'lc2410'!B76*W77/1000 -> 18.99213 | M77: =+'lc2411'!B76*W77/1000 -> 18.96666 | N77: =+'lc2412'!B76*W77/1000 -> 19.02609 | O77: =+'lc2501'!B76*W77/1000 -> 19.0176 | P77: =+'lc2502'!B77*W77/1000 -> 19.21287 | Q77: =+'lc2503'!B78*W77/1000 -> 19.14495 | S77: =+AVERAGE(C77:O77) -> 15.75461 | W77: 0.1698 | Z77: =+'lc2402'!G76 -> 0 | AA77: =+'lc2403'!G76 -> 0 | AB77: =+'lc2404'!G76 -> 8613 | AC77: =+'lc2405'!G76 -> 22370 | AD77: =+'lc2406'!G76 -> 12230 | AE77: =+'lc2407'!G76 -> 191181 | AF77: =+'lc2408'!G76 -> 17487 | AG77: =+'lc2409'!G76 -> 8153 | AH77: =+'lc2410'!G76 -> 5262 | AI77: =+'lc2411'!G76 -> 15088 | AJ77: =+'lc2412'!G76 -> 4937 | AK77: =+'lc2501'!G76 -> 6036 | AL77: =+'lc2502'!G77 -> 595 | AM77: =+'lc2503'!G78 -> 167 | AO77: =+SUM(Y77:AL77) -> 291952 | AP77: =+AO77/AO76-1 -> -0.034566227
B78: 45386 | D78: =+'lc2402'!B77*W78/1000 -> 0 | E78: =+'lc2403'!B77*W78/1000 -> 0 | F78: =+'lc2404'!B77*W78/1000 -> 18.7629 | G78: =+'lc2405'!B77*W78/1000 -> 18.85629 | H78: =+'lc2406'!B77*W78/1000 -> 18.9327 | I78: =+'lc2407'!B77*W78/1000 -> 18.98364 | J78: =+'lc2408'!B77*W78/1000 -> 19.11948 | K78: =+'lc2409'!B77*W78/1000 -> 19.13646 | L78: =+'lc2410'!B77*W78/1000 -> 19.13646 | M78: =+'lc2411'!B77*W78/1000 -> 19.13646 | N78: =+'lc2412'!B77*W78/1000 -> 19.17042 | O78: =+'lc2501'!B77*W78/1000 -> 19.17891 | P78: =+'lc2502'!B78*W78/1000 -> 19.42512 | Q78: =+'lc2503'!B79*W78/1000 -> 19.14495 | S78: =+AVERAGE(C78:Q78) -> 16.355985 | W78: 0.1698 | Z78: =+'lc2402'!G77 -> 0 | AA78: =+'lc2403'!G77 -> 0 | AB78: =+'lc2404'!G77 -> 7523 | AC78: =+'lc2405'!G77 -> 21988 | AD78: =+'lc2406'!G77 -> 12247 | AE78: =+'lc2407'!G77 -> 183070 | AF78: =+'lc2408'!G77 -> 17563 | AG78: =+'lc2409'!G77 -> 8115 | AH78: =+'lc2410'!G77 -> 5284 | AI78: =+'lc2411'!G77 -> 15023 | AJ78: =+'lc2412'!G77 -> 4915 | AK78: =+'lc2501'!G77 -> 6090 | AL78: =+'lc2502'!G78 -> 605 | AM78: =+'lc2503'!G79 -> 167 | AO78: =+SUM(Y78:AL78) -> 282423 | AP78: =+AO78/AO77-1 -> -0.032638927
B79: 45387 | D79: =+'lc2402'!B78*W79/1000 -> 0 | E79: =+'lc2403'!B78*W79/1000 -> 0 | F79: =+'lc2404'!B78*W79/1000 -> 18.7629 | G79: =+'lc2405'!B78*W79/1000 -> 18.85629 | H79: =+'lc2406'!B78*W79/1000 -> 18.9327 | I79: =+'lc2407'!B78*W79/1000 -> 19.2723 | J79: =+'lc2408'!B78*W79/1000 -> 19.11948 | K79: =+'lc2409'!B78*W79/1000 -> 19.13646 | L79: =+'lc2410'!B78*W79/1000 -> 19.13646 | M79: =+'lc2411'!B78*W79/1000 -> 19.13646 | N79: =+'lc2412'!B78*W79/1000 -> 19.17042 | O79: =+'lc2501'!B78*W79/1000 -> 19.17891 | P79: =+'lc2502'!B79*W79/1000 -> 19.43361 | Q79: =+'lc2503'!B80*W79/1000 -> 19.14495 | S79: =+AVERAGE(C79:Q79) -> 16.37721 | W79: 0.1698 | Z79: =+'lc2402'!G78 -> 0 | AA79: =+'lc2403'!G78 -> 0 | AB79: =+'lc2404'!G78 -> 7523 | AC79: =+'lc2405'!G78 -> 21988 | AD79: =+'lc2406'!G78 -> 12247 | AE79: =+'lc2407'!G78 -> 183798 | AF79: =+'lc2408'!G78 -> 17563 | AG79: =+'lc2409'!G78 -> 8115 | AH79: =+'lc2410'!G78 -> 5284 | AI79: =+'lc2411'!G78 -> 15023 | AJ79: =+'lc2412'!G78 -> 4915 | AK79: =+'lc2501'!G78 -> 6090 | AL79: =+'lc2502'!G79 -> 613 | AM79: =+'lc2503'!G80 -> 167 | AO79: =+SUM(Y79:AL79) -> 283159 | AP79: =+AO79/AO78-1 -> 0.00260602
B80: 45388 | D80: =+'lc2402'!B79*W80/1000 -> 0 | E80: =+'lc2403'!B79*W80/1000 -> 0 | F80: =+'lc2404'!B79*W80/1000 -> 0 | G80: =+'lc2405'!B79*W80/1000 -> 0 | H80: =+'lc2406'!B79*W80/1000 -> 0 | I80: =+'lc2407'!B79*W80/1000 -> 0 | J80: =+'lc2408'!B79*W80/1000 -> 0 | K80: =+'lc2409'!B79*W80/1000 -> 0 | L80: =+'lc2410'!B79*W80/1000 -> 0 | M80: =+'lc2411'!B79*W80/1000 -> 0 | N80: =+'lc2412'!B79*W80/1000 -> 0 | O80: =+'lc2501'!B79*W80/1000 -> 0 | P80: =+'lc2502'!B80*W80/1000 -> 0 | Q80: =+'lc2503'!B81*W80/1000 -> 0
B81: 45389 | D81: =+'lc2402'!B80*W81/1000 -> 0 | E81: =+'lc2403'!B80*W81/1000 -> 0 | F81: =+'lc2404'!B80*W81/1000 -> 0 | G81: =+'lc2405'!B80*W81/1000 -> 0 | H81: =+'lc2406'!B80*W81/1000 -> 0 | I81: =+'lc2407'!B80*W81/1000 -> 0 | J81: =+'lc2408'!B80*W81/1000 -> 0 | K81: =+'lc2409'!B80*W81/1000 -> 0 | L81: =+'lc2410'!B80*W81/1000 -> 0 | M81: =+'lc2411'!B80*W81/1000 -> 0 | N81: =+'lc2412'!B80*W81/1000 -> 0 | O81: =+'lc2501'!B80*W81/1000 -> 0 | P81: =+'lc2502'!B81*W81/1000 -> 0 | Q81: =+'lc2503'!B82*W81/1000 -> 0 | AH81: 24' Worldwide Production est. | AL81: 1250000 | AM81: =+AO74/$AL$81 -> 0.2436544
B82: 45390 | D82: =+'lc2402'!B81*W82/1000 -> 0 | E82: =+'lc2403'!B81*W82/1000 -> 0 | F82: =+'lc2404'!B81*W82/1000 -> 0 | G82: =+'lc2405'!B81*W82/1000 -> 0 | H82: =+'lc2406'!B81*W82/1000 -> 0 | I82: =+'lc2407'!B81*W82/1000 -> 0 | J82: =+'lc2408'!B81*W82/1000 -> 0 | K82: =+'lc2409'!B81*W82/1000 -> 0 | L82: =+'lc2410'!B81*W82/1000 -> 0 | M82: =+'lc2411'!B81*W82/1000 -> 0 | N82: =+'lc2412'!B81*W82/1000 -> 0 | O82: =+'lc2501'!B81*W82/1000 -> 0 | P82: =+'lc2502'!B82*W82/1000 -> 0 | Q82: =+'lc2503'!B83*W82/1000 -> 0 | AH82: Warehouse delivery receipt | AK82: =+TODAY() -> 46092 | AL82: 16240
B83: 45391 | D83: =+'lc2402'!B82*W83/1000 -> 0 | E83: =+'lc2403'!B82*W83/1000 -> 0 | F83: =+'lc2404'!B82*W83/1000 -> 0 | G83: =+'lc2405'!B82*W83/1000 -> 0 | H83: =+'lc2406'!B82*W83/1000 -> 0 | I83: =+'lc2407'!B82*W83/1000 -> 0 | J83: =+'lc2408'!B82*W83/1000 -> 0 | K83: =+'lc2409'!B82*W83/1000 -> 0 | L83: =+'lc2410'!B82*W83/1000 -> 0 | M83: =+'lc2411'!B82*W83/1000 -> 0 | N83: =+'lc2412'!B82*W83/1000 -> 0 | O83: =+'lc2501'!B82*W83/1000 -> 0 | P83: =+'lc2502'!B83*W83/1000 -> 0 | Q83: =+'lc2503'!B84*W83/1000 -> 0
B84: 45392 | D84: =+'lc2402'!B83*W84/1000 -> 0 | E84: =+'lc2403'!B83*W84/1000 -> 0 | F84: =+'lc2404'!B83*W84/1000 -> 0 | G84: =+'lc2405'!B83*W84/1000 -> 0 | H84: =+'lc2406'!B83*W84/1000 -> 0 | I84: =+'lc2407'!B83*W84/1000 -> 0 | J84: =+'lc2408'!B83*W84/1000 -> 0 | K84: =+'lc2409'!B83*W84/1000 -> 0 | L84: =+'lc2410'!B83*W84/1000 -> 0 | M84: =+'lc2411'!B83*W84/1000 -> 0 | N84: =+'lc2412'!B83*W84/1000 -> 0 | O84: =+'lc2501'!B83*W84/1000 -> 0 | P84: =+'lc2502'!B84*W84/1000 -> 0 | Q84: =+'lc2503'!B85*W84/1000 -> 0
B85: 45393 | D85: =+'lc2402'!B84*W85/1000 -> 0 | E85: =+'lc2403'!B84*W85/1000 -> 0 | F85: =+'lc2404'!B84*W85/1000 -> 0 | G85: =+'lc2405'!B84*W85/1000 -> 0 | H85: =+'lc2406'!B84*W85/1000 -> 0 | I85: =+'lc2407'!B84*W85/1000 -> 0 | J85: =+'lc2408'!B84*W85/1000 -> 0 | K85: =+'lc2409'!B84*W85/1000 -> 0 | L85: =+'lc2410'!B84*W85/1000 -> 0 | M85: =+'lc2411'!B84*W85/1000 -> 0 | N85: =+'lc2412'!B84*W85/1000 -> 0 | O85: =+'lc2501'!B84*W85/1000 -> 0 | P85: =+'lc2502'!B85*W85/1000 -> 0 | Q85: =+'lc2503'!B86*W85/1000 -> 0
B86: 45394 | D86: =+'lc2402'!B85*W86/1000 -> 0 | E86: =+'lc2403'!B85*W86/1000 -> 0 | F86: =+'lc2404'!B85*W86/1000 -> 0 | G86: =+'lc2405'!B85*W86/1000 -> 0 | H86: =+'lc2406'!B85*W86/1000 -> 0 | I86: =+'lc2407'!B85*W86/1000 -> 0 | J86: =+'lc2408'!B85*W86/1000 -> 0 | K86: =+'lc2409'!B85*W86/1000 -> 0 | L86: =+'lc2410'!B85*W86/1000 -> 0 | M86: =+'lc2411'!B85*W86/1000 -> 0 | N86: =+'lc2412'!B85*W86/1000 -> 0 | O86: =+'lc2501'!B85*W86/1000 -> 0 | P86: =+'lc2502'!B86*W86/1000 -> 0 | Q86: =+'lc2503'!B87*W86/1000 -> 0
B87: 45395 | D87: =+'lc2402'!B86*W87/1000 -> 0 | E87: =+'lc2403'!B86*W87/1000 -> 0 | F87: =+'lc2404'!B86*W87/1000 -> 0 | G87: =+'lc2405'!B86*W87/1000 -> 0 | H87: =+'lc2406'!B86*W87/1000 -> 0 | I87: =+'lc2407'!B86*W87/1000 -> 0 | J87: =+'lc2408'!B86*W87/1000 -> 0 | K87: =+'lc2409'!B86*W87/1000 -> 0 | L87: =+'lc2410'!B86*W87/1000 -> 0 | M87: =+'lc2411'!B86*W87/1000 -> 0 | N87: =+'lc2412'!B86*W87/1000 -> 0 | O87: =+'lc2501'!B86*W87/1000 -> 0 | P87: =+'lc2502'!B87*W87/1000 -> 0 | Q87: =+'lc2503'!B88*W87/1000 -> 0
B88: 45396 | D88: =+'lc2402'!B87*W88/1000 -> 0 | E88: =+'lc2403'!B87*W88/1000 -> 0 | F88: =+'lc2404'!B87*W88/1000 -> 0 | G88: =+'lc2405'!B87*W88/1000 -> 0 | H88: =+'lc2406'!B87*W88/1000 -> 0 | I88: =+'lc2407'!B87*W88/1000 -> 0 | J88: =+'lc2408'!B87*W88/1000 -> 0 | K88: =+'lc2409'!B87*W88/1000 -> 0 | L88: =+'lc2410'!B87*W88/1000 -> 0 | M88: =+'lc2411'!B87*W88/1000 -> 0 | N88: =+'lc2412'!B87*W88/1000 -> 0 | O88: =+'lc2501'!B87*W88/1000 -> 0 | P88: =+'lc2502'!B88*W88/1000 -> 0 | Q88: =+'lc2503'!B89*W88/1000 -> 0
B89: 45397 | D89: =+'lc2402'!B88*W89/1000 -> 0 | E89: =+'lc2403'!B88*W89/1000 -> 0 | F89: =+'lc2404'!B88*W89/1000 -> 0 | G89: =+'lc2405'!B88*W89/1000 -> 0 | H89: =+'lc2406'!B88*W89/1000 -> 0 | I89: =+'lc2407'!B88*W89/1000 -> 0 | J89: =+'lc2408'!B88*W89/1000 -> 0 | K89: =+'lc2409'!B88*W89/1000 -> 0 | L89: =+'lc2410'!B88*W89/1000 -> 0 | M89: =+'lc2411'!B88*W89/1000 -> 0 | N89: =+'lc2412'!B88*W89/1000 -> 0 | O89: =+'lc2501'!B88*W89/1000 -> 0 | P89: =+'lc2502'!B89*W89/1000 -> 0 | Q89: =+'lc2503'!B90*W89/1000 -> 0
B90: 45398 | D90: =+'lc2402'!B89*W90/1000 -> 0 | E90: =+'lc2403'!B89*W90/1000 -> 0 | F90: =+'lc2404'!B89*W90/1000 -> 0 | G90: =+'lc2405'!B89*W90/1000 -> 0 | H90: =+'lc2406'!B89*W90/1000 -> 0 | I90: =+'lc2407'!B89*W90/1000 -> 0 | J90: =+'lc2408'!B89*W90/1000 -> 0 | K90: =+'lc2409'!B89*W90/1000 -> 0 | L90: =+'lc2410'!B89*W90/1000 -> 0 | M90: =+'lc2411'!B89*W90/1000 -> 0 | N90: =+'lc2412'!B89*W90/1000 -> 0 | O90: =+'lc2501'!B89*W90/1000 -> 0 | P90: =+'lc2502'!B90*W90/1000 -> 0 | Q90: =+'lc2503'!B91*W90/1000 -> 0
B91: 45399 | D91: =+'lc2402'!B90*W91/1000 -> 0 | E91: =+'lc2403'!B90*W91/1000 -> 0 | F91: =+'lc2404'!B90*W91/1000 -> 0 | G91: =+'lc2405'!B90*W91/1000 -> 0 | H91: =+'lc2406'!B90*W91/1000 -> 0 | I91: =+'lc2407'!B90*W91/1000 -> 0 | J91: =+'lc2408'!B90*W91/1000 -> 0 | K91: =+'lc2409'!B90*W91/1000 -> 0 | L91: =+'lc2410'!B90*W91/1000 -> 0 | M91: =+'lc2411'!B90*W91/1000 -> 0 | N91: =+'lc2412'!B90*W91/1000 -> 0 | O91: =+'lc2501'!B90*W91/1000 -> 0 | P91: =+'lc2502'!B91*W91/1000 -> 0 | Q91: =+'lc2503'!B92*W91/1000 -> 0
B92: 45400 | D92: =+'lc2402'!B91*W92/1000 -> 0 | E92: =+'lc2403'!B91*W92/1000 -> 0 | F92: =+'lc2404'!B91*W92/1000 -> 0 | G92: =+'lc2405'!B91*W92/1000 -> 0 | H92: =+'lc2406'!B91*W92/1000 -> 0 | I92: =+'lc2407'!B91*W92/1000 -> 0 | J92: =+'lc2408'!B91*W92/1000 -> 0 | K92: =+'lc2409'!B91*W92/1000 -> 0 | L92: =+'lc2410'!B91*W92/1000 -> 0 | M92: =+'lc2411'!B91*W92/1000 -> 0 | N92: =+'lc2412'!B91*W92/1000 -> 0 | O92: =+'lc2501'!B91*W92/1000 -> 0 | P92: =+'lc2502'!B92*W92/1000 -> 0 | Q92: =+'lc2503'!B93*W92/1000 -> 0
B93: 45401 | D93: =+'lc2402'!B92*W93/1000 -> 0 | E93: =+'lc2403'!B92*W93/1000 -> 0 | F93: =+'lc2404'!B92*W93/1000 -> 0 | G93: =+'lc2405'!B92*W93/1000 -> 0 | H93: =+'lc2406'!B92*W93/1000 -> 0 | I93: =+'lc2407'!B92*W93/1000 -> 0 | J93: =+'lc2408'!B92*W93/1000 -> 0 | K93: =+'lc2409'!B92*W93/1000 -> 0 | L93: =+'lc2410'!B92*W93/1000 -> 0 | M93: =+'lc2411'!B92*W93/1000 -> 0 | N93: =+'lc2412'!B92*W93/1000 -> 0 | O93: =+'lc2501'!B92*W93/1000 -> 0 | P93: =+'lc2502'!B93*W93/1000 -> 0 | Q93: =+'lc2503'!B94*W93/1000 -> 0
B94: 45402 | D94: =+'lc2402'!B93*W94/1000 -> 0 | E94: =+'lc2403'!B93*W94/1000 -> 0 | F94: =+'lc2404'!B93*W94/1000 -> 0 | G94: =+'lc2405'!B93*W94/1000 -> 0 | H94: =+'lc2406'!B93*W94/1000 -> 0 | I94: =+'lc2407'!B93*W94/1000 -> 0 | J94: =+'lc2408'!B93*W94/1000 -> 0 | K94: =+'lc2409'!B93*W94/1000 -> 0 | L94: =+'lc2410'!B93*W94/1000 -> 0 | M94: =+'lc2411'!B93*W94/1000 -> 0 | N94: =+'lc2412'!B93*W94/1000 -> 0 | O94: =+'lc2501'!B93*W94/1000 -> 0 | P94: =+'lc2502'!B94*W94/1000 -> 0 | Q94: =+'lc2503'!B95*W94/1000 -> 0
... B101: 45409 | D101: =+'lc2402'!B100*W101/1000 -> 0 | E101: =+'lc2403'!B100*W101/1000 -> 0 | F101: =+'lc2404'!B100*W101/1000 -> 0 | G101: =+'lc2405'!B100*W101/1000 -> 0 | H101: =+'lc2406'!B100*W101/1000 -> 0 | I101: =+'lc2407'!B100*W101/1000 -> 0 | J101: =+'lc2408'!B100*W101/1000 -> 0 | K101: =+'lc2409'!B100*W101/1000 -> 0 | L101: =+'lc2410'!B100*W101/1000 -> 0 | M101: =+'lc2411'!B100*W101/1000 -> 0 | N101: =+'lc2412'!B100*W101/1000 -> 0 | O101: =+'lc2501'!B100*W101/1000 -> 0 | P101: =+'lc2502'!B101*W101/1000 -> 0 | Q101: =+'lc2503'!B102*W101/1000 -> 0
B102: 45410
B103: 45411
B104: 45412
B105: 45413
B106: 45414
B107: 45415
B108: 45416
B109: 45417
B110: 45418
B111: 45419
B112: 45420
B113: 45421
... B141: 45449

Sheet Market
A1: Conversion en Notas | B1: Industrial Grade | C1: Battery Grade | D1: SMM LC Idx | E1: Lithium Hydroxide BG | F1: Lithium Hydroxide Idx | G1: Lithium Hydroxide BG Fine | H1: Lithium Carbonate CIF China | I1: Lithium Hydroxide CIF China | J1: Lithium Hexafluorophosphate | K1: Lithium Fluoride BG | L1: Lithium Hydroxide IG | M1: Spodumene Concentrate IDX CIF China | N1: Spodumene Domestic China 5% | O1: Spodumene Domestic China 4% | P1: Spodumene Dometic China 3% | Q1: Spodumene 1,2% | R1: Spodumene 2% | S1: Spodumene 3% | T1: Lepidolite 1,5% | U1: Lepidolite 2% | V1: Montebrasite 6% | W1: Montebrasite 7% | X1: AUS Spodumene 6% Spot cif China | Y1: BRL Spodumene 6% Spot CIF China
A2: Dec 01, 2023 | B2: 118500 | C2: 130000 | D2: 128431 | E2: 119500 | F2: 119904 | G2: 128500 | H2: 18.505 | I2: 18.5 | J2: 82000 | K2: 259000 | L2: 111000 | M2: 1730 | N2: 9675 | O2: 8500 | P2: 8500 | Q2: 167.5 | R2: 300 | S2: 585 | T2: 2100 | U2: 3375 | V2: 12900 | W2: 15800
A3: Dec 04, 2023 | B3: 116000 | C3: 128000 | D3: 126864 | E3: 117500 | F3: 117936 | G3: 126500 | H3: 17.75 | I3: 18 | J3: 82000 | K3: 259000 | L3: 109000 | M3: 1700 | N3: 9335 | O3: 8185 | P3: 8185 | Q3: 167 | R3: 300 | S3: 585 | T3: 2100 | U3: 3375 | V3: 12900 | W3: 15800
A4: Dec 05, 2023 | B4: 113500 | C4: 126000 | D4: 124781 | E4: 115500 | F4: 115443 | G4: 124500 | H4: 17.6 | I4: 17.75 | J4: 81750 | K4: 259000 | L4: 107000 | M4: 1670 | N4: 9125 | O4: 7960 | P4: 7960 | Q4: 167.5 | R4: 300 | S4: 585 | T4: 2025 | U4: 3275 | V4: 12800 | W4: 15600
A5: Dec 06, 2023 | B5: 109500 | C5: 122500 | D5: 121771 | E5: 112500 | F5: 112411 | G5: 121000 | H5: 17.5 | I5: 17.5 | J5: 81500 | K5: 259000 | L5: 104000 | M5: 1655 | N5: 8900 | O5: 7735 | P5: 7735 | Q5: 167.5 | R5: 300 | S5: 585 | T5: 1975 | U5: 3200 | V5: 12600 | W5: 15300
A6: Dec 07, 2023 | B6: 107000 | C6: 120500 | D6: 119655 | E6: 110500 | F6: 110186 | G6: 118500 | H6: 17 | I6: 17.5 | J6: 80500 | K6: 259000 | L6: 102000 | M6: 1640 | N6: 8755 | O6: 7550 | P6: 7550 | Q6: 152.5 | R6: 280 | S6: 545 | T6: 1950 | U6: 3162.5 | V6: 12325 | W6: 14925
A7: Dec 11, 2023 | B7: 101500 | C7: 115000 | D7: 114815 | E7: 106500 | F7: 106772 | G7: 114500 | H7: 16.5 | I7: 16.75 | J7: 77500 | K7: 235500 | L7: 98500 | M7: 1565 | N7: 8285 | O7: 6970 | P7: 6970 | Q7: 152.5 | R7: 280 | S7: 545 | T7: 1875 | U7: 3050 | V7: 12275 | W7: 14850
A8: Dec 12, 2023 | B8: 98500 | C8: 112000 | D8: 112927 | E8: 103500 | F8: 103671 | G8: 111500 | H8: 16.25 | I8: 16.65 | J8: 77000 | K8: 235500 | L8: 95500 | M8: 1535 | N8: 8130 | O8: 6815 | P8: 6815 | Q8: 152.5 | R8: 280 | S8: 545 | T8: 1850 | U8: 3012.5 | V8: 12275 | W8: 14850
A9: Dec 13, 2023 | B9: 96000 | C9: 109000 | D9: 109468 | E9: 100500 | F9: 100118 | G9: 108500 | H9: 16 | I9: 16.5 | J9: 76500 | K9: 235500 | L9: 92500 | M9: 1515 | N9: 8050 | O9: 6650 | P9: 6650 | Q9: 152.5 | R9: 280 | S9: 545 | T9: 1825 | U9: 2975 | V9: 11775 | W9: 14275
A10: Dec 14, 2023 | B10: 94500 | C10: 106500 | D10: 106787 | E10: 98000 | F10: 97747 | G10: 106000 | H10: 15.75 | I10: 16.25 | J10: 76000 | K10: 235500 | L10: 90000 | M10: 1495 | N10: 7970 | O10: 6490 | P10: 6490 | Q10: 143.5 | R10: 262.5 | S10: 520 | T10: 1775 | U10: 2900 | V10: 11575 | W10: 14025
A11: Dec 15, 2023 | B11: 93750 | C11: 104500 | D11: 104371 | E11: 95750 | F11: 95250 | G11: 103750 | H11: 15.5 | I11: 16.25 | J11: 75500 | K11: 210300 | L11: 88000 | M11: 1470 | N11: 7890 | O11: 6360 | P11: 6360 | Q11: 143.5 | R11: 262.5 | S11: 520 | T11: 1725 | U11: 2862 | V11: 11275 | W11: 13650
A12: Dec 18, 2023 | B12: 93250 | C12: 103000 | D12: 102628 | E12: 93750 | F12: 93540 | G12: 101750 | H12: 15.25 | I12: 16 | J12: 75000 | K12: 210300 | L12: 86000 | M12: 1455 | N12: 7810 | O12: 6250 | P12: 6250 | Q12: 143.5 | R12: 262.5 | S12: 520 | T12: 1625 | U12: 2737.5 | V12: 10875 | W12: 13200
A13: Dec 19, 2023 | B13: 92750 | C13: 102000 | D13: 101066 | E13: 91750 | F13: 91790 | G13: 99750 | H13: 15 | I13: 16 | J13: 74500 | K13: 210300 | L13: 84000 | M13: 1440 | N13: 7740 | O13: 6185 | P13: 6185 | Q13: 143.5 | R13: 262.5 | S13: 520 | T13: 1550 | U13: 2625 | V13: 10675 | W13: 12950
... A34: Jan 31, 2024 | B34: 89200 | C34: 96750 | D34: 95640 | E34: 84650 | F34: 83538 | G34: 90550 | H34: 14 | I34: 13.75 | J34: 65000 | K34: 165000 | L34: 77000 | M34: 938 | N34: 6425 | O34: 5225 | P34: 3375 | Q34: 100 | R34: 183.5 | S34: 385 | T34: 1210 | U34: 2085 | V34: 9620 | W34: 11600
A35: Feb 01, 2024 | B35: 89500 | C35: 97050 | D35: 95730 | E35: 84850 | F35: 83819 | G35: 90750 | H35: 14 | I35: 13.75 | J35: 65000 | K35: 165000 | L35: 77000 | M35: 938 | N35: 6425 | O35: 5225 | P35: 3375 | Q35: 100 | R35: 183.5 | S35: 385 | T35: 1210 | U35: 2085 | V35: 9620 | W35: 11600 | X35: 900 | Y35: 825
A36: Feb 02, 2024 | B36: 89500 | C36: 97050 | D36: 95801 | E36: 84850 | F36: 83819 | G36: 90750 | H36: 14 | I36: 13.75 | J36: 65000 | K36: 165000 | L36: 77000 | M36: 938 | N36: 6425 | O36: 5225 | P36: 3375 | Q36: 100 | R36: 183.5 | S36: 385 | T36: 1210 | U36: 2085 | V36: 9620 | W36: 11600 | X36: 900 | Y36: 825
A37: Feb 05, 2024 | B37: 89500 | C37: 97050 | D37: 95801 | E37: 84950 | F37: 83837 | G37: 90850 | H37: 14 | I37: 13.75 | J37: 65000 | K37: 165000 | L37: 77000 | M37: 938 | N37: 6425 | O37: 5225 | P37: 3375 | Q37: 100 | R37: 183.5 | S37: 385 | T37: 1210 | U37: 2085 | V37: 9620 | W37: 11600 | X37: 900 | Y37: 825
A38: Feb 06, 2024 | B38: 89500 | C38: 97050 | D38: 95921 | E38: 85150 | F38: 83864 | G38: 91050 | H38: 14 | I38: 13.75 | J38: 65000 | K38: 165000 | L38: 77200 | M38: 938 | N38: 6425 | O38: 5225 | P38: 3375 | Q38: 100 | R38: 183.5 | S38: 385 | T38: 1210 | U38: 2085 | V38: 9620 | W38: 11600 | X38: 900 | Y38: 825
A39: Feb 07, 2024 | B39: 89500 | C39: 97050 | D39: 95921 | E39: 85150 | F39: 83869 | G39: 91050 | H39: 14 | I39: 13.75 | J39: 65000 | K39: 165000 | L39: 77200 | M39: 938 | N39: 6425 | O39: 5225 | P39: 3375 | Q39: 100 | R39: 183.5 | S39: 385 | T39: 1210 | U39: 2085 | V39: 9620 | W39: 11600 | X39: 900 | Y39: 825
A40: Feb 08, 2024 | B40: 89500 | C40: 97050 | D40: 95921 | E40: 85150 | F40: 83869 | G40: 91050 | H40: 14 | I40: 13.75 | J40: 65000 | K40: 165000 | L40: 77200 | M40: 938 | N40: 6425 | O40: 5225 | P40: 3375 | Q40: 100 | R40: 183.5 | S40: 385 | T40: 1210 | U40: 2085 | V40: 9620 | W40: 11600 | X40: 900 | Y40: 825
A41: Feb 19, 2024 | B41: 89400 | C41: 96900 | D41: 95732 | E41: 85150 | F41: 83923 | G41: 91050 | H41: 14 | I41: 13.75 | J41: 65000 | K41: 165000 | L41: 77200 | M41: 920 | N41: 6425 | O41: 5225 | P41: 3375 | Q41: 100 | R41: 183.5 | S41: 385 | T41: 1210 | U41: 2085 | V41: 9620 | W41: 11600 | X41: 900 | Y41: 825
A42: Feb 20, 2024 | B42: 89400 | C42: 96750 | D42: 95671 | E42: 85150 | F42: 83923 | G42: 91050 | H42: 14 | I42: 13.75 | J42: 65000 | K42: 165000 | L42: 77200 | M42: 910 | N42: 6425 | O42: 5225 | P42: 3375 | Q42: 100 | R42: 183.5 | S42: 385 | T42: 1210 | U42: 2085 | V42: 9620 | W42: 11600 | X42: 900 | Y42: 825
A43: Feb 21, 2024 | B43: 88750 | C43: 96150 | D43: 95489 | E43: 85050 | F43: 83878 | G43: 90950 | H43: 14 | I43: 13.75 | J43: 65000 | K43: 165000 | L43: 77200 | M43: 910 | N43: 6425 | O43: 5225 | P43: 3375 | Q43: 100 | R43: 183.5 | S43: 385 | T43: 1210 | U43: 2085 | V43: 9620 | W43: 11600 | X43: 900 | Y43: 825
A44: Feb 22, 2024 | B44: 88800 | C44: 96150 | D44: 95504 | E44: 85050 | F44: 83899 | G44: 90950 | H44: 14 | I44: 13.75 | J44: 65000 | K44: 165000 | L44: 77200 | M44: 910 | N44: 6425 | O44: 5225 | P44: 3375 | Q44: 100 | R44: 183.5 | S44: 385 | T44: 1210 | U44: 2085 | V44: 9620 | W44: 11600 | X44: 900 | Y44: 825
A45: Mar 19, 2024 | B45: 107500 | C45: 112550 | D45: 111376 | E45: 98750 | F45: 97424 | G45: 104650 | H45: 13.5 | I45: 13.83 | J45: 72000 | K45: 191300 | L45: 91000 | M45: 1075 | N45: 8165 | O45: 6655 | P45: 4485 | Q45: 121.5 | R45: 217.5 | S45: 432.5 | T45: 1260 | U45: 2150 | V45: 9620 | W45: 11600 | X45: 1095 | Y45: 1015
A46: Mar 25, 2024 | B46: 107900 | C46: 112450 | D46: 111548 | E46: 99250 | F46: 97988 | G46: 105150 | H46: 13.68 | I46: 13.85 | J46: 72000 | K46: 195800 | L46: 91500 | M46: 1083 | N46: 8175 | O46: 6665 | P46: 4485 | Q46: 128 | R46: 227.5 | S46: 443.5 | T46: 1320 | U46: 2220 | V46: 9620 | W46: 11600 | X46: 1100 | Y46: 1040
... A474: Jan 30, 2026 | B474: 157000 | C474: 160500 | D474: 159309 | E474: 158000 | F474: 158082 | G474: 163550 | H474: 20.9 | I474: 19.5 | J474: 142500 | K474: 273200 | L474: 148500 | M474: 2070 | N474: 14900 | O474: 12125 | P474: 9025 | Q474: 195 | R474: 320 | S474: 595 | T474: 3240 | U474: 4965 | V474: 15075 | W474: 16500 | X474: 2175 | Y474: 2170
A475: Feb 06, 2026 | B475: 131000 | C475: 134500 | D475: 136038 | E475: 132500 | F475: 134096 | G475: 139000 | H475: N/A | I475: N/A | J475: 126000 | K475: 250000 | L475: 122000 | M475: N/A | N475: 12925 | O475: 10600 | P475: 7725 | Q475: N/A | R475: N/A | S475: N/A | T475: 2875 | U475: 4375 | V475: 13000 | W475: 13900 | X475: N/A | Y475: N/A
A476: Feb 09, 2026 | B476: 132000 | C476: 135500 | D476: 134390 | E476: 133000 | F476: 134819 | G476: 139500 | H476: N/A | I476: N/A | J476: 125000 | K476: 250000 | L476: 122500 | M476: N/A | N476: 13015 | O476: 10675 | P476: 7785 | Q476: N/A | R476: N/A | S476: N/A | T476: 2875 | U476: 4375 | V476: 13000 | W476: 13900 | X476: N/A | Y476: N/A
A477: Feb 10, 2026 | B477: 132500 | C477: 136000 | D477: 134406 | E477: 133750 | F477: 135598 | G477: 140250 | H477: N/A | I477: N/A | J477: 125000 | K477: 250000 | L477: 123200 | M477: N/A | N477: 13015 | O477: 10675 | P477: 7785 | Q477: N/A | R477: N/A | S477: N/A | T477: 2875 | U477: 4375 | V477: 13000 | W477: 13900 | X477: N/A | Y477: N/A
A478: Feb 11, 2026 | B478: 134500 | C478: 138000 | D478: 138483 | E478: 134500 | F478: 136050 | G478: 141000 | H478: N/A | I478: N/A | J478: 125000 | K478: 250000 | L478: 123950 | M478: N/A | N478: 13090 | O478: 10730 | P478: 7840 | Q478: N/A | R478: N/A | S478: N/A | T478: 2915 | U478: 4415 | V478: 13100 | W478: 14000 | X478: N/A | Y478: N/A
A479: Feb 12, 2026 | B479: 139000 | C479: 142500 | D479: 142168 | E479: 136500 | F479: 137962 | G479: 143000 | H479: N/A | I479: N/A | J479: 125000 | K479: 250000 | L479: 125950 | M479: N/A | N479: 13250 | O479: 10840 | P479: 7940 | Q479: N/A | R479: N/A | S479: N/A | T479: 3065 | U479: 4575 | V479: 13250 | W479: 14200 | X479: N/A | Y479: N/A
A480: Feb 13, 2026 | B480: 140250 | C480: 143750 | D480: 143223 | E480: 137500 | F480: 139006 | G480: 144000 | H480: N/A | I480: N/A | J480: 125000 | K480: 238700 | L480: 126950 | M480: N/A | N480: 13375 | O480: 10925 | P480: 8000 | Q480: N/A | R480: N/A | S480: N/A | T480: 3125 | U480: 4640 | V480: 13340 | W480: 14300 | X480: N/A | Y480: N/A
A481: Feb 24, 2026 | B481: 148500 | C481: 152000 | D481: 152025 | E481: 144500 | F481: 145759 | G481: 151000 | H481: N/A | I481: N/A | J481: 125000 | K481: 238700 | L481: 133450 | M481: N/A | N481: 14000 | O481: 11300 | P481: 8200 | Q481: N/A | R481: N/A | S481: N/A | T481: 3250 | U481: 4825 | V481: 13600 | W481: 14700 | X481: N/A | Y481: N/A
A482: Feb 25, 2026 | B482: 158250 | C482: 161750 | D482: 161243 | E482: 153000 | F482: 153111 | G482: 159500 | H482: N/A | I482: N/A | J482: 125000 | K482: 238700 | L482: 141450 | M482: N/A | N482: 14950 | O482: 11850 | P482: 8600 | Q482: N/A | R482: N/A | S482: N/A | T482: 3600 | U482: 5400 | V482: 14100 | W482: 15300 | X482: N/A | Y482: N/A
A483: Feb 26, 2026 | B483: 169500 | C483: 173000 | D483: 172310 | E483: 163000 | F483: 161938 | G483: 169500 | H483: N/A | I483: N/A | J483: 125000 | K483: 238700 | L483: 151450 | M483: N/A | N483: 15850 | O483: 12500 | P483: 9100 | Q483: N/A | R483: N/A | S483: N/A | T483: 3800 | U483: 5700 | V483: 14500 | W483: 15800 | X483: N/A | Y483: N/A
A484: Feb 27, 2026 | B484: 168500 | C484: 172000 | D484: 171196 | E484: 162600 | F484: 161638 | G484: 169100 | H484: N/A | I484: N/A | J484: 125000 | K484: 260750 | L484: 151050 | M484: N/A | N484: 15850 | O484: 12500 | P484: 9100 | Q484: N/A | R484: N/A | S484: N/A | T484: 3725 | U484: 5600 | V484: 14075 | W484: 15350 | X484: N/A | Y484: N/A
A485: Mar 02, 2026 | B485: 169000 | C485: 172500 | D485: 171847 | E485: 162600 | F485: 161742 | G485: 169100 | H485: N/A | I485: N/A | J485: 125000 | K485: 260750 | L485: 151050 | M485: N/A | N485: 15850 | O485: 12500 | P485: 9100 | Q485: N/A | R485: N/A | S485: N/A | T485: 3685 | U485: 5525 | V485: 13775 | W485: 15050 | X485: N/A | Y485: N/A
A486: Mar 03, 2026 | B486: 157500 | C486: 161000 | D486: 161266 | E486: 155600 | F486: 155853 | G486: 162100 | H486: N/A | I486: N/A | J486: 121500 | K486: 260750 | L486: 144050 | M486: N/A | N486: 15150 | O486: 12125 | P486: 8850 | Q486: N/A | R486: N/A | S486: N/A | T486: 3565 | U486: 5350 | V486: 13225 | W486: 14475 | X486: N/A | Y486: N/A
... A492: Mar 11, 2026 | B492: 155750 | C492: 159000 | D492: 159393 | E492: 152000 | F492: 152874 | G492: 158500 | H492: N/A | I492: N/A | J492: 112500 | K492: 273500 | L492: 140050 | M492: N/A | N492: 15300 | O492: 12325 | P492: 9075 | Q492: N/A | R492: N/A | S492: N/A | T492: 3440 | U492: 5140 | V492: 13175 | W492: 14350 | X492: N/A | Y492: N/A

Sheet lc2401
A1: Date | B1: Latest | C1: Prev.Close | D1: Volume | E1: Prev.Settle | F1: Open | G1: Open Interest | H1: Latest % | I1: O.I %
A2: Nov 08, 2023 15:00:00 | B2: 145350 | C2: 142550 | D2: 584534 | E2: 143800 | F2: 141900 | G2: 105467 | H2: =+B2/E2-1 -> 0.01077886
A3: Nov 09, 2023 15:00:00 | B3: 144150 | C3: 145350 | D3: 323961 | E3: 143100 | F3: 145300 | G3: 106948 | H3: =+B3/E3-1 -> 0.0073375262 | I3: =+G3/G2-1 -> 0.014042307
A4: Nov 10, 2023 15:00:00 | B4: 148900 | C4: 144150 | D4: 374012 | E4: 144600 | F4: 144600 | G4: 98275 | H4: =+B4/E4-1 -> 0.029737206 | I4: =+G4/G3-1 -> -0.081095486
A5: Nov 13, 2023 15:00:00 | B5: 141650 | C5: 148900 | D5: 382854 | E5: 147500 | F5: 149800 | G5: 96195 | H5: =+B5/E5-1 -> -0.039661017 | I5: =+G5/G4-1 -> -0.021165098
A6: Nov 14, 2023 15:00:00 | B6: 142550 | C6: 141650 | D6: 367056 | E6: 147200 | F6: 141150 | G6: 99509 | H6: =+B6/E6-1 -> -0.031589674 | I6: =+G6/G5-1 -> 0.034450855
A7: Nov 15, 2023 15:00:00 | B7: 142600 | C7: 142550 | D7: 269895 | E7: 142800 | F7: 144000 | G7: 107801 | H7: =+B7/E7-1 -> -0.0014005602 | I7: =+G7/G6-1 -> 0.083329146
A8: Nov 16, 2023 15:00:00 | B8: 140900 | C8: 142600 | D8: 234117 | E8: 142800 | F8: 142500 | G8: 113750 | H8: =+B8/E8-1 -> -0.013305322 | I8: =+G8/G7-1 -> 0.055185017
A9: Nov 17, 2023 15:00:00 | B9: 138000 | C9: 140900 | D9: 260599 | E9: 141450 | F9: 139500 | G9: 113625 | H9: =+B9/E9-1 -> -0.024390244 | I9: =+G9/G8-1 -> -0.0010989011
A10: Nov 20, 2023 15:00:00 | B10: 137200 | C10: 138000 | D10: 242544 | E10: 138800 | F10: 138000 | G10: 117451 | H10: =+B10/E10-1 -> -0.011527378 | I10: =+G10/G9-1 -> 0.033672167
A11: Nov 21, 2023 15:00:00 | B11: 132300 | C11: 137200 | D11: 342945 | E11: 138600 | F11: 137900 | G11: 119970 | H11: =+B11/E11-1 -> -0.045454545 | I11: =+G11/G10-1 -> 0.021447242
A12: Nov 22, 2023 15:00:00 | B12: 124700 | C12: 132300 | D12: 531056 | E12: 134050 | F12: 132300 | G12: 117807 | H12: =+B12/E12-1 -> -0.069750093 | I12: =+G12/G11-1 -> -0.018029507
A13: Nov 23, 2023 15:00:00 | B13: 124800 | C13: 124700 | D13: 581420 | E13: 127600 | F13: 124400 | G13: 115316 | H13: =+B13/E13-1 -> -0.021943574 | I13: =+G13/G12-1 -> -0.021144754
A14: Nov 24, 2023 15:00:00 | B14: 124050 | C14: 124800 | D14: 699474 | E14: 122900 | F14: 125050 | G14: 121691 | H14: =+B14/E14-1 -> 0.009357201 | I14: =+G14/G13-1 -> 0.055282875
... A49: Jan 15, 2024 15:00:00 | B49: 96800 | C49: 97400 | D49: 63 | E49: 97500 | F49: 97000 | G49: 0 | H49: =+B49/E49-1 -> -0.0071794872 | I49: =+G49/G48-1 -> -1

Sheet lc2402
A1: Date | B1: Latest | C1: Prev.Close | D1: Volume | E1: Prev.Settle | F1: Open | G1: Open Interest | H1: Var % | I1: O.I %
A2: Nov 08, 2023 15:00:00 | B2: 136000 | C2: 134250 | D2: 3354 | E2: 135750 | F2: 134250 | G2: 5489 | H2: =+B2/E2-1 -> 0.0018416206
A3: Nov 09, 2023 15:00:00 | B3: 135700 | C3: 136000 | D3: 2076 | E3: 134350 | F3: 136000 | G3: 5501 | H3: =+B3/E3-1 -> 0.010048381 | I3: =+G3/G2-1 -> 0.0021861906
A4: Nov 10, 2023 15:00:00 | B4: 139800 | C4: 135700 | D4: 2056 | E4: 136100 | F4: 136200 | G4: 5262 | H4: =+B4/E4-1 -> 0.027185893 | I4: =+G4/G3-1 -> -0.043446646
A5: Nov 13, 2023 15:00:00 | B5: 134550 | C5: 139800 | D5: 2563 | E5: 138700 | F5: 139000 | G5: 5545 | H5: =+B5/E5-1 -> -0.029920692 | I5: =+G5/G4-1 -> 0.053781832
A6: Nov 14, 2023 15:00:00 | B6: 136250 | C6: 134550 | D6: 2467 | E6: 138950 | F6: 134050 | G6: 5802 | H6: =+B6/E6-1 -> -0.01943145 | I6: =+G6/G5-1 -> 0.046348061
A7: Nov 15, 2023 15:00:00 | B7: 136700 | C7: 136250 | D7: 1916 | E7: 136150 | F7: 139800 | G7: 6023 | H7: =+B7/E7-1 -> 0.0040396621 | I7: =+G7/G6-1 -> 0.038090314
A8: Nov 16, 2023 15:00:00 | B8: 135900 | C8: 136700 | D8: 1123 | E8: 136950 | F8: 136050 | G8: 6118 | H8: =+B8/E8-1 -> -0.0076670318 | I8: =+G8/G7-1 -> 0.015772871
A9: Nov 17, 2023 15:00:00 | B9: 133400 | C9: 135900 | D9: 1745 | E9: 136000 | F9: 134900 | G9: 5920 | H9: =+B9/E9-1 -> -0.019117647 | I9: =+G9/G8-1 -> -0.032363517
A10: Nov 20, 2023 15:00:00 | B10: 131900 | C10: 133400 | D10: 1137 | E10: 133650 | F10: 133600 | G10: 5875 | H10: =+B10/E10-1 -> -0.013093902 | I10: =+G10/G9-1 -> -0.0076013514
A11: Nov 21, 2023 15:00:00 | B11: 127750 | C11: 131900 | D11: 2244 | E11: 133100 | F11: 131100 | G11: 5781 | H11: =+B11/E11-1 -> -0.040195342 | I11: =+G11/G10-1 -> -0.016
A12: Nov 22, 2023 15:00:00 | B12: 119900 | C12: 127750 | D12: 8008 | E12: 128900 | F12: 126600 | G12: 5793 | H12: =+B12/E12-1 -> -0.069821567 | I12: =+G12/G11-1 -> 0.0020757654
A13: Nov 23, 2023 15:00:00 | B13: 119600 | C13: 119900 | D13: 5453 | E13: 122450 | F13: 119500 | G13: 6045 | H13: =+B13/E13-1 -> -0.023274806 | I13: =+G13/G12-1 -> 0.043500777
A14: Nov 24, 2023 15:00:00 | B14: 119100 | C14: 119600 | D14: 4123 | E14: 118500 | F14: 120500 | G14: 6327 | H14: =+B14/E14-1 -> 0.0050632911 | I14: =+G14/G13-1 -> 0.046650124
... A70: Feb 21, 2024 15:00:00 | B70: 99250 | C70: 90000 | D70: 16 | E70: 90450 | F70: 95800 | G70: 351 | H70: =+B70/E70-1 -> 0.097291321 | I70: =+G70/G69-1 -> -0.064

Sheet lc2403
A1: Date | B1: Latest | C1: Prev.Close | D1: Volume | E1: Prev.Settle | F1: Open | G1: Open Interest | H1: Var % | I1: O.I %
A2: Nov 08, 2023 15:00:00 | B2: 131700 | C2: 130900 | D2: 1747 | E2: 132400 | F2: 130600 | G2: 3464 | H2: =+B2/E2-1 -> -0.0052870091
A3: Nov 09, 2023 15:00:00 | B3: 131850 | C3: 131700 | D3: 847 | E3: 130500 | F3: 131600 | G3: 3495 | H3: =+B3/E3-1 -> 0.010344828 | I3: =+G3/G2-1 -> 0.0089491917
A4: Nov 10, 2023 15:00:00 | B4: 135500 | C4: 131850 | D4: 1223 | E4: 131750 | F4: 131900 | G4: 3412 | H4: =+B4/E4-1 -> 0.028462998 | I4: =+G4/G3-1 -> -0.023748212
A5: Nov 13, 2023 15:00:00 | B5: 131500 | C5: 135500 | D5: 1474 | E5: 134300 | F5: 135700 | G5: 3497 | H5: =+B5/E5-1 -> -0.020848846 | I5: =+G5/G4-1 -> 0.024912075
A6: Nov 14, 2023 15:00:00 | B6: 132950 | C6: 131500 | D6: 1432 | E6: 134450 | F6: 131400 | G6: 3233 | H6: =+B6/E6-1 -> -0.011156564 | I6: =+G6/G5-1 -> -0.07549328
A7: Nov 15, 2023 15:00:00 | B7: 133200 | C7: 132950 | D7: 506 | E7: 133000 | F7: 133100 | G7: 3227 | H7: =+B7/E7-1 -> 0.0015037594 | I7: =+G7/G6-1 -> -0.0018558614
A8: Nov 16, 2023 15:00:00 | B8: 132600 | C8: 133200 | D8: 469 | E8: 133700 | F8: 133200 | G8: 3297 | H8: =+B8/E8-1 -> -0.0082273747 | I8: =+G8/G7-1 -> 0.021691974
A9: Nov 17, 2023 15:00:00 | B9: 131250 | C9: 132600 | D9: 826 | E9: 132950 | F9: 132200 | G9: 3310 | H9: =+B9/E9-1 -> -0.012786762 | I9: =+G9/G8-1 -> 0.0039429785
A10: Nov 20, 2023 15:00:00 | B10: 128650 | C10: 131250 | D10: 927 | E10: 131600 | F10: 131200 | G10: 3393 | H10: =+B10/E10-1 -> -0.022416413 | I10: =+G10/G9-1 -> 0.025075529
A11: Nov 21, 2023 15:00:00 | B11: 125400 | C11: 128650 | D11: 900 | E11: 130450 | F11: 128900 | G11: 3548 | H11: =+B11/E11-1 -> -0.03871215 | I11: =+G11/G10-1 -> 0.045682287
A12: Nov 22, 2023 15:00:00 | B12: 117900 | C12: 125400 | D12: 2137 | E12: 126650 | F12: 125700 | G12: 3822 | H12: =+B12/E12-1 -> -0.069088038 | I12: =+G12/G11-1 -> 0.077226607
A13: Nov 23, 2023 15:00:00 | B13: 117900 | C13: 117900 | D13: 2871 | E13: 120800 | F13: 117950 | G13: 3830 | H13: =+B13/E13-1 -> -0.024006623 | I13: =+G13/G12-1 -> 0.002093145
A14: Nov 24, 2023 15:00:00 | B14: 116900 | C14: 117900 | D14: 2661 | E14: 116300 | F14: 118300 | G14: 4409 | H14: =+B14/E14-1 -> 0.0051590714 | I14: =+G14/G13-1 -> 0.15117493
... A70: Feb 21, 2024 15:00:00 | B70: 93700 | C70: 90150 | D70: 4808 | E70: 90800 | F70: 91000 | G70: 13102 | H70: =+B70/E70-1 -> 0.031938326 | I70: =+G70/G69-1 -> -0.072687381

Sheet lc2404
A1: Date | B1: Latest | C1: Prev.Close | D1: Volume | E1: Prev.Settle | F1: Open | G1: Open Interest | H1: Var % | I1: O.I %
A2: Nov 08, 2023 15:00:00 | B2: 130200 | C2: 128800 | D2: 798 | E2: 131000 | F2: 128850 | G2: 3424 | H2: =+B2/E2-1 -> -0.0061068702
A3: Nov 09, 2023 15:00:00 | B3: 130400 | C3: 130200 | D3: 718 | E3: 128950 | F3: 129750 | G3: 3565 | H3: =+B3/E3-1 -> 0.011244668 | I3: =+G3/G2-1 -> 0.041179907
A4: Nov 10, 2023 15:00:00 | B4: 134650 | C4: 130400 | D4: 1039 | E4: 130000 | F4: 130250 | G4: 3891 | H4: =+B4/E4-1 -> 0.035769231 | I4: =+G4/G3-1 -> 0.0914446
A5: Nov 13, 2023 15:00:00 | B5: 130650 | C5: 134650 | D5: 819 | E5: 133100 | F5: 136200 | G5: 4076 | H5: =+B5/E5-1 -> -0.018407213 | I5: =+G5/G4-1 -> 0.047545618
A6: Nov 14, 2023 15:00:00 | B6: 131100 | C6: 130650 | D6: 838 | E6: 133050 | F6: 129950 | G6: 3965 | H6: =+B6/E6-1 -> -0.014656144 | I6: =+G6/G5-1 -> -0.027232581
A7: Nov 15, 2023 15:00:00 | B7: 131700 | C7: 131100 | D7: 421 | E7: 131550 | F7: 131900 | G7: 4059 | H7: =+B7/E7-1 -> 0.0011402509 | I7: =+G7/G6-1 -> 0.02370744
A8: Nov 16, 2023 15:00:00 | B8: 131350 | C8: 131700 | D8: 348 | E8: 132300 | F8: 131450 | G8: 4205 | H8: =+B8/E8-1 -> -0.00718065 | I8: =+G8/G7-1 -> 0.035969451
A9: Nov 17, 2023 15:00:00 | B9: 130350 | C9: 131350 | D9: 819 | E9: 131750 | F9: 131750 | G9: 4508 | H9: =+B9/E9-1 -> -0.010626186 | I9: =+G9/G8-1 -> 0.072057075
A10: Nov 20, 2023 15:00:00 | B10: 126650 | C10: 130350 | D10: 896 | E10: 130550 | F10: 129350 | G10: 4289 | H10: =+B10/E10-1 -> -0.029873612 | I10: =+G10/G9-1 -> -0.048580302
A11: Nov 21, 2023 15:00:00 | B11: 124350 | C11: 126650 | D11: 545 | E11: 128950 | F11: 127750 | G11: 4282 | H11: =+B11/E11-1 -> -0.035672741 | I11: =+G11/G10-1 -> -0.0016320821
A12: Nov 22, 2023 15:00:00 | B12: 117900 | C12: 124350 | D12: 1531 | E12: 125200 | F12: 124350 | G12: 4137 | H12: =+B12/E12-1 -> -0.058306709 | I12: =+G12/G11-1 -> -0.033862681
A13: Nov 23, 2023 15:00:00 | B13: 116500 | C13: 117900 | D13: 2505 | E13: 119550 | F13: 117900 | G13: 4055 | H13: =+B13/E13-1 -> -0.025512338 | I13: =+G13/G12-1 -> -0.019821126
A14: Nov 24, 2023 15:00:00 | B14: 116750 | C14: 116500 | D14: 1738 | E14: 115350 | F14: 117700 | G14: 4498 | H14: =+B14/E14-1 -> 0.012136974 | I14: =+G14/G13-1 -> 0.10924784
... A91: Apr 16, 2024 15:00:00 | B91: 106200 | C91: 111250 | D91: 342 | E91: 111850 | F91: 111850 | G91: 0 | H91: =+B91/E91-1 -> -0.050514081 | I91: =+G91/G90-1 -> -1

Sheet lc2405
A1: Date | B1: Latest | C1: Prev.Close | D1: Volume | E1: Prev.Settle | F1: Open | G1: Open Interest | H1: Var % | I1: O.I %
A2: Nov 08, 2023 15:00:00 | B2: 128350 | C2: 126650 | D2: 1867 | E2: 128700 | F2: 126050 | G2: 5244 | H2: =+B2/E2-1 -> -0.0027195027
A3: Nov 09, 2023 15:00:00 | B3: 128600 | C3: 128350 | D3: 833 | E3: 127050 | F3: 128150 | G3: 5277 | H3: =+B3/E3-1 -> 0.012199921 | I3: =+G3/G2-1 -> 0.0062929062
A4: Nov 10, 2023 15:00:00 | B4: 132650 | C4: 128600 | D4: 3016 | E4: 128200 | F4: 128900 | G4: 5316 | H4: =+B4/E4-1 -> 0.034711388 | I4: =+G4/G3-1 -> 0.0073905628
A5: Nov 13, 2023 15:00:00 | B5: 129200 | C5: 132650 | D5: 2919 | E5: 131350 | F5: 133000 | G5: 5537 | H5: =+B5/E5-1 -> -0.016368481 | I5: =+G5/G4-1 -> 0.041572611
A6: Nov 14, 2023 15:00:00 | B6: 129150 | C6: 129200 | D6: 2449 | E6: 131800 | F6: 130000 | G6: 5714 | H6: =+B6/E6-1 -> -0.020106222 | I6: =+G6/G5-1 -> 0.031966769
A7: Nov 15, 2023 15:00:00 | B7: 130200 | C7: 129150 | D7: 2051 | E7: 129600 | F7: 129900 | G7: 5750 | H7: =+B7/E7-1 -> 0.0046296296 | I7: =+G7/G6-1 -> 0.006300315
A8: Nov 16, 2023 15:00:00 | B8: 130100 | C8: 130200 | D8: 1289 | E8: 130550 | F8: 130050 | G8: 5748 | H8: =+B8/E8-1 -> -0.0034469552 | I8: =+G8/G7-1 -> -0.00034782609
A9: Nov 17, 2023 15:00:00 | B9: 129700 | C9: 130100 | D9: 1631 | E9: 130350 | F9: 130000 | G9: 5846 | H9: =+B9/E9-1 -> -0.0049865746 | I9: =+G9/G8-1 -> 0.017049408
A10: Nov 20, 2023 15:00:00 | B10: 125000 | C10: 129700 | D10: 3310 | E10: 129550 | F10: 129400 | G10: 6229 | H10: =+B10/E10-1 -> -0.035121575 | I10: =+G10/G9-1 -> 0.065514882
A11: Nov 21, 2023 15:00:00 | B11: 123100 | C11: 125000 | D11: 2759 | E11: 127400 | F11: 126300 | G11: 6303 | H11: =+B11/E11-1 -> -0.033751962 | I11: =+G11/G10-1 -> 0.011879917
A12: Nov 22, 2023 15:00:00 | B12: 116650 | C12: 123100 | D12: 5379 | E12: 123950 | F12: 123600 | G12: 6568 | H12: =+B12/E12-1 -> -0.058894716 | I12: =+G12/G11-1 -> 0.042043471
A13: Nov 23, 2023 15:00:00 | B13: 115350 | C13: 116650 | D13: 5868 | E13: 118550 | F13: 116400 | G13: 6694 | H13: =+B13/E13-1 -> -0.02699283 | I13: =+G13/G12-1 -> 0.019183922
A14: Nov 24, 2023 15:00:00 | B14: 116250 | C14: 115350 | D14: 4713 | E14: 114200 | F14: 115950 | G14: 6910 | H14: =+B14/E14-1 -> 0.017950963 | I14: =+G14/G13-1 -> 0.032267702
... A111: May 16, 2024 15:00:00 | B111: 103400 | C111: 102200 | D111: 17 | E111: 101950 | F111: 103450 | G111: 458 | H111: =+B111/E111-1 -> 0.014222658 | I111: =+G111/G110-1 -> -0.76880363

Sheet lc2406
A1: Date | B1: Latest | C1: Prev.Close | D1: Volume | E1: Prev.Settle | F1: Open | G1: Open Interest | H1: Var % | I1: O.I %
A2: Nov 08, 2023 15:00:00 | B2: 126100 | C2: 123900 | D2: 412 | E2: 126550 | F2: 124100 | G2: 3897 | H2: =+B2/E2-1 -> -0.0035559068
A3: Nov 09, 2023 15:00:00 | B3: 126100 | C3: 126100 | D3: 224 | E3: 124450 | F3: 125800 | G3: 3880 | H3: =+B3/E3-1 -> 0.013258337 | I3: =+G3/G2-1 -> -0.00436233
A4: Nov 10, 2023 15:00:00 | B4: 130550 | C4: 126100 | D4: 969 | E4: 125850 | F4: 126650 | G4: 3855 | H4: =+B4/E4-1 -> 0.037346047 | I4: =+G4/G3-1 -> -0.006443299
A5: Nov 13, 2023 15:00:00 | B5: 127250 | C5: 130550 | D5: 482 | E5: 129500 | F5: 131800 | G5: 3868 | H5: =+B5/E5-1 -> -0.017374517 | I5: =+G5/G4-1 -> 0.0033722438
A6: Nov 14, 2023 15:00:00 | B6: 127100 | C6: 127250 | D6: 539 | E6: 130300 | F6: 126400 | G6: 3850 | H6: =+B6/E6-1 -> -0.024558711 | I6: =+G6/G5-1 -> -0.0046535677
A7: Nov 15, 2023 15:00:00 | B7: 128150 | C7: 127100 | D7: 390 | E7: 127150 | F7: 127200 | G7: 3864 | H7: =+B7/E7-1 -> 0.0078647267 | I7: =+G7/G6-1 -> 0.0036363636
A8: Nov 16, 2023 15:00:00 | B8: 128150 | C8: 128150 | D8: 326 | E8: 128650 | F8: 128150 | G8: 3863 | H8: =+B8/E8-1 -> -0.0038865138 | I8: =+G8/G7-1 -> -0.00025879917
A9: Nov 17, 2023 15:00:00 | B9: 127900 | C9: 128150 | D9: 562 | E9: 128650 | F9: 127650 | G9: 3865 | H9: =+B9/E9-1 -> -0.0058297707 | I9: =+G9/G8-1 -> 0.00051773233
A10: Nov 20, 2023 15:00:00 | B10: 123150 | C10: 127900 | D10: 1027 | E10: 128000 | F10: 127700 | G10: 3844 | H10: =+B10/E10-1 -> -0.037890625 | I10: =+G10/G9-1 -> -0.0054333765
A11: Nov 21, 2023 15:00:00 | B11: 121750 | C11: 123150 | D11: 918 | E11: 124900 | F11: 123700 | G11: 3872 | H11: =+B11/E11-1 -> -0.025220176 | I11: =+G11/G10-1 -> 0.0072840791
A12: Nov 22, 2023 15:00:00 | B12: 115250 | C12: 121750 | D12: 1698 | E12: 122350 | F12: 121400 | G12: 4026 | H12: =+B12/E12-1 -> -0.058030241 | I12: =+G12/G11-1 -> 0.039772727
A13: Nov 23, 2023 15:00:00 | B13: 113800 | C13: 115250 | D13: 2141 | E13: 116900 | F13: 115300 | G13: 4060 | H13: =+B13/E13-1 -> -0.026518392 | I13: =+G13/G12-1 -> 0.0084451068
A14: Nov 24, 2023 15:00:00 | B14: 115550 | C14: 113800 | D14: 1328 | E14: 113200 | F14: 115100 | G14: 4141 | H14: =+B14/E14-1 -> 0.020759717 | I14: =+G14/G13-1 -> 0.019950739
... A133: Jun 17, 2024 15:00:00 | B133: 96500 | C133: 97000 | D133: 60 | E133: 97250 | F133: 96000 | G133: 0 | H133: =+B133/E133-1 -> -0.0077120823 | I133: =+G133/G132-1 -> -1

Sheet lc2407
A1: Date | B1: Latest | C1: Prev.Close | D1: Volume | E1: Prev.Settle | F1: Open | G1: Open Interest | H1: Var % | I1: O.I %
A2: Nov 08, 2023 15:00:00 | B2: 124650 | C2: 0 | D2: 56821 | E2: 124700 | F2: 122500 | G2: 53080 | H2: =+B2/E2-1 -> -0.00040096231 | I2: 0
A3: Nov 09, 2023 15:00:00 | B3: 124700 | C3: 124650 | D3: 26989 | E3: 123200 | F3: 124600 | G3: 52858 | H3: =+B3/E3-1 -> 0.012175325 | I3: =+G3/G2-1 -> -0.0041823662
A4: Nov 10, 2023 15:00:00 | B4: 129250 | C4: 124700 | D4: 66824 | E4: 124400 | F4: 125150 | G4: 53766 | H4: =+B4/E4-1 -> 0.038987138 | I4: =+G4/G3-1 -> 0.0171781
A5: Nov 13, 2023 15:00:00 | B5: 125600 | C5: 129250 | D5: 54145 | E5: 128150 | F5: 130050 | G5: 55395 | H5: =+B5/E5-1 -> -0.019898556 | I5: =+G5/G4-1 -> 0.030297958
A6: Nov 14, 2023 15:00:00 | B6: 125600 | C6: 125600 | D6: 44718 | E6: 128400 | F6: 125350 | G6: 55084 | H6: =+B6/E6-1 -> -0.021806854 | I6: =+G6/G5-1 -> -0.0056142251
A7: Nov 15, 2023 15:00:00 | B7: 127000 | C7: 125600 | D7: 46894 | E7: 125850 | F7: 127300 | G7: 57820 | H7: =+B7/E7-1 -> 0.0091378625 | I7: =+G7/G6-1 -> 0.049669596
A8: Nov 16, 2023 15:00:00 | B8: 127150 | C8: 127000 | D8: 32690 | E8: 127200 | F8: 127000 | G8: 59678 | H8: =+B8/E8-1 -> -0.00039308176 | I8: =+G8/G7-1 -> 0.03213421
A9: Nov 17, 2023 15:00:00 | B9: 127000 | C9: 127150 | D9: 38737 | E9: 127400 | F9: 126900 | G9: 60858 | H9: =+B9/E9-1 -> -0.0031397174 | I9: =+G9/G8-1 -> 0.019772781
A10: Nov 20, 2023 15:00:00 | B10: 122400 | C10: 127000 | D10: 74280 | E10: 127050 | F10: 126500 | G10: 64639 | H10: =+B10/E10-1 -> -0.036599764 | I10: =+G10/G9-1 -> 0.062128233
A11: Nov 21, 2023 15:00:00 | B11: 121200 | C11: 122400 | D11: 68703 | E11: 124900 | F11: 122750 | G11: 67378 | H11: =+B11/E11-1 -> -0.029623699 | I11: =+G11/G10-1 -> 0.042373799
A12: Nov 22, 2023 15:00:00 | B12: 115150 | C12: 121200 | D12: 132920 | E12: 121550 | F12: 121000 | G12: 72059 | H12: =+B12/E12-1 -> -0.052653229 | I12: =+G12/G11-1 -> 0.069473715
A13: Nov 23, 2023 15:00:00 | B13: 113800 | C13: 115150 | D13: 123231 | E13: 116650 | F13: 114500 | G13: 74096 | H13: =+B13/E13-1 -> -0.024432062 | I13: =+G13/G12-1 -> 0.028268502
A14: Nov 24, 2023 15:00:00 | B14: 114850 | C14: 113800 | D14: 106683 | E14: 112950 | F14: 114500 | G14: 77344 | H14: =+B14/E14-1 -> 0.016821602 | I14: =+G14/G13-1 -> 0.043835025
... A144: Jul 11, 2024 15:00:00 | B144: 86900 | C144: 86800 | D144: 101 | E144: 87750 | F144: 85800 | G144: 52 | H144: =+B144/E144-1 -> -0.0096866097 | I144: =+G144/G143-1 -> 0

Sheet Contrato 2407
A1: Date | B1: Latest | C1: Prev.Close | D1: Volume | E1: Prev.Settle | F1: Open | G1: Open Interest | H1: Var % | I1: O.I %
A2: Nov 08, 2023 15:00:00 | B2: 124650 | C2: 0 | D2: 56821 | E2: 124700 | F2: 122500 | G2: 53080 | H2: -0.00040096231 | I2: 0
A3: Nov 09, 2023 15:00:00 | B3: 124700 | C3: 124650 | D3: 26989 | E3: 123200 | F3: 124600 | G3: 52858 | H3: 0.012175325 | I3: -0.0041823662
A4: Nov 10, 2023 15:00:00 | B4: 129250 | C4: 124700 | D4: 66824 | E4: 124400 | F4: 125150 | G4: 53766 | H4: 0.038987138 | I4: 0.0171781
A5: Nov 13, 2023 15:00:00 | B5: 125600 | C5: 129250 | D5: 54145 | E5: 128150 | F5: 130050 | G5: 55395 | H5: -0.019898556 | I5: 0.030297958
A6: Nov 14, 2023 15:00:00 | B6: 125600 | C6: 125600 | D6: 44718 | E6: 128400 | F6: 125350 | G6: 55084 | H6: -0.021806854 | I6: -0.0056142251
A7: Nov 15, 2023 15:00:00 | B7: 127000 | C7: 125600 | D7: 46894 | E7: 125850 | F7: 127300 | G7: 57820 | H7: 0.0091378625 | I7: 0.049669596
A8: Nov 16, 2023 15:00:00 | B8: 127150 | C8: 127000 | D8: 32690 | E8: 127200 | F8: 127000 | G8: 59678 | H8: -0.00039308176 | I8: 0.03213421
A9: Nov 17, 2023 15:00:00 | B9: 127000 | C9: 127150 | D9: 38737 | E9: 127400 | F9: 126900 | G9: 60858 | H9: -0.0031397174 | I9: 0.019772781
A10: Nov 20, 2023 15:00:00 | B10: 122400 | C10: 127000 | D10: 74280 | E10: 127050 | F10: 126500 | G10: 64639 | H10: -0.036599764 | I10: 0.062128233
A11: Nov 21, 2023 15:00:00 | B11: 121200 | C11: 122400 | D11: 68703 | E11: 124900 | F11: 122750 | G11: 67378 | H11: -0.029623699 | I11: 0.042373799
A12: Nov 22, 2023 15:00:00 | B12: 115150 | C12: 121200 | D12: 132920 | E12: 121550 | F12: 121000 | G12: 72059 | H12: -0.052653229 | I12: 0.069473715
A13: Nov 23, 2023 15:00:00 | B13: 113800 | C13: 115150 | D13: 123231 | E13: 116650 | F13: 114500 | G13: 74096 | H13: -0.024432062 | I13: 0.028268502
... A77: Apr 03, 2024 15:00:00 | B77: 111800 | C77: 111000 | D77: 199227 | E77: 111550 | F77: 111550 | G77: 183070 | H77: 0.0022411475 | I77: -0.042425764
A78: Apr 08, 2024 15:00:00 | B78: 113500 | C78: 111800 | D78: 178332 | E78: 112300 | F78: 112500 | G78: 183798 | H78: 0.010685663 | I78: =+G78/G77-1 -> 0.003976621
A79: Apr 09, 2024 15:00:00 | B79: 114150 | C79: 113500 | D79: 159011 | E79: 113650 | F79: 114000 | G79: 184198 | H79: 0.0043994721 | I79: 0.0021763022
A80: Apr 10, 2024 15:00:00 | B80: 115950 | C80: 114150 | D80: 180964 | E80: 113650 | F80: 114850 | G80: 184304 | H80: 0.020237571 | I80: 0.0005754677
A81: Apr 11, 2024 15:00:00 | B81: 112500 | C81: 115950 | D81: 195122 | E81: 116050 | F81: 115600 | G81: 180154 | H81: -0.030590263 | I81: -0.022517146
A82: Apr 12, 2024 15:00:00 | B82: 112200 | C82: 112500 | D82: 126606 | E82: 112750 | F82: 111050 | G82: 178440 | H82: -0.0048780488 | I82: -0.0095140824
A83: Apr 15, 2024 15:00:00 | B83: 111750 | C83: 112200 | D83: 107237 | E83: 112350 | F83: 113200 | G83: 179104 | H83: -0.0053404539 | I83: 0.0037211388
A84: Apr 16, 2024 15:00:00 | B84: 108150 | C84: 111750 | D84: 176355 | E84: 112400 | F84: 111400 | G84: 179955 | H84: -0.037811388 | I84: 0.0047514293
A85: Apr 17, 2024 15:00:00 | B85: 109400 | C85: 108150 | D85: 98410 | E85: 109100 | F85: 108400 | G85: 175021 | H85: 0.0027497709 | I85: -0.027417966
A86: Apr 18, 2024 15:00:00 | B86: 108400 | C86: 109400 | D86: 131581 | E86: 109200 | F86: 109900 | G86: 174354 | H86: -0.0073260073 | I86: -0.0038109713
A87: Apr 19, 2024 15:00:00 | B87: 107700 | C87: 108400 | D87: 172997 | E87: 110050 | F87: 108200 | G87: 176344 | H87: -0.02135393 | I87: 0.011413561
A88: Apr 22, 2024 15:00:00 | B88: 108550 | C88: 107700 | D88: 134200 | E88: 108150 | F88: 108600 | G88: 177912 | H88: =+B88/E88-1 -> 0.0036985668 | I88: =+G88/G87-1 -> 0.0088917117
A89: Apr 23, 2024 15:00:00 | B89: 109150 | C89: 108550 | D89: 139477 | E89: 109000 | F89: 108650 | G89: 176631 | H89: 0.0013761468 | I89: -0.0072001889
A90: Apr 24, 2024 15:00:00 | B90: 110400 | C90: 109150 | D90: 179713 | E90: 108950 | F90: 109800 | G90: 178807 | H90: 0.013308857 | I90: 0.012319468
A91: Apr 25, 2024 15:00:00 | B91: 109600 | C91: 110400 | D91: 158133 | E91: 110550 | F91: 110500 | G91: 176148 | H91: -0.0085933967 | I91: -0.014870782
A92: Apr 26, 2024 15:00:00 | B92: 109900 | C92: 109600 | D92: 98463 | E92: 110900 | F92: 109800 | G92: 172606 | H92: -0.0090171326 | I92: -0.020108091
A93: Apr 29, 2024 15:00:00 | B93: 115900 | C93: 109900 | D93: 287181 | E93: 109700 | F93: 109700 | G93: 193148 | H93: 0.056517776 | I93: 0.11901093
A94: Apr 30, 2024 15:00:00 | B94: 111450 | C94: 115900 | D94: 242267 | E94: 113900 | F94: 116000 | G94: 179848 | H94: -0.021510097 | I94: -0.068859113
A95: May 06, 2024 15:00:00 | B95: 112400 | C95: 111450 | D95: 117124 | E95: 113250 | F95: 112000 | G95: 185096 | H95: -0.0075055188 | I95: 0.029180197
A96: May 07, 2024 15:00:00 | B96: 113900 | C96: 112400 | D96: 151842 | E96: 112000 | F96: 113000 | G96: 189460 | H96: 0.016964286 | I96: 0.023576955
A97: May 08, 2024 15:00:00 | B97: 112050 | C97: 113900 | D97: 118354 | E97: 113900 | F97: 114000 | G97: 190964 | H97: -0.016242318 | I97: 0.0079383511
A98: May 09, 2024 15:00:00 | B98: 111700 | C98: 112050 | D98: 136072 | E98: 112550 | F98: 112500 | G98: 193390 | H98: -0.007552199 | I98: 0.012703965
A99: May 10, 2024 15:00:00 | B99: 108350 | C99: 111700 | D99: 202809 | E99: 111850 | F99: 111900 | G99: 195326 | H99: -0.031291909 | I99: 0.010010859
A100: May 13, 2024 15:00:00 | B100: 107100 | C100: 108350 | D100: 129937 | E100: 109450 | F100: 107550 | G100: 198230 | H100: -0.021470991 | I100: 0.014867452
... A143: Jul 11, 2024 15:00:00 | B143: 86900 | C143: 86800 | D143: 101 | E143: 87750 | F143: 85800 | G143: 52 | H143: -0.0096866097 | I143: 0

Sheet lc2408
A1: Date | B1: Latest | C1: Prev.Close | D1: Volume | E1: Prev.Settle | F1: Open | G1: Open Interest | H1: Var % | I1: O.I %
A2: Nov 08, 2023 15:00:00 | B2: 123000 | C2: 121700 | D2: 1047 | E2: 123350 | F2: 121700 | G2: 5687 | H2: =+B2/E2-1 -> -0.0028374544
A3: Nov 09, 2023 15:00:00 | B3: 122850 | C3: 123000 | D3: 1143 | E3: 122000 | F3: 122750 | G3: 5768 | H3: =+B3/E3-1 -> 0.0069672131 | I3: =+G3/G2-1 -> 0.01424301
A4: Nov 10, 2023 15:00:00 | B4: 127050 | C4: 122850 | D4: 1047 | E4: 122850 | F4: 123300 | G4: 5677 | H4: =+B4/E4-1 -> 0.034188034 | I4: =+G4/G3-1 -> -0.015776699
A5: Nov 13, 2023 15:00:00 | B5: 123950 | C5: 127050 | D5: 566 | E5: 125950 | F5: 128000 | G5: 5673 | H5: =+B5/E5-1 -> -0.015879317 | I5: =+G5/G4-1 -> -0.0007045975
A6: Nov 14, 2023 15:00:00 | B6: 124200 | C6: 123950 | D6: 630 | E6: 126800 | F6: 123700 | G6: 5653 | H6: =+B6/E6-1 -> -0.020504732 | I6: =+G6/G5-1 -> -0.0035254715
A7: Nov 15, 2023 15:00:00 | B7: 125550 | C7: 124200 | D7: 568 | E7: 124100 | F7: 125100 | G7: 5651 | H7: =+B7/E7-1 -> 0.011684126 | I7: =+G7/G6-1 -> -0.00035379445
A8: Nov 16, 2023 15:00:00 | B8: 125900 | C8: 125550 | D8: 330 | E8: 125750 | F8: 125400 | G8: 5684 | H8: =+B8/E8-1 -> 0.0011928429 | I8: =+G8/G7-1 -> 0.0058396744
A9: Nov 17, 2023 15:00:00 | B9: 125850 | C9: 125900 | D9: 316 | E9: 126100 | F9: 124950 | G9: 5686 | H9: =+B9/E9-1 -> -0.0019825535 | I9: =+G9/G8-1 -> 0.00035186488
A10: Nov 20, 2023 15:00:00 | B10: 122250 | C10: 125850 | D10: 1835 | E10: 125850 | F10: 125500 | G10: 5526 | H10: =+B10/E10-1 -> -0.028605483 | I10: =+G10/G9-1 -> -0.028139289
A11: Nov 21, 2023 15:00:00 | B11: 121200 | C11: 122250 | D11: 2380 | E11: 123300 | F11: 122750 | G11: 6065 | H11: =+B11/E11-1 -> -0.01703163 | I11: =+G11/G10-1 -> 0.097538907
A12: Nov 22, 2023 15:00:00 | B12: 115000 | C12: 121200 | D12: 2981 | E12: 121500 | F12: 121450 | G12: 6662 | H12: =+B12/E12-1 -> -0.053497942 | I12: =+G12/G11-1 -> 0.098433636
A13: Nov 23, 2023 15:00:00 | B13: 114150 | C13: 115000 | D13: 3394 | E13: 116200 | F13: 115450 | G13: 6626 | H13: =+B13/E13-1 -> -0.017641997 | I13: =+G13/G12-1 -> -0.0054037826
A14: Nov 24, 2023 15:00:00 | B14: 114900 | C14: 114150 | D14: 1432 | E14: 113050 | F14: 114300 | G14: 6395 | H14: =+B14/E14-1 -> 0.016364441 | I14: =+G14/G13-1 -> -0.034862662
... A173: Aug 14, 2024 15:00:00 | B173: 72250 | C173: 76200 | D173: 623 | E173: 75500 | F173: 75100 | G173: 0 | H173: =+B173/E173-1 -> -0.043046358 | I173: =+G173/G172-1 -> -1

Sheet lc2409
A1: Date | B1: Latest | C1: Prev.Close | D1: Volume | E1: Prev.Settle | F1: Open | G1: Open Interest | H1: Var % | I1: O.I %
A2: Nov 08, 2023 15:00:00 | B2: 120950 | C2: 120100 | D2: 3872 | E2: 121350 | F2: 120300 | G2: 10288 | H2: =+B2/E2-1 -> -0.0032962505
A3: Nov 09, 2023 15:00:00 | B3: 120900 | C3: 120950 | D3: 1854 | E3: 120350 | F3: 120500 | G3: 10234 | H3: =+B3/E3-1 -> 0.0045700042 | I3: =+G3/G2-1 -> -0.0052488336
A4: Nov 10, 2023 15:00:00 | B4: 124800 | C4: 120900 | D4: 3738 | E4: 121050 | F4: 121250 | G4: 9884 | H4: =+B4/E4-1 -> 0.030978934 | I4: =+G4/G3-1 -> -0.034199726
A5: Nov 13, 2023 15:00:00 | B5: 122150 | C5: 124800 | D5: 2736 | E5: 123900 | F5: 124850 | G5: 9663 | H5: =+B5/E5-1 -> -0.014124294 | I5: =+G5/G4-1 -> -0.022359369
A6: Nov 14, 2023 15:00:00 | B6: 122500 | C6: 122150 | D6: 2121 | E6: 124250 | F6: 122150 | G6: 9738 | H6: =+B6/E6-1 -> -0.014084507 | I6: =+G6/G5-1 -> 0.0077615647
A7: Nov 15, 2023 15:00:00 | B7: 123950 | C7: 122500 | D7: 2266 | E7: 122650 | F7: 123500 | G7: 9647 | H7: =+B7/E7-1 -> 0.010599266 | I7: =+G7/G6-1 -> -0.0093448347
A8: Nov 16, 2023 15:00:00 | B8: 124650 | C8: 123950 | D8: 1512 | E8: 124050 | F8: 123850 | G8: 9771 | H8: =+B8/E8-1 -> 0.0048367594 | I8: =+G8/G7-1 -> 0.012853737
A9: Nov 17, 2023 15:00:00 | B9: 124300 | C9: 124650 | D9: 1708 | E9: 124700 | F9: 124600 | G9: 9598 | H9: =+B9/E9-1 -> -0.0032076985 | I9: =+G9/G8-1 -> -0.017705455
A10: Nov 20, 2023 15:00:00 | B10: 121450 | C10: 124300 | D10: 3705 | E10: 124550 | F10: 125000 | G10: 9550 | H10: =+B10/E10-1 -> -0.024889603 | I10: =+G10/G9-1 -> -0.0050010419
A11: Nov 21, 2023 15:00:00 | B11: 120500 | C11: 121450 | D11: 3274 | E11: 123000 | F11: 121800 | G11: 9887 | H11: =+B11/E11-1 -> -0.020325203 | I11: =+G11/G10-1 -> 0.035287958
A12: Nov 22, 2023 15:00:00 | B12: 115000 | C12: 120500 | D12: 7465 | E12: 121000 | F12: 120500 | G12: 10645 | H12: =+B12/E12-1 -> -0.049586777 | I12: =+G12/G11-1 -> 0.07666633
A13: Nov 23, 2023 15:00:00 | B13: 113500 | C13: 115000 | D13: 6166 | E13: 116000 | F13: 114800 | G13: 10959 | H13: =+B13/E13-1 -> -0.021551724 | I13: =+G13/G12-1 -> 0.029497417
A14: Nov 24, 2023 15:00:00 | B14: 114100 | C14: 113500 | D14: 4273 | E14: 112550 | F14: 113300 | G14: 10718 | H14: =+B14/E14-1 -> 0.013771657 | I14: =+G14/G13-1 -> -0.021991058
... A194: Sep 12, 2024 15:00:00 | B194: 77000 | C194: 76450 | D194: 27 | E194: 73000 | F194: 76350 | G194: 85 | H194: =+B194/E194-1 -> 0.054794521 | I194: =+G194/G193-1 -> -0.58536585

Sheet lc2410
A1: Date | B1: Latest | C1: Prev.Close | D1: Volume | E1: Prev.Settle | F1: Open | G1: Open Interest | H1: Var % | I1: O.I %
A14: Nov 24, 2023 15:00:00 | B14: 113150 | C14: 112500 | D14: 1382 | E14: 111750 | F14: 112200 | G14: 4499 | H14: =+B14/E14-1 -> 0.012527964
A15: Nov 27, 2023 15:00:00 | B15: 106200 | C15: 113150 | D15: 2303 | E15: 113350 | F15: 112900 | G15: 4627 | H15: =+B15/E15-1 -> -0.063078959 | I15: =+G15/G14-1 -> 0.028450767
A16: Nov 28, 2023 15:00:00 | B16: 108000 | C16: 106200 | D16: 1671 | E16: 109150 | F16: 106000 | G16: 4742 | H16: =+B16/E16-1 -> -0.01053596 | I16: =+G16/G15-1 -> 0.024854117
A17: Nov 29, 2023 15:00:00 | B17: 109600 | C17: 108000 | D17: 2156 | E17: 107200 | F17: 108250 | G17: 4802 | H17: =+B17/E17-1 -> 0.02238806 | I17: =+G17/G16-1 -> 0.012652889
A18: Nov 30, 2023 15:00:00 | B18: 107000 | C18: 109600 | D18: 1717 | E18: 109550 | F18: 110000 | G18: 4777 | H18: =+B18/E18-1 -> -0.023277042 | I18: =+G18/G17-1 -> -0.0052061641
A19: Dec 01, 2023 15:00:00 | B19: 103850 | C19: 107000 | D19: 2854 | E19: 107900 | F19: 106950 | G19: 4755 | H19: =+B19/E19-1 -> -0.037534754 | I19: =+G19/G18-1 -> -0.0046054009
A20: Dec 04, 2023 15:00:00 | B20: 96800 | C20: 103850 | D20: 3141 | E20: 104050 | F20: 103650 | G20: 4773 | H20: =+B20/E20-1 -> -0.069678039 | I20: =+G20/G19-1 -> 0.003785489
A21: Dec 05, 2023 15:00:00 | B21: 89900 | C21: 96800 | D21: 3330 | E21: 99850 | F21: 95000 | G21: 4956 | H21: =+B21/E21-1 -> -0.099649474 | I21: =+G21/G20-1 -> 0.038340666
A22: Dec 06, 2023 15:00:00 | B22: 92400 | C22: 89900 | D22: 4531 | E22: 91900 | F22: 85050 | G22: 5036 | H22: =+B22/E22-1 -> 0.0054406964 | I22: =+G22/G21-1 -> 0.01614205
A23: Dec 07, 2023 15:00:00 | B23: 94550 | C23: 92400 | D23: 1271 | E23: 88400 | F23: 91000 | G23: 4995 | H23: =+B23/E23-1 -> 0.069570136 | I23: =+G23/G22-1 -> -0.008141382
A24: Dec 08, 2023 15:00:00 | B24: 101350 | C24: 94550 | D24: 691 | E24: 92150 | F24: 97650 | G24: 4812 | H24: =+B24/E24-1 -> 0.099837222 | I24: =+G24/G23-1 -> -0.036636637
A25: Dec 11, 2023 15:00:00 | B25: 96000 | C25: 101350 | D25: 7900 | E25: 100600 | F25: 111350 | G25: 4359 | H25: =+B25/E25-1 -> -0.045725646 | I25: =+G25/G24-1 -> -0.094139651
A26: Dec 12, 2023 15:00:00 | B26: 93600 | C26: 96000 | D26: 3229 | E26: 102150 | F26: 95500 | G26: 4575 | H26: =+B26/E26-1 -> -0.083700441 | I26: =+G26/G25-1 -> 0.04955265
... A214: Oct 21, 2024 15:00:00 | B214: 70100 | C214: 70450 | D214: 462 | E214: 70450 | F214: 70100 | G214: 0 | H214: =+B214/E214-1 -> -0.0049680625 | I214: =+G214/G213-1 -> -1

Sheet lc2411
A1: Date | B1: Latest | C1: Prev.Close | D1: Volume | E1: Prev.Settle | F1: Open | G1: Open Interest | H1: Var % | I1: O.I %
A14: Nov 24, 2023 15:00:00 | B14: 112050 | C14: 111650 | D14: 1004 | E14: 110800 | F14: 111450 | G14: 2325 | H14: =+B14/E14-1 -> 0.011281588
A15: Nov 27, 2023 15:00:00 | B15: 105200 | C15: 112050 | D15: 2558 | E15: 112150 | F15: 111050 | G15: 2800 | H15: =+B15/E15-1 -> -0.061970575 | I15: =+G15/G14-1 -> 0.20430108
A16: Nov 28, 2023 15:00:00 | B16: 106800 | C16: 105200 | D16: 2080 | E16: 107950 | F16: 105700 | G16: 2937 | H16: =+B16/E16-1 -> -0.01065308 | I16: =+G16/G15-1 -> 0.048928571
A17: Nov 29, 2023 15:00:00 | B17: 108850 | C17: 106800 | D17: 2147 | E17: 106550 | F17: 107100 | G17: 2894 | H17: =+B17/E17-1 -> 0.02158611 | I17: =+G17/G16-1 -> -0.01464079
A18: Nov 30, 2023 15:00:00 | B18: 106150 | C18: 108850 | D18: 1253 | E18: 108500 | F18: 108850 | G18: 3129 | H18: =+B18/E18-1 -> -0.021658986 | I18: =+G18/G17-1 -> 0.081202488
A19: Dec 01, 2023 15:00:00 | B19: 102900 | C19: 106150 | D19: 3043 | E19: 107200 | F19: 106050 | G19: 3608 | H19: =+B19/E19-1 -> -0.04011194 | I19: =+G19/G18-1 -> 0.15308405
A20: Dec 04, 2023 15:00:00 | B20: 96050 | C20: 102900 | D20: 3831 | E20: 103250 | F20: 102950 | G20: 4562 | H20: =+B20/E20-1 -> -0.069733656 | I20: =+G20/G19-1 -> 0.26441242
A21: Dec 05, 2023 15:00:00 | B21: 92050 | C21: 96050 | D21: 2418 | E21: 98950 | F21: 96000 | G21: 5254 | H21: =+B21/E21-1 -> -0.069732188 | I21: =+G21/G20-1 -> 0.15168786
A22: Dec 06, 2023 15:00:00 | B22: 92150 | C22: 92050 | D22: 6158 | E22: 93300 | F22: 88500 | G22: 5389 | H22: =+B22/E22-1 -> -0.012325831 | I22: =+G22/G21-1 -> 0.025694709
A23: Dec 07, 2023 15:00:00 | B23: 94100 | C23: 92150 | D23: 2511 | E23: 87950 | F23: 91900 | G23: 5496 | H23: =+B23/E23-1 -> 0.069926094 | I23: =+G23/G22-1 -> 0.019855261
A24: Dec 08, 2023 15:00:00 | B24: 100850 | C24: 94100 | D24: 4490 | E24: 91700 | F24: 97050 | G24: 7421 | H24: =+B24/E24-1 -> 0.099781897 | I24: =+G24/G23-1 -> 0.35025473
A25: Dec 11, 2023 15:00:00 | B25: 95650 | C25: 100850 | D25: 14380 | E25: 100200 | F25: 104050 | G25: 6493 | H25: =+B25/E25-1 -> -0.045409182 | I25: =+G25/G24-1 -> -0.12505053
A26: Dec 12, 2023 15:00:00 | B26: 92950 | C26: 95650 | D26: 8183 | E26: 100800 | F26: 94850 | G26: 7420 | H26: =+B26/E26-1 -> -0.077876984 | I26: =+G26/G25-1 -> 0.14276914
... A231: Nov 14, 2024 15:00:00 | B231: 82250 | C231: 84400 | D231: 155 | E231: 82500 | F231: 84150 | G231: 0 | H231: =+B231/E231-1 -> -0.003030303 | I231: =+G231/G230-1 -> -1

Sheet Contrato 2411
A1: Date | B1: Latest | C1: Prev.Close | D1: Volume | E1: Prev.Settle | F1: Open | G1: Open Interest | H1: Var % | I1: O.I %
A14: Nov 24, 2023 15:00:00 | B14: 112050 | C14: 111650 | D14: 1004 | E14: 110800 | F14: 111450 | G14: 2325 | H14: 0.011281588
A15: Nov 27, 2023 15:00:00 | B15: 105200 | C15: 112050 | D15: 2558 | E15: 112150 | F15: 111050 | G15: 2800 | H15: -0.061970575 | I15: 0.20430108
A16: Nov 28, 2023 15:00:00 | B16: 106800 | C16: 105200 | D16: 2080 | E16: 107950 | F16: 105700 | G16: 2937 | H16: -0.01065308 | I16: 0.048928571
A17: Nov 29, 2023 15:00:00 | B17: 108850 | C17: 106800 | D17: 2147 | E17: 106550 | F17: 107100 | G17: 2894 | H17: 0.02158611 | I17: -0.01464079
A18: Nov 30, 2023 15:00:00 | B18: 106150 | C18: 108850 | D18: 1253 | E18: 108500 | F18: 108850 | G18: 3129 | H18: -0.021658986 | I18: 0.081202488
A19: Dec 01, 2023 15:00:00 | B19: 102900 | C19: 106150 | D19: 3043 | E19: 107200 | F19: 106050 | G19: 3608 | H19: -0.04011194 | I19: 0.15308405
A20: Dec 04, 2023 15:00:00 | B20: 96050 | C20: 102900 | D20: 3831 | E20: 103250 | F20: 102950 | G20: 4562 | H20: -0.069733656 | I20: 0.26441242
A21: Dec 05, 2023 15:00:00 | B21: 92050 | C21: 96050 | D21: 2418 | E21: 98950 | F21: 96000 | G21: 5254 | H21: -0.069732188 | I21: 0.15168786
A22: Dec 06, 2023 15:00:00 | B22: 92150 | C22: 92050 | D22: 6158 | E22: 93300 | F22: 88500 | G22: 5389 | H22: -0.012325831 | I22: 0.025694709
A23: Dec 07, 2023 15:00:00 | B23: 94100 | C23: 92150 | D23: 2511 | E23: 87950 | F23: 91900 | G23: 5496 | H23: 0.069926094 | I23: 0.019855261
A24: Dec 08, 2023 15:00:00 | B24: 100850 | C24: 94100 | D24: 4490 | E24: 91700 | F24: 97050 | G24: 7421 | H24: 0.099781897 | I24: 0.35025473
A25: Dec 11, 2023 15:00:00 | B25: 95650 | C25: 100850 | D25: 14380 | E25: 100200 | F25: 104050 | G25: 6493 | H25: -0.045409182 | I25: -0.12505053
A26: Dec 12, 2023 15:00:00 | B26: 92950 | C26: 95650 | D26: 8183 | E26: 100800 | F26: 94850 | G26: 7420 | H26: -0.077876984 | I26: 0.14276914
... A231: Nov 14, 2024 15:00:00 | B231: 82250 | C231: 84400 | D231: 155 | E231: 82500 | F231: 84150 | G231: 0 | H231: -0.003030303 | I231: -1

Sheet lc2412
A1: Date | B1: Latest | C1: Prev.Close | D1: Volume | E1: Prev.Settle | F1: Open | G1: Open Interest | H1: Var % | I1: O.I %
A29: Dec 15, 2023 15:00:00 | B29: 104650 | D29: 177 | E29: 99300 | F29: 98700 | G29: 70 | H29: =+B29/E29-1 -> 0.05387714
A30: Dec 18, 2023 15:00:00 | B30: 102500 | C30: 104650 | D30: 229 | E30: 104200 | F30: 105050 | G30: 122 | H30: =+B30/E30-1 -> -0.016314779 | I30: =+G30/G29-1 -> 0.74285714
A31: Dec 19, 2023 15:00:00 | B31: 101350 | C31: 102500 | D31: 43 | E31: 103050 | F31: 101900 | G31: 137 | H31: =+B31/E31-1 -> -0.016496846 | I31: =+G31/G30-1 -> 0.12295082
A32: Dec 20, 2023 15:00:00 | B32: 101400 | C32: 101350 | D32: 71 | E32: 102000 | F32: 102500 | G32: 160 | H32: =+B32/E32-1 -> -0.0058823529 | I32: =+G32/G31-1 -> 0.16788321
A33: Dec 21, 2023 15:00:00 | B33: 98500 | C33: 101400 | D33: 105 | E33: 101950 | F33: 100800 | G33: 197 | H33: =+B33/E33-1 -> -0.033840118 | I33: =+G33/G32-1 -> 0.23125
A34: Dec 22, 2023 15:00:00 | B34: 103200 | C34: 98500 | D34: 194 | E34: 99650 | F34: 99250 | G34: 216 | H34: =+B34/E34-1 -> 0.035624686 | I34: =+G34/G33-1 -> 0.096446701
A35: Dec 25, 2023 15:00:00 | B35: 104450 | C35: 103200 | D35: 133 | E35: 102200 | F35: 103600 | G35: 209 | H35: =+B35/E35-1 -> 0.022015656 | I35: =+G35/G34-1 -> -0.032407407
A36: Dec 26, 2023 15:00:00 | B36: 107600 | C36: 104450 | D36: 247 | E36: 104550 | F36: 105000 | G36: 275 | H36: =+B36/E36-1 -> 0.029172645 | I36: =+G36/G35-1 -> 0.31578947
A37: Dec 27, 2023 15:00:00 | B37: 107650 | C37: 107600 | D37: 261 | E37: 106750 | F37: 107450 | G37: 259 | H37: =+B37/E37-1 -> 0.0084309133 | I37: =+G37/G36-1 -> -0.058181818
A38: Dec 28, 2023 15:00:00 | B38: 108600 | C38: 107650 | D38: 75 | E38: 108500 | F38: 108050 | G38: 260 | H38: =+B38/E38-1 -> 0.00092165899 | I38: =+G38/G37-1 -> 0.0038610039
A39: Dec 29, 2023 15:00:00 | B39: 110000 | C39: 108600 | D39: 140 | E39: 107800 | F39: 108050 | G39: 260 | H39: =+B39/E39-1 -> 0.020408163 | I39: =+G39/G38-1 -> 0
A40: Jan 02, 2024 15:00:00 | B40: 110200 | C40: 110000 | D40: 121 | E40: 108400 | F40: 108300 | G40: 283 | H40: =+B40/E40-1 -> 0.016605166 | I40: =+G40/G39-1 -> 0.088461538
A41: Jan 03, 2024 15:00:00 | B41: 108300 | C41: 110200 | D41: 142 | E41: 109550 | F41: 109800 | G41: 306 | H41: =+B41/E41-1 -> -0.011410315 | I41: =+G41/G40-1 -> 0.081272085
... A252: Dec 12, 2024 15:00:00 | B252: 76400 | C252: 76400 | D252: 126 | E252: 77600 | F252: 76400 | G252: 10 | H252: =+B252/E252-1 -> -0.015463918 | I252: =+G252/G251-1 -> 0

Sheet lc2501
A1: Date | B1: Latest | C1: Prev.Close | D1: Volume | E1: Prev.Settle | F1: Open | G1: Open Interest | H1: Var % | I1: O.I %
A50: Jan 16, 2024 15:00:00 | B50: 105600 | C50: 103750 | D50: 39 | E50: 103750 | F50: 105000 | G50: 26 | H50: =+B50/E50-1 -> 0.017831325
A51: Jan 17, 2024 15:00:00 | B51: 103800 | C51: 105600 | D51: 49 | E51: 104900 | F51: 106000 | G51: 56 | H51: =+B51/E51-1 -> -0.010486177 | I51: =+G51/G50-1 -> 1.1538462
A52: Jan 18, 2024 15:00:00 | B52: 104200 | C52: 103800 | D52: 48 | E52: 104900 | F52: 103550 | G52: 62 | H52: =+B52/E52-1 -> -0.0066730219 | I52: =+G52/G51-1 -> 0.10714286
A53: Jan 19, 2024 15:00:00 | B53: 103050 | C53: 104200 | D53: 31 | E53: 103600 | F53: 105200 | G53: 68 | H53: =+B53/E53-1 -> -0.0053088803 | I53: =+G53/G52-1 -> 0.096774194
A54: Jan 22, 2024 15:00:00 | B54: 101950 | C54: 103050 | D54: 55 | E54: 103700 | F54: 102100 | G54: 87 | H54: =+B54/E54-1 -> -0.016875603 | I54: =+G54/G53-1 -> 0.27941176
A55: Jan 23, 2024 15:00:00 | B55: 103450 | C55: 101950 | D55: 24 | E55: 102050 | F55: 102050 | G55: 94 | H55: =+B55/E55-1 -> 0.013718765 | I55: =+G55/G54-1 -> 0.08045977
A56: Jan 24, 2024 15:00:00 | B56: 104200 | C56: 103450 | D56: 40 | E56: 102700 | F56: 102650 | G56: 110 | H56: =+B56/E56-1 -> 0.014605648 | I56: =+G56/G55-1 -> 0.17021277
A57: Jan 25, 2024 15:00:00 | B57: 102950 | C57: 104200 | D57: 31 | E57: 104100 | F57: 104950 | G57: 112 | H57: =+B57/E57-1 -> -0.01104707 | I57: =+G57/G56-1 -> 0.018181818
A58: Jan 26, 2024 15:00:00 | B58: 103500 | C58: 102950 | D58: 41 | E58: 103900 | F58: 103950 | G58: 121 | H58: =+B58/E58-1 -> -0.0038498556 | I58: =+G58/G57-1 -> 0.080357143
A59: Jan 29, 2024 15:00:00 | B59: 104150 | C59: 103500 | D59: 33 | E59: 103950 | F59: 104050 | G59: 128 | H59: =+B59/E59-1 -> 0.0019240019 | I59: =+G59/G58-1 -> 0.05785124
A60: Jan 30, 2024 15:00:00 | B60: 103850 | C60: 104150 | D60: 32 | E60: 103950 | F60: 104600 | G60: 136 | H60: =+B60/E60-1 -> -0.00096200096 | I60: =+G60/G59-1 -> 0.0625
A61: Jan 31, 2024 15:00:00 | B61: 102050 | C61: 103850 | D61: 50 | E61: 104050 | F61: 103350 | G61: 158 | H61: =+B61/E61-1 -> -0.019221528 | I61: =+G61/G60-1 -> 0.16176471
A62: Feb 01, 2024 15:00:00 | B62: 103050 | C62: 102050 | D62: 42 | E62: 102750 | F62: 101400 | G62: 168 | H62: =+B62/E62-1 -> 0.002919708 | I62: =+G62/G61-1 -> 0.063291139
... A271: Jan 14, 2025 15:00:00 | B271: 76040 | C271: 75040 | D271: 415 | E271: 75780 | F271: 75880 | G271: 395 | H271: =+B271/E271-1 -> 0.0034309844 | I271: =+G271/G270-1 -> 0

Sheet Contrato 2501
A1: Date | B1: Latest | C1: Prev.Close | D1: Volume | E1: Prev.Settle | F1: Open | G1: Open Interest | H1: Var % | I1: O.I %
A50: Jan 16, 2024 15:00:00 | B50: 105600 | C50: 103750 | D50: 39 | E50: 103750 | F50: 105000 | G50: 26 | H50: 0.017831325
A51: Jan 17, 2024 15:00:00 | B51: 103800 | C51: 105600 | D51: 49 | E51: 104900 | F51: 106000 | G51: 56 | H51: -0.010486177 | I51: 1.1538462
A52: Jan 18, 2024 15:00:00 | B52: 104200 | C52: 103800 | D52: 48 | E52: 104900 | F52: 103550 | G52: 62 | H52: -0.0066730219 | I52: 0.10714286
A53: Jan 19, 2024 15:00:00 | B53: 103050 | C53: 104200 | D53: 31 | E53: 103600 | F53: 105200 | G53: 68 | H53: -0.0053088803 | I53: 0.096774194
A54: Jan 22, 2024 15:00:00 | B54: 101950 | C54: 103050 | D54: 55 | E54: 103700 | F54: 102100 | G54: 87 | H54: -0.016875603 | I54: 0.27941176
A55: Jan 23, 2024 15:00:00 | B55: 103450 | C55: 101950 | D55: 24 | E55: 102050 | F55: 102050 | G55: 94 | H55: 0.013718765 | I55: 0.08045977
A56: Jan 24, 2024 15:00:00 | B56: 104200 | C56: 103450 | D56: 40 | E56: 102700 | F56: 102650 | G56: 110 | H56: 0.014605648 | I56: 0.17021277
A57: Jan 25, 2024 15:00:00 | B57: 102950 | C57: 104200 | D57: 31 | E57: 104100 | F57: 104950 | G57: 112 | H57: -0.01104707 | I57: 0.018181818
A58: Jan 26, 2024 15:00:00 | B58: 103500 | C58: 102950 | D58: 41 | E58: 103900 | F58: 103950 | G58: 121 | H58: -0.0038498556 | I58: 0.080357143
A59: Jan 29, 2024 15:00:00 | B59: 104150 | C59: 103500 | D59: 33 | E59: 103950 | F59: 104050 | G59: 128 | H59: 0.0019240019 | I59: 0.05785124
A60: Jan 30, 2024 15:00:00 | B60: 103850 | C60: 104150 | D60: 32 | E60: 103950 | F60: 104600 | G60: 136 | H60: -0.00096200096 | I60: 0.0625
A61: Jan 31, 2024 15:00:00 | B61: 102050 | C61: 103850 | D61: 50 | E61: 104050 | F61: 103350 | G61: 158 | H61: -0.019221528 | I61: 0.16176471
A62: Feb 01, 2024 15:00:00 | B62: 103050 | C62: 102050 | D62: 42 | E62: 102750 | F62: 101400 | G62: 168 | H62: 0.002919708 | I62: 0.063291139
... A126: Jun 06, 2024 15:00:00 | B126: 106500 | C126: 105850 | D126: 2521 | E126: 106050 | F126: 105950 | G126: 13992 | H126: 0.0042432815 | I126: 0.020048115
A127: Jun 07, 2024 15:00:00 | B127: 105450 | C127: 106500 | D127: 4275 | E127: 106000 | F127: 107050 | G127: 14436 | H127: =+B127/E127-1 -> -0.0051886792 | I127: =+G127/G126-1 -> 0.031732419
A128: Jun 11, 2024 15:00:00 | B128: 102900 | C128: 105450 | D128: 4692 | E128: 105800 | F128: 103450 | G128: 15154 | H128: -0.027410208 | I128: 0.049736769
A129: Jun 12, 2024 15:00:00 | B129: 105100 | C129: 102900 | D129: 6995 | E129: 103750 | F129: 103000 | G129: 15757 | H129: =+B129/E129-1 -> 0.013012048 | I129: =+G129/G128-1 -> 0.039791474
A130: Jun 13, 2024 15:00:00 | B130: 103850 | C130: 105100 | D130: 5293 | E130: 103300 | F130: 105000 | G130: 16248 | H130: 0.0053242982 | I130: 0.031160754
A131: Jun 14, 2024 15:00:00 | B131: 103300 | C131: 103850 | D131: 1846 | E131: 104250 | F131: 103600 | G131: 16364 | H131: -0.0091127098 | I131: 0.0071393402
A132: Jun 17, 2024 15:00:00 | B132: 102100 | C132: 103300 | D132: 3348 | E132: 103550 | F132: 103300 | G132: 17057 | H132: -0.014002897 | I132: 0.042349059
A133: Jun 19, 2024 15:00:00 | B133: 100650 | C133: 100050 | D133: 4275 | E133: 101100 | F133: 100500 | G133: 18688 | H133: -0.0044510386 | I133: 0.014604484
A134: Jun 20, 2024 15:00:00 | B134: 100850 | C134: 100650 | D134: 2243 | E134: 100500 | F134: 100700 | G134: 18774 | H134: 0.0034825871 | I134: 0.0046018836
A135: Jun 21, 2024 15:00:00 | B135: 99100 | C135: 100850 | D135: 3748 | E135: 100800 | F135: 101100 | G135: 18936 | H135: -0.016865079 | I135: 0.0086289549
A136: Jun 24, 2024 15:00:00 | B136: 96000 | C136: 99100 | D136: 6575 | E136: 100000 | F136: 99000 | G136: 19311 | H136: -0.04 | I136: 0.019803549
A137: Jun 25, 2024 15:00:00 | B137: 97800 | C137: 96000 | D137: 6405 | E137: 96850 | F137: 96200 | G137: 19509 | H137: 0.009808983 | I137: 0.010253224
A138: Jun 26, 2024 15:00:00 | B138: 99900 | C138: 97800 | D138: 7672 | E138: 95800 | F138: 97450 | G138: 20044 | H138: 0.042797495 | I138: 0.027423241
A139: Jun 27, 2024 15:00:00 | B139: 97650 | C139: 99900 | D139: 5069 | E139: 99150 | F139: 99500 | G139: 20424 | H139: -0.015128593 | I139: 0.018958292
A140: Jun 28, 2024 15:00:00 | B140: 97400 | C140: 97650 | D140: 5061 | E140: 98350 | F140: 97650 | G140: 20569 | H140: -0.0096593798 | I140: 0.0070994908
A141: Jul 01, 2024 15:00:00 | B141: 98550 | C141: 97400 | D141: 5951 | E141: 97150 | F141: 96500 | G141: 20514 | H141: 0.014410705 | I141: -0.0026739268
... A179: Aug 23, 2024 15:00:00 | B179: 76100 | C179: 78050 | D179: 17163 | E179: 79000 | F179: 78050 | G179: 38789 | H179: -0.036708861 | I179: 0.028149601
A180: Aug 26, 2024 15:00:00 | B180: 77200 | C180: 76100 | D180: 14988 | E180: 76850 | F180: 76900 | G180: 38804 | H180: =+B180/E180-1 -> 0.0045543266 | I180: =+G180/G179-1 -> 0.00038670757
A181: Aug 27, 2024 15:00:00 | B181: 78800 | C181: 77200 | D181: 18025 | E181: 76950 | F181: 77450 | G181: 39332 | H181: 0.024041585 | I181: 0.013606845
A182: Aug 28, 2024 15:00:00 | B182: 78700 | C182: 78800 | D182: 15722 | E182: 78400 | F182: 78600 | G182: 39555 | H182: 0.0038265306 | I182: 0.0056696837
A183: Aug 29, 2024 15:00:00 | B183: 79600 | C183: 78700 | D183: 22406 | E183: 78350 | F183: 78850 | G183: 41149 | H183: 0.015954052 | I183: 0.040298319
A184: Aug 30, 2024 15:00:00 | B184: 81550 | C184: 79600 | D184: 28666 | E184: 79300 | F184: 79250 | G184: 43856 | H184: 0.028373266 | I184: 0.065785317
A185: Sep 02, 2024 15:00:00 | B185: 77800 | C185: 81550 | D185: 47089 | E185: 81000 | F185: 81000 | G185: 53934 | H185: =+B185/E185-1 -> -0.039506173 | I185: =+G185/G184-1 -> 0.22979752
A186: Sep 03, 2024 15:00:00 | B186: 77400 | C186: 77800 | D186: 25302 | E186: 79000 | F186: 77450 | G186: 54726 | H186: -0.020253165 | I186: 0.014684615
A187: Sep 04, 2024 15:00:00 | B187: 76000 | C187: 77400 | D187: 26416 | E187: 77150 | F187: 76850 | G187: 57397 | H187: -0.014906027 | I187: 0.048806783
A188: Sep 05, 2024 15:00:00 | B188: 73200 | C188: 76000 | D188: 33286 | E188: 76450 | F188: 75900 | G188: 60201 | H188: -0.042511445 | I188: 0.048852727
A189: Sep 06, 2024 15:00:00 | B189: 73250 | C189: 73200 | D189: 37546 | E189: 74600 | F189: 74500 | G189: 61215 | H189: -0.018096515 | I189: 0.016843574
A190: Sep 09, 2024 15:00:00 | B190: 75400 | C190: 73250 | D190: 47357 | E190: 73200 | F190: 72650 | G190: 65660 | H190: 0.030054645 | I190: 0.072612922
A191: Sep 10, 2024 15:00:00 | B191: 74200 | C191: 75400 | D191: 41994 | E191: 73550 | F191: 75400 | G191: 72224 | H191: 0.0088375255 | I191: 0.09996954
A192: Sep 11, 2024 15:00:00 | B192: 80400 | C192: 74200 | D192: 111531 | E192: 74750 | F192: 77000 | G192: 73411 | H192: 0.075585284 | I192: 0.01643498
A193: Sep 12, 2024 15:00:00 | B193: 78700 | C193: 80400 | D193: 77896 | E193: 78600 | F193: 80850 | G193: 76958 | H193: 0.0012722646 | I193: 0.04831701
A194: Sep 13, 2024 15:00:00 | B194: 79300 | C194: 78700 | D194: 45648 | E194: 79150 | F194: 79300 | G194: 76651 | H194: 0.0018951358 | I194: -0.0039891889
A195: Sep 13, 2024 15:00:00 | B195: 79300 | C195: 78700 | D195: 45648 | E195: 79150 | F195: 79300 | G195: 76651 | H195: 0.0018951358 | I195: 0
A196: Sep 13, 2024 15:00:00 | B196: 79300 | C196: 78700 | D196: 45648 | E196: 79150 | F196: 79300 | G196: 76651 | H196: 0.0018951358 | I196: -0.0039891889
A197: Sep 18, 2024 15:00:00 | B197: 77500 | C197: 79300 | D197: 50567 | E197: 79050 | F197: 79500 | G197: 80424 | H197: -0.019607843 | I197: 0.049223102
... A202: Sep 25, 2024 15:00:00 | B202: 78200 | C202: 78750 | D202: 112735 | E202: 78300 | F202: 80500 | G202: 96512 | H202: -0.0012771392 | I202: 0.053854553
A203: Sep 26, 2024 15:00:00 | B203: 79850 | C203: 78200 | D203: 69439 | E203: 80050 | F203: 78800 | G203: 98291 | H203: =+B203/E203-1 -> -0.0024984385 | I203: =+G203/G202-1 -> 0.018432941
A204: Sep 27, 2024 15:00:00 | B204: 79700 | C204: 79850 | D204: 94188 | E204: 78900 | F204: 80400 | G204: 98902 | H204: 0.010139417 | I204: 0.0062162355
A205: Sep 30, 2024 15:00:00 | B205: 82300 | C205: 79700 | D205: 127769 | E205: 80250 | F205: 82000 | G205: 108433 | H205: 0.025545171 | I205: 0.096368122
A206: Oct 08, 2024 15:00:00 | B206: 79700 | C206: 82300 | D206: 171475 | E206: 82000 | F206: 86000 | G206: 119317 | H206: -0.02804878 | I206: 0.10037535
A207: Oct 09, 2024 15:00:00 | B207: 79550 | C207: 79700 | D207: 83325 | E207: 83650 | F207: 79000 | G207: 121790 | H207: -0.049013748 | I207: 0.020726301
A208: Oct 10, 2024 15:00:00 | B208: 77100 | C208: 79550 | D208: 103912 | E208: 79950 | F208: 80000 | G208: 127735 | H208: -0.03564728 | I208: 0.048813531
A209: Oct 11, 2024 15:00:00 | B209: 77700 | C209: 77100 | D209: 90262 | E209: 79650 | F209: 78050 | G209: 128317 | H209: -0.024482109 | I209: 0.004556308
A210: Oct 14, 2024 15:00:00 | B210: 76850 | C210: 77700 | D210: 98797 | E210: 77400 | F210: 78200 | G210: 146098 | H210: -0.0071059432 | I210: 0.13857088
A211: Oct 15, 2024 15:00:00 | B211: 77250 | C211: 76850 | D211: 76926 | E211: 77300 | F211: 76500 | G211: 147248 | H211: -0.00064683053 | I211: 0.0078714288
A212: Oct 16, 2024 15:00:00 | B212: 74750 | C212: 77250 | D212: 103803 | E212: 77100 | F212: 77000 | G212: 152326 | H212: -0.030479896 | I212: 0.034486037
A213: Oct 17, 2024 15:00:00 | B213: 72100 | C213: 74750 | D213: 134641 | E213: 75950 | F213: 75000 | G213: 161200 | H213: -0.050691244 | I213: 0.058256634
A214: Oct 18, 2024 15:00:00 | B214: 74150 | C214: 72100 | D214: 222055 | E214: 73750 | F214: 72100 | G214: 172151 | H214: 0.0054237288 | I214: 0.067934243
A215: Oct 21, 2024 15:00:00 | B215: 72450 | C215: 74150 | D215: 205476 | E215: 73750 | F215: 74050 | G215: 194121 | H215: -0.017627119 | I215: 0.12762052
... A254: Dec 16, 2024 15:00:00 | B254: 76000 | C254: 75800 | D254: 109461 | E254: 76200 | F254: 75600 | G254: 137204 | H254: -0.0026246719 | I254: -0.067958263
A255: Dec 17, 2024 15:00:00 | B255: 75200 | C255: 76000 | D255: 89440 | E255: 75700 | F255: 76100 | G255: 125218 | H255: =+B255/E255-1 -> -0.0066050198 | I255: =+G255/G254-1 -> -0.087358969
A256: Dec 18, 2024 15:00:00 | B256: 74360 | C256: 75200 | D256: 102598 | E256: 75340 | F256: 75820 | G256: 113130 | H256: -0.013007698 | I256: -0.096535642
A257: Dec 19, 2024 15:00:00 | B257: 73920 | C257: 74360 | D257: 76096 | E257: 75040 | F257: 74020 | G257: 101059 | H257: =+B257/E257-1 -> -0.014925373 | I257: =+G257/G256-1 -> -0.10670026
A258: Dec 20, 2024 15:00:00 | B258: 74900 | C258: 73920 | D258: 58389 | E258: 74080 | F258: 73900 | G258: 83544 | H258: 0.011069114 | I258: -0.1733146
A259: Dec 23, 2024 15:00:00 | B259: 74480 | C259: 74900 | D259: 29915 | E259: 74620 | F259: 75100 | G259: 74112 | H259: -0.0018761726 | I259: -0.11289859
A260: Dec 24, 2024 15:00:00 | B260: 75140 | C260: 74480 | D260: 25536 | E260: 74760 | F260: 74240 | G260: 65026 | H260: 0.005082932 | I260: -0.12259823
A261: Dec 26, 2024 15:00:00 | B261: 74520 | C261: 74760 | D261: 19870 | E261: 74720 | F261: 74760 | G261: 48711 | H261: -0.0026766595 | I261: -0.25089964
A262: Dec 27, 2024 15:00:00 | B262: 73600 | C262: 74520 | D262: 21861 | E262: 74680 | F262: 74500 | G262: 40165 | H262: -0.014461703 | I262: -0.17544292
A263: Dec 30, 2024 15:00:00 | B263: 74520 | C263: 73600 | D263: 25319 | E263: 74400 | F263: 73000 | G263: 30840 | H263: 0.0016129032 | I263: -0.23216731
A264: Jan 03, 2025 15:00:00 | B264: 73020 | C264: 73840 | D264: 3358 | E264: 73880 | F264: 73880 | G264: 8307 | H264: -0.011640498 | I264: -0.73064202
A265: Jan 06, 2025 15:00:00 | B265: 74660 | C265: 73020 | D265: 1693 | E265: 73240 | F265: 73240 | G265: 6511 | H265: 0.019388312 | I265: -0.2162032
A266: Jan 07, 2025 15:00:00 | B266: 76160 | C266: 74660 | D266: 1143 | E266: 74960 | F266: 74960 | G266: 4912 | H266: 0.016008538 | I266: -0.2455844
A267: Jan 08, 2025 15:00:00 | B267: 74360 | C267: 76160 | D267: 1341 | E267: 74820 | F267: 74820 | G267: 4838 | H267: =+B267/E267-1 -> -0.0061480887 | I267: =+G267/G266-1 -> -0.015065147
A268: Jan 09, 2025 15:00:00 | B268: 75420 | C268: 74360 | D268: 559 | E268: 74880 | F268: 74860 | G268: 3535 | H268: 0.0072115385 | I268: -0.26932617
A269: Jan 10, 2025 15:00:00 | B269: 74920 | C269: 75420 | D269: 243 | E269: 75020 | F269: 75020 | G269: 2646 | H269: -0.0013329779 | I269: -0.25148515
A270: Jan 13, 2025 15:00:00 | B270: 75040 | C270: 74920 | D270: 566 | E270: 74980 | F270: 76000 | G270: 1631 | H270: 0.00080021339 | I270: -0.38359788
A271: Jan 14, 2025 15:00:00 | B271: 76040 | C271: 75040 | D271: 415 | E271: 75780 | F271: 75880 | G271: 395 | H271: 0.0034309844 | I271: -0.75781729

Sheet lc2502
A1: Date | B1: Latest | C1: Prev.Close | D1: Volume | E1: Prev.Settle | F1: Open | G1: Open Interest | H1: Var % | I1: O.I %
A70: Mar 19, 2024 15:00:00 | B70: 114350 | C70: 116050 | D70: 144 | E70: 116950 | F70: 116050 | G70: 409 | H70: =+B70/E70-1 -> -0.022231723 | I70: 0
A72: Mar 25, 2024 15:00:00 | B72: 108000 | C72: 114450 | D72: 143 | E72: 114150 | F72: 113200 | G72: 553 | H72: =+B72/E72-1 -> -0.053876478 | I72: =+G72/G70-1 -> 0.35207824
A73: Mar 28, 2024 15:00:00 | B73: 109350 | C73: 109000 | D73: 88 | E73: 108100 | F73: 109650 | G73: 564 | H73: =+B73/E73-1 -> 0.011563367 | I73: =+G73/G72-1 -> 0.019891501
A74: Mar 29, 2024 15:00:00 | B74: 108650 | C74: 109350 | D74: 84 | E74: 109150 | F74: 109500 | G74: 573 | H74: =+B74/E74-1 -> -0.004580852 | I74: =+G74/G73-1 -> 0.015957447
A75: Apr 01, 2024 15:00:00 | B75: 112600 | C75: 108650 | D75: 128 | E75: 108800 | F75: 108300 | G75: 558 | H75: =+B75/E75-1 -> 0.034926471 | I75: =+G75/G74-1 -> -0.02617801
A76: Apr 02, 2024 15:00:00 | B76: 112300 | C76: 112600 | D76: 22 | E76: 110950 | F76: 112900 | G76: 563 | H76: =+B76/E76-1 -> 0.012167643 | I76: =+G76/G75-1 -> 0.0089605735
A77: Apr 03, 2024 15:00:00 | B77: 113150 | C77: 112300 | D77: 89 | E77: 112400 | F77: 112400 | G77: 595 | H77: =+B77/E77-1 -> 0.0066725979 | I77: =+G77/G76-1 -> 0.056838366
A78: Apr 08, 2024 15:00:00 | B78: 114400 | C78: 113150 | D78: 97 | E78: 113600 | F78: 113800 | G78: 605 | H78: =+B78/E78-1 -> 0.0070422535 | I78: =+G78/G77-1 -> 0.016806723
A79: Apr 09, 2024 15:00:00 | B79: 114450 | C79: 114400 | D79: 83 | E79: 114800 | F79: 114550 | G79: 613 | H79: =+B79/E79-1 -> -0.0030487805 | I79: =+G79/G78-1 -> 0.01322314
A80: Apr 10, 2024 15:00:00 | B80: 116700 | C80: 114450 | D80: 204 | E80: 114550 | F80: 116800 | G80: 671 | H80: =+B80/E80-1 -> 0.018769096 | I80: =+G80/G79-1 -> 0.094616639
A81: Apr 11, 2024 15:00:00 | B81: 113550 | C81: 116700 | D81: 151 | E81: 116850 | F81: 115600 | G81: 687 | H81: =+B81/E81-1 -> -0.028241335 | I81: =+G81/G80-1 -> 0.023845007
A82: Apr 12, 2024 15:00:00 | B82: 113500 | C82: 113550 | D82: 57 | E82: 113750 | F82: 113200 | G82: 681 | H82: =+B82/E82-1 -> -0.0021978022 | I82: =+G82/G81-1 -> -0.0087336245
A83: Apr 15, 2024 15:00:00 | B83: 112900 | C83: 113500 | D83: 67 | E83: 113300 | F83: 114800 | G83: 671 | H83: =+B83/E83-1 -> -0.0035304501 | I83: =+G83/G82-1 -> -0.014684288
A84: Apr 16, 2024 15:00:00 | B84: 110800 | C84: 112900 | D84: 67 | E84: 113350 | F84: 111750 | G84: 670 | H84: =+B84/E84-1 -> -0.022496692 | I84: =+G84/G83-1 -> -0.001490313
... A281: Feb 17, 2025 15:00:00 | B281: 74500 | C281: 75620 | D281: 135 | E281: 75620 | F281: 75620 | G281: 238 | H281: =+B281/E281-1 -> -0.014810897 | I281: =+G281/G280-1 -> 0

Sheet lc2503
A1: Date | B1: Latest | C1: Prev.Close | D1: Volume | E1: Prev.Settle | F1: Open | G1: Open Interest | H1: Var % | I1: O.I %
A70: Mar 19, 2024 15:00:00 | B70: 115050 | C70: 116000 | D70: 5 | E70: 117100 | F70: 117300 | G70: 582050 | H70: =+B70/E70-1 -> -0.017506405 | I70: 0
A73: Mar 25, 2024 15:00:00 | B73: 108250 | C73: 113100 | D73: 35 | E73: 114450 | F73: 113250 | G73: 110 | H73: =+B73/E73-1 -> -0.054172128 | I73: =+G73/G70-1 -> -0.99981101
A74: Mar 28, 2024 15:00:00 | B74: 109300 | C74: 108700 | D74: 36 | E74: 108150 | F74: 108800 | G74: 122 | H74: =+B74/E74-1 -> 0.01063338 | I74: =+G74/G73-1 -> 0.10909091
A75: Mar 29, 2024 15:00:00 | B75: 108150 | C75: 109300 | D75: 30 | E75: 109000 | F75: 109250 | G75: 139 | H75: =+B75/E75-1 -> -0.0077981651 | I75: =+G75/G74-1 -> 0.13934426
A76: Apr 01, 2024 15:00:00 | B76: 112750 | C76: 108150 | D76: 55 | E76: 108800 | F76: 107550 | G76: 165 | H76: =+B76/E76-1 -> 0.036305147 | I76: =+G76/G75-1 -> 0.18705036
A77: Apr 02, 2024 15:00:00 | B77: 112350 | C77: 112750 | D77: 31 | E77: 111400 | F77: 111900 | G77: 170 | H77: =+B77/E77-1 -> 0.0085278276 | I77: =+G77/G76-1 -> 0.03030303
A78: Apr 03, 2024 15:00:00 | B78: 112750 | C78: 112350 | D78: 26 | E78: 112150 | F78: 112850 | G78: 167 | H78: =+B78/E78-1 -> 0.0053499777 | I78: =+G78/G77-1 -> -0.017647059
A79: Apr 03, 2024 15:00:00 | B79: 112750 | C79: 112350 | D79: 26 | E79: 112150 | F79: 112850 | G79: 167 | H79: =+B79/E79-1 -> 0.0053499777 | I79: =+G79/G78-1 -> 0
A80: Apr 03, 2024 15:00:00 | B80: 112750 | C80: 112350 | D80: 26 | E80: 112150 | F80: 112850 | G80: 167 | H80: =+B80/E80-1 -> 0.0053499777 | I80: =+G80/G79-1 -> 0
A81: Apr 03, 2024 15:00:00 | B81: 112750 | C81: 112350 | D81: 26 | E81: 112150 | F81: 112850 | G81: 167 | H81: =+B81/E81-1 -> 0.0053499777 | I81: =+G81/G80-1 -> 0
A82: Apr 03, 2024 15:00:00 | B82: 112750 | C82: 112350 | D82: 26 | E82: 112150 | F82: 112850 | G82: 167 | H82: =+B82/E82-1 -> 0.0053499777 | I82: =+G82/G81-1 -> 0
A83: Apr 03, 2024 15:00:00 | B83: 112750 | C83: 112350 | D83: 26 | E83: 112150 | F83: 112850 | G83: 167 | H83: =+B83/E83-1 -> 0.0053499777 | I83: =+G83/G82-1 -> 0
A84: Apr 03, 2024 15:00:00 | B84: 112750 | C84: 112350 | D84: 26 | E84: 112150 | F84: 112850 | G84: 167 | H84: =+B84/E84-1 -> 0.0053499777 | I84: =+G84/G83-1 -> 0
A85: Apr 03, 2024 15:00:00 | B85: 112750 | C85: 112350 | D85: 26 | E85: 112150 | F85: 112850 | G85: 167 | H85: =+B85/E85-1 -> 0.0053499777 | I85: =+G85/G84-1 -> 0
... A300: Mar 14, 2025 15:00:00 | B300: 73900 | C300: 73700 | D300: 118 | E300: 73840 | F300: 74000 | G300: 0 | H300: =+B300/E300-1 -> 0.00081256771 | I300: =+G300/G299-1 -> -1

Sheet lc2504
A1: Date | B1: Latest | C1: Prev.Close | D1: Volume | E1: Prev.Settle | F1: Open | G1: Open Interest | H1: Var % | I1: O.I %
A93: Apr 17, 2024 15:00:00 | B93: 112250 | C93: 110700 | D93: 13 | E93: 110700 | F93: 112000 | G93: 12 | H93: =+B93/E93-1 -> 0.014001807 | I93: 0
A94: Apr 17, 2024 15:00:00 | B94: 112250 | C94: 110700 | D94: 13 | E94: 110700 | F94: 112000 | G94: 12 | H94: =+B94/E94-1 -> 0.014001807 | I94: =+G94/G93-1 -> 0
A95: Apr 19, 2024 15:00:00 | B95: 110650 | C95: 111850 | D95: 4 | E95: 111850 | F95: 110500 | G95: 442050 | H95: =+B95/E95-1 -> -0.010728654 | I95: =+G95/G94-1 -> 36836.5
A96: Apr 22, 2024 15:00:00 | B96: 112400 | C96: 110650 | D96: 17 | E96: 110500 | F96: 113300 | G96: 26 | H96: =+B96/E96-1 -> 0.01719457 | I96: =+G96/G95-1 -> -0.99994118
A97: Apr 23, 2024 15:00:00 | B97: 112050 | C97: 112400 | D97: 6 | E97: 113050 | F97: 113450 | G97: 677200 | H97: =+B97/E97-1 -> -0.0088456435 | I97: =+G97/G96-1 -> 26045.154
A98: Apr 24, 2024 15:00:00 | B98: 114750 | C98: 112050 | D98: 14 | E98: 112850 | F98: 112150 | G98: 32 | H98: =+B98/E98-1 -> 0.016836509 | I98: =+G98/G97-1 -> -0.99995275
A99: Apr 25, 2024 15:00:00 | B99: 112550 | C99: 114750 | D99: 10 | E99: 113400 | F99: 115100 | G99: 32 | H99: =+B99/E99-1 -> -0.0074955908 | I99: =+G99/G98-1 -> 0
A100: Apr 26, 2024 15:00:00 | B100: 113800 | C100: 112550 | D100: 25 | E100: 114300 | F100: 112550 | G100: 55 | H100: =+B100/E100-1 -> -0.0043744532 | I100: =+G100/G99-1 -> 0.71875
A101: Apr 29, 2024 15:00:00 | B101: 116050 | C101: 113800 | D101: 173 | E101: 113100 | F101: 114600 | G101: 136 | H101: =+B101/E101-1 -> 0.026083112 | I101: =+G101/G100-1 -> 1.4727273
A102: Apr 30, 2024 15:00:00 | B102: 114700 | C102: 116050 | D102: 83 | E102: 116050 | F102: 117150 | G102: 155 | H102: =+B102/E102-1 -> -0.011632917 | I102: =+G102/G101-1 -> 0.13970588
A103: May 06, 2024 15:00:00 | B103: 115100 | C103: 114700 | D103: 44 | E103: 114800 | F103: 114750 | G103: 161 | H103: =+B103/E103-1 -> 0.0026132404 | I103: =+G103/G102-1 -> 0.038709677
A104: May 07, 2024 15:00:00 | B104: 116850 | C104: 115100 | D104: 38 | E104: 114850 | F104: 117200 | G104: 173 | H104: =+B104/E104-1 -> 0.017414018 | I104: =+G104/G103-1 -> 0.074534161
A105: May 08, 2024 15:00:00 | B105: 116200 | C105: 116850 | D105: 36 | E105: 116500 | F105: 116500 | G105: 191 | H105: =+B105/E105-1 -> -0.0025751073 | I105: =+G105/G104-1 -> 0.10404624
... A321: Apr 15, 2025 15:00:00 | B321: 70600 | C321: 71000 | D321: 514 | E321: 70880 | F321: 70600 | G321: 0 | H321: =+B321/E321-1 -> -0.0039503386 | I321: =+G321/G320-1 -> #DIV/0!

Sheet lc2505
A1: Date | B1: Latest | C1: Prev.Close | D1: Volume | E1: Prev.Settle | F1: Open | G1: Open Interest | H1: Var % | I1: O.I %
A112: May 20, 2024 15:00:00 | B112: 113400 | C112: 112450 | D112: 4 | E112: 112450 | F112: 114500 | G112: 459200 | H112: 0 | I112: 0
A113: May 21, 2024 15:00:00 | B113: 114400 | C113: 113400 | D113: 28 | E113: 114800 | F113: 115000 | G113: 25 | H113: =+B113/E113-1 -> -0.0034843206 | I113: =+G113/G112-1 -> -0.99994556
A114: May 22, 2024 15:00:00 | B114: 113800 | C114: 114400 | D114: 49 | E114: 114750 | F114: 114750 | G114: 62 | H114: =+B114/E114-1 -> -0.0082788671 | I114: =+G114/G113-1 -> 1.48
A115: May 23, 2024 15:00:00 | B115: 114200 | C115: 113800 | D115: 21 | E115: 114200 | F115: 113550 | G115: 69 | H115: =+B115/E115-1 -> 0 | I115: =+G115/G114-1 -> 0.11290323
A116: May 24, 2024 15:00:00 | B116: 114650 | C116: 114200 | D116: 75 | E116: 113550 | F116: 114350 | G116: 106 | H116: =+B116/E116-1 -> 0.0096873624 | I116: =+G116/G115-1 -> 0.53623188
A117: May 27, 2024 15:00:00 | B117: 113800 | C117: 114650 | D117: 45 | E117: 114650 | F117: 115100 | G117: 116 | H117: =+B117/E117-1 -> -0.0074138683 | I117: =+G117/G116-1 -> 0.094339623
A118: May 28, 2024 15:00:00 | B118: 112850 | C118: 113800 | D118: 69 | E118: 114300 | F118: 114900 | G118: 139 | H118: =+B118/E118-1 -> -0.012685914 | I118: =+G118/G117-1 -> 0.19827586
A119: May 29, 2024 15:00:00 | B119: 112650 | C119: 112850 | D119: 48 | E119: 113500 | F119: 112950 | G119: 162 | H119: =+B119/E119-1 -> -0.0074889868 | I119: =+G119/G118-1 -> 0.16546763
A120: May 30, 2024 15:00:00 | B120: 113050 | C120: 112650 | D120: 49 | E120: 112450 | F120: 112650 | G120: 181 | H120: =+B120/E120-1 -> 0.0053357048 | I120: =+G120/G119-1 -> 0.11728395
A121: May 31, 2024 15:00:00 | B121: 113000 | C121: 113050 | D121: 31 | E121: 113900 | F121: 113750 | G121: 199 | H121: =+B121/E121-1 -> -0.0079016681 | I121: =+G121/G120-1 -> 0.099447514
A122: Jun 03, 2024 15:00:00 | B122: 111350 | C122: 113000 | D122: 99 | E122: 113000 | F122: 112000 | G122: 243 | H122: =+B122/E122-1 -> -0.01460177 | I122: =+G122/G121-1 -> 0.22110553
A123: Jun 04, 2024 15:00:00 | B123: 110600 | C123: 111350 | D123: 42 | E123: 111250 | F123: 111300 | G123: 264 | H123: =+B123/E123-1 -> -0.0058426966 | I123: =+G123/G122-1 -> 0.086419753
A124: Jun 05, 2024 15:00:00 | B124: 109050 | C124: 110600 | D124: 145 | E124: 111050 | F124: 110000 | G124: 321 | H124: =+B124/E124-1 -> -0.018009905 | I124: =+G124/G123-1 -> 0.21590909
... A338: May 16, 2025 15:00:00 | B338: 62120 | C338: 64200 | D338: 106 | E338: 64360 | F338: 62700 | G338: 176 | H338: =+B338/E338-1 -> -0.034804226 | I338: =+G338/G337-1 -> -0.21076233

Sheet Contrato 2505
A1: Date | B1: Latest | C1: Prev.Close | D1: Volume | E1: Prev.Settle | F1: Open | G1: Open Interest | H1: Var % | I1: O.I %
A112: May 20, 2024 15:00:00 | B112: 113400 | C112: 112450 | D112: 4 | E112: 112450 | F112: 114500 | G112: 459200 | H112: 0 | I112: 0
A113: May 21, 2024 15:00:00 | B113: 114400 | C113: 113400 | D113: 28 | E113: 114800 | F113: 115000 | G113: 25 | H113: -0.0034843206 | I113: -0.99994556
A114: May 22, 2024 15:00:00 | B114: 113800 | C114: 114400 | D114: 49 | E114: 114750 | F114: 114750 | G114: 62 | H114: -0.0082788671 | I114: 1.48
A115: May 23, 2024 15:00:00 | B115: 114200 | C115: 113800 | D115: 21 | E115: 114200 | F115: 113550 | G115: 69 | H115: 0 | I115: 0.11290323
A116: May 24, 2024 15:00:00 | B116: 114650 | C116: 114200 | D116: 75 | E116: 113550 | F116: 114350 | G116: 106 | H116: 0.0096873624 | I116: 0.53623188
A117: May 27, 2024 15:00:00 | B117: 113800 | C117: 114650 | D117: 45 | E117: 114650 | F117: 115100 | G117: 116 | H117: -0.0074138683 | I117: 0.094339623
A118: May 28, 2024 15:00:00 | B118: 112850 | C118: 113800 | D118: 69 | E118: 114300 | F118: 114900 | G118: 139 | H118: -0.012685914 | I118: 0.19827586
A119: May 29, 2024 15:00:00 | B119: 112650 | C119: 112850 | D119: 48 | E119: 113500 | F119: 112950 | G119: 162 | H119: -0.0074889868 | I119: 0.16546763
A120: May 30, 2024 15:00:00 | B120: 113050 | C120: 112650 | D120: 49 | E120: 112450 | F120: 112650 | G120: 181 | H120: 0.0053357048 | I120: 0.11728395
A121: May 31, 2024 15:00:00 | B121: 113000 | C121: 113050 | D121: 31 | E121: 113900 | F121: 113750 | G121: 199 | H121: -0.0079016681 | I121: 0.099447514
A122: Jun 03, 2024 15:00:00 | B122: 111350 | C122: 113000 | D122: 99 | E122: 113000 | F122: 112000 | G122: 243 | H122: -0.01460177 | I122: 0.22110553
A123: Jun 04, 2024 15:00:00 | B123: 110600 | C123: 111350 | D123: 42 | E123: 111250 | F123: 111300 | G123: 264 | H123: -0.0058426966 | I123: 0.086419753
... A237: Nov 25, 2024 15:00:00 | B237: 82350 | C237: 81250 | D237: 31505 | E237: 82000 | F237: 81900 | G237: 76465 | H237: 0.0042682927 | I237: 0.035451677
A238: Nov 26, 2024 15:00:00 | B238: 81050 | C238: 82350 | D238: 34577 | E238: 82200 | F238: 82000 | G238: 79055 | H238: =+B238/E238-1 -> -0.013990268 | I238: =+G238/G237-1 -> 0.033871706
A239: Nov 27, 2024 15:00:00 | B239: 81200 | C239: 81050 | D239: 20013 | E239: 81350 | F239: 81000 | G239: 80146 | H239: -0.0018438844 | I239: 0.013800519
A240: Nov 28, 2024 15:00:00 | B240: 80800 | C240: 81200 | D240: 31952 | E240: 81200 | F240: 81000 | G240: 81082 | H240: -0.0049261084 | I240: 0.011678686
A241: Nov 29, 2024 15:00:00 | B241: 81800 | C241: 80800 | D241: 44240 | E241: 80550 | F241: 80850 | G241: 88730 | H241: 0.015518312 | I241: 0.094324264
A242: Dec 02, 2024 15:00:00 | B242: 81400 | C242: 81800 | D242: 34657 | E242: 81600 | F242: 80900 | G242: 94627 | H242: -0.0024509804 | I242: 0.066460047
A243: Dec 03, 2024 15:00:00 | B243: 80700 | C243: 81400 | D243: 40153 | E243: 81650 | F243: 81400 | G243: 98017 | H243: -0.011635028 | I243: 0.03582487
A244: Dec 04, 2024 15:00:00 | B244: 79150 | C244: 80700 | D244: 51484 | E244: 81400 | F244: 80900 | G244: 99735 | H244: -0.027641278 | I244: 0.017527572
A245: Dec 05, 2024 15:00:00 | B245: 79650 | C245: 79150 | D245: 32916 | E245: 80200 | F245: 79300 | G245: 102496 | H245: -0.0068578554 | I245: 0.027683361
A246: Dec 06, 2024 15:00:00 | B246: 80000 | C246: 79650 | D246: 42844 | E246: 79400 | F246: 79750 | G246: 105968 | H246: 0.0075566751 | I246: 0.033874493
A247: Dec 09, 2024 15:00:00 | B247: 80100 | C247: 80000 | D247: 50395 | E247: 79850 | F247: 79850 | G247: 108784 | H247: 0.0031308704 | I247: 0.02657406
A248: Dec 10, 2024 15:00:00 | B248: 80150 | C248: 80100 | D248: 81866 | E248: 79600 | F248: 82000 | G248: 112325 | H248: 0.0069095477 | I248: 0.032550743
A249: Dec 11, 2024 15:00:00 | B249: 80300 | C249: 80150 | D249: 43340 | E249: 80950 | F249: 80300 | G249: 116148 | H249: -0.0080296479 | I249: 0.034035166
A250: Dec 12, 2024 15:00:00 | B250: 80500 | C250: 80300 | D250: 47486 | E250: 80400 | F250: 80450 | G250: 119147 | H250: 0.0012437811 | I250: 0.025820505
... A254: Dec 18, 2024 15:00:00 | B254: 77140 | C254: 77800 | D254: 79080 | E254: 78140 | F254: 77800 | G254: 135107 | H254: -0.012797543 | I254: 0.042387723
A255: Dec 19, 2024 15:00:00 | B255: 76680 | C255: 77140 | D255: 78488 | E255: 77660 | F255: 76980 | G255: 132883 | H255: =+B255/E255-1 -> -0.012619109 | I255: =+G255/G254-1 -> -0.016461027
A256: Dec 20, 2024 15:00:00 | B256: 77880 | C256: 76680 | D256: 116409 | E256: 76740 | F256: 76680 | G256: 144633 | H256: 0.014855356 | I256: 0.088423651
A257: Dec 23, 2024 15:00:00 | B257: 77180 | C257: 77880 | D257: 106661 | E257: 77480 | F257: 77660 | G257: 151398 | H257: -0.003871967 | I257: 0.046773558
A258: Dec 24, 2024 15:00:00 | B258: 78200 | C258: 77180 | D258: 112681 | E258: 77480 | F258: 77000 | G258: 160753 | H258: 0.0092927207 | I258: 0.061790777
A259: Dec 26, 2024 15:00:00 | B259: 77520 | C259: 77500 | D259: 92560 | E259: 77480 | F259: 77600 | G259: 163310 | H259: 0.00051626226 | I259: 0.015906391
A260: Dec 27, 2024 15:00:00 | B260: 76500 | C260: 77520 | D260: 122618 | E260: 77680 | F260: 77620 | G260: 171752 | H260: -0.015190525 | I260: 0.051693099
A261: Jan 03, 2025 15:00:00 | B261: 76380 | C261: 77800 | D261: 188527 | E261: 77860 | F261: 77560 | G261: 188017 | H261: -0.019008477 | I261: 0.03626032
A262: Jan 06, 2025 15:00:00 | B262: 77660 | C262: 76380 | D262: 298136 | E262: 76500 | F262: 76680 | G262: 183347 | H262: =+B262/E262-1 -> 0.015163399 | I262: =+G262/G261-1 -> -0.02483818
A263: Jan 07, 2025 15:00:00 | B263: 78820 | C263: 77660 | D263: 262723 | E263: 78140 | F263: 77860 | G263: 204995 | H263: 0.0087023292 | I263: 0.1180712
A264: Jan 08, 2025 15:00:00 | B264: 77180 | C264: 78820 | D264: 202254 | E264: 78540 | F264: 78920 | G264: 195768 | H264: -0.017316017 | I264: -0.045010854
A265: Jan 09, 2025 15:00:00 | B265: 78240 | C265: 77180 | D265: 162495 | E265: 77900 | F265: 77400 | G265: 198644 | H265: 0.00436457 | I265: 0.014690859
A266: Jan 10, 2025 15:00:00 | B266: 77920 | C266: 78240 | D266: 148488 | E266: 77900 | F266: 78000 | G266: 197891 | H266: 0.00025673941 | I266: -0.003790701
A267: Jan 13, 2025 15:00:00 | B267: 78760 | C267: 77920 | D267: 201942 | E267: 77800 | F267: 78520 | G267: 201358 | H267: 0.012339332 | I267: 0.017519746
A268: Jan 14, 2025 15:00:00 | B268: 79100 | C268: 78760 | D268: 204887 | E268: 78720 | F268: 78740 | G268: 219211 | H268: 0.0048272358 | I268: 0.088662978
A269: Jan 15, 2025 15:00:00 | B269: 80260 | C269: 79100 | D269: 320628 | E269: 79280 | F269: 78880 | G269: 243381 | H269: =+B269/E269-1 -> 0.012361251 | I269: =+G269/G268-1 -> 0.11025907
A270: Jan 16, 2025 15:00:00 | B270: 79860 | C270: 80260 | D270: 174290 | E270: 80160 | F270: 80500 | G270: 237300 | H270: -0.003742515 | I270: -0.024985517
A271: Jan 17, 2025 15:00:00 | B271: 80740 | C271: 79860 | D271: 235115 | E271: 79920 | F271: 80500 | G271: 244609 | H271: 0.01026026 | I271: 0.030800674
A272: Jan 20, 2025 15:00:00 | B272: 80720 | C272: 80740 | D272: 244998 | E272: 80700 | F272: 80900 | G272: 248620 | H272: 0.00024783147 | I272: 0.016397598
A273: Jan 21, 2025 15:00:00 | B273: 78520 | C273: 80720 | D273: 312684 | E273: 80500 | F273: 81000 | G273: 241515 | H273: -0.024596273 | I273: -0.028577749
A274: Jan 22, 2025 15:00:00 | B274: 79200 | C274: 78520 | D274: 134231 | E274: 79260 | F274: 78520 | G274: 234572 | H274: -0.00075700227 | I274: -0.028747697
A275: Jan 23, 2025 15:00:00 | B275: 79580 | C275: 79200 | D275: 126404 | E275: 79000 | F275: 79120 | G275: 231918 | H275: 0.0073417722 | I275: -0.011314223
A276: Jan 24, 2025 15:00:00 | B276: 79580 | C276: 79580 | D276: 104125 | E276: 79520 | F276: 79520 | G276: 224092 | H276: 0.00075452716 | I276: -0.033744686
A277: Jan 27, 2025 15:00:00 | B277: 79620 | C277: 79580 | D277: 135203 | E277: 79400 | F277: 79480 | G277: 222388 | H277: 0.0027707809 | I277: -0.0076040198
A278: Feb 06, 2025 15:00:00 | B278: 77500 | C278: 78120 | D278: 159155 | E278: 78420 | F278: 78120 | G278: 245868 | H278: =+B278/E278-1 -> -0.011731701 | I278: =+G278/G277-1 -> 0.10558124
A279: Feb 07, 2025 15:00:00 | B279: 77800 | C279: 77500 | D279: 154686 | E279: 77600 | F279: 77500 | G279: 237903 | H279: 0.0025773196 | I279: -0.032395432
A280: Feb 10, 2025 15:00:00 | B280: 78600 | C280: 77800 | D280: 199973 | E280: 78060 | F280: 77600 | G280: 238359 | H280: 0.0069177556 | I280: 0.0019167476
A281: Feb 11, 2025 15:00:00 | B281: 77300 | C281: 78600 | D281: 165731 | E281: 78440 | F281: 78300 | G281: 243842 | H281: -0.014533401 | I281: 0.023003117
A282: Feb 12, 2025 15:00:00 | B282: 77500 | C282: 77300 | D282: 121343 | E282: 77620 | F282: 77300 | G282: 246602 | H282: -0.0015459933 | I282: 0.011318805
A283: Feb 13, 2025 15:00:00 | B283: 77300 | C283: 77500 | D283: 134408 | E283: 77640 | F283: 77300 | G283: 248595 | H283: -0.004379186 | I283: 0.0080818485
A284: Feb 14, 2025 15:00:00 | B284: 76780 | C284: 77300 | D284: 153612 | E284: 77540 | F284: 77200 | G284: 255409 | H284: -0.0098013928 | I284: 0.027410044
A285: Feb 17, 2025 15:00:00 | B285: 77160 | C285: 76780 | D285: 120500 | E285: 76980 | F285: 76600 | G285: 248480 | H285: =+B285/E285-1 -> 0.0023382697 | I285: =+G285/G284-1 -> -0.027129036
A286: Feb 18, 2025 15:00:00 | B286: 77060 | C286: 77160 | D286: 93893 | E286: 76960 | F286: 77420 | G286: 247338 | H286: 0.0012993763 | I286: -0.0045959433
A287: Feb 19, 2025 15:00:00 | B287: 77300 | C287: 77060 | D287: 111053 | E287: 77200 | F287: 77260 | G287: 245775 | H287: =+B287/E287-1 -> 0.0012953368 | I287: =+G287/G286-1 -> -0.0063192878
A288: Feb 20, 2025 15:00:00 | B288: 77180 | C288: 77300 | D288: 110015 | E288: 77420 | F288: 77300 | G288: 243976 | H288: =+B288/E288-1 -> -0.0030999742 | I288: =+G288/G287-1 -> -0.007319703
A289: Feb 21, 2025 15:00:00 | B289: 76620 | C289: 77180 | D289: 134313 | E289: 77320 | F289: 77020 | G289: 256680 | H289: -0.009053285 | I289: 0.052070695
A290: Mar 04, 2025 15:00:00 | B290: 75260 | C290: 75400 | D290: 91783 | E290: 75500 | F290: 75300 | G290: 273492 | H290: -0.0031788079 | I290: 0.065497896
A291: Mar 05, 2025 15:00:00 | B291: 75340 | C291: 75260 | D291: 107729 | E291: 75280 | F291: 75320 | G291: 267741 | H291: 0.00079702444 | I291: -0.021028037
A292: Mar 06, 2025 15:00:00 | B292: 76800 | C292: 75340 | D292: 156436 | E292: 75340 | F292: 75340 | G292: 257990 | H292: 0.019378816 | I292: -0.036419525
A293: Mar 07, 2025 15:00:00 | B293: 76120 | C293: 76800 | D293: 167557 | E293: 75960 | F293: 76720 | G293: 258267 | H293: 0.0021063718 | I293: 0.001073685
A294: Mar 10, 2025 15:00:00 | B294: 75760 | C294: 76120 | D294: 106629 | E294: 76520 | F294: 76040 | G294: 256739 | H294: -0.0099320439 | I294: -0.0059163579
A295: Mar 11, 2025 15:00:00 | B295: 75960 | C295: 75760 | D295: 88034 | E295: 76100 | F295: 75620 | G295: 256599 | H295: =+B295/E295-1 -> -0.0018396846 | I295: =+G295/G294-1 -> -0.00054530087
A296: Mar 12, 2025 15:00:00 | B296: 75600 | C296: 75960 | D296: 75956 | E296: 75660 | F296: 76100 | G296: 256166 | H296: -0.00079302141 | I296: -0.0016874579
A297: Mar 13, 2025 15:00:00 | B297: 75340 | C297: 75600 | D297: 71232 | E297: 75820 | F297: 75600 | G297: 258337 | H297: -0.0063307834 | I297: 0.0084749733
A298: Mar 14, 2025 15:00:00 | B298: 75540 | C298: 75340 | D298: 99360 | E298: 75460 | F298: 75540 | G298: 255256 | H298: 0.0010601643 | I298: -0.011926282
A299: Mar 17, 2025 15:00:00 | B299: 76240 | C299: 75540 | D299: 137017 | E299: 75720 | F299: 75780 | G299: 254611 | H299: 0.0068674062 | I299: -0.002526875
A300: Mar 18, 2025 15:00:00 | B300: 75400 | C300: 76240 | D300: 134587 | E300: 76120 | F300: 76200 | G300: 256955 | H300: -0.0094587493 | I300: 0.0092062008
A301: Mar 19, 2025 15:00:00 | B301: 75200 | C301: 75400 | D301: 69936 | E301: 75780 | F301: 75580 | G301: 253930 | H301: -0.0076537345 | I301: -0.011772489
A302: Mar 20, 2025 15:00:00 | B302: 73260 | C302: 75200 | D302: 236597 | E302: 75380 | F302: 75220 | G302: 261415 | H302: -0.028124171 | I302: 0.029476627
A303: Mar 21, 2025 15:00:00 | B303: 73240 | C303: 73260 | D303: 153360 | E303: 73780 | F303: 73500 | G303: 256784 | H303: -0.0073190567 | I303: -0.017715127
A304: Mar 24, 2025 15:00:00 | B304: 73720 | C304: 73240 | D304: 92617 | E304: 73080 | F304: 73400 | G304: 247653 | H304: 0.008757526 | I304: -0.035559069
A305: Mar 25, 2025 15:00:00 | B305: 73800 | C305: 73720 | D305: 101240 | E305: 73560 | F305: 73720 | G305: 237509 | H305: 0.0032626427 | I305: -0.040960538
A306: Mar 26, 2025 15:00:00 | B306: 74480 | C306: 73800 | D306: 113885 | E306: 73960 | F306: 73620 | G306: 226538 | H306: 0.0070308275 | I306: -0.046191934
A307: Mar 27, 2025 15:00:00 | B307: 74380 | C307: 74480 | D307: 104899 | E307: 74200 | F307: 74420 | G307: 222920 | H307: 0.002425876 | I307: -0.015970831
... A337: May 16, 2025 15:00:00 | B337: 62120 | C337: 64200 | D337: 106 | E337: 64360 | F337: 62700 | G337: 176 | H337: -0.034804226 | I337: -0.21076233

Sheet lc2506
A1: Date | B1: Latest | C1: Prev.Close | D1: Volume | E1: Prev.Settle | F1: Open | G1: Open Interest | H1: Var % | I1: O.I %
A132: Jun 18, 2024 15:00:00 | B132: 103000 | C132: 104150 | D132: 2 | E132: 104150 | F132: 103000 | G132: 206000 | H132: 0 | I132: 0
A133: Jun 19, 2024 15:00:00 | B133: 102550 | C133: 103000 | D133: 25 | E133: 103000 | F133: 106050 | G133: 16 | H133: =+B133/E133-1 -> -0.004368932 | I133: =+G133/G132-1 -> -0.99992233
A134: Jun 20, 2024 15:00:00 | B134: 102800 | C134: 102550 | D134: 15 | E134: 102500 | F134: 102500 | G134: 24 | H134: =+B134/E134-1 -> 0.0029268293 | I134: =+G134/G133-1 -> 0.5
A135: Jun 21, 2024 15:00:00 | B135: 101600 | C135: 102800 | D135: 25 | E135: 102550 | F135: 103100 | G135: 46 | H135: =+B135/E135-1 -> -0.0092637738 | I135: =+G135/G134-1 -> 0.91666667
A136: Jun 24, 2024 15:00:00 | B136: 97950 | C136: 101600 | D136: 56 | E136: 102150 | F136: 100950 | G136: 80 | H136: =+B136/E136-1 -> -0.041116006 | I136: =+G136/G135-1 -> 0.73913043
A137: Jun 25, 2024 15:00:00 | B137: 99750 | C137: 97950 | D137: 96 | E137: 99550 | F137: 97500 | G137: 148 | H137: =+B137/E137-1 -> 0.0020090407 | I137: =+G137/G136-1 -> 0.85
A138: Jun 26, 2024 15:00:00 | B138: 102050 | C138: 99750 | D138: 197 | E138: 99100 | F138: 100800 | G138: 249 | H138: =+B138/E138-1 -> 0.029767911 | I138: =+G138/G137-1 -> 0.68243243
A139: Jun 27, 2024 15:00:00 | B139: 100150 | C139: 102050 | D139: 176 | E139: 102400 | F139: 101700 | G139: 260 | H139: =+B139/E139-1 -> -0.021972656 | I139: =+G139/G138-1 -> 0.044176707
A140: Jun 28, 2024 15:00:00 | B140: 100000 | C140: 100150 | D140: 203 | E140: 101150 | F140: 99500 | G140: 366 | H140: =+B140/E140-1 -> -0.011369254 | I140: =+G140/G139-1 -> 0.40769231
A141: Jul 01, 2024 15:00:00 | B141: 100450 | C141: 100000 | D141: 129 | E141: 99850 | F141: 98300 | G141: 427 | H141: =+B141/E141-1 -> 0.0060090135 | I141: =+G141/G140-1 -> 0.16666667
A142: Jul 02, 2024 15:00:00 | B142: 99400 | C142: 100450 | D142: 207 | E142: 98750 | F142: 100400 | G142: 507 | H142: =+B142/E142-1 -> 0.0065822785 | I142: =+G142/G141-1 -> 0.18735363
A143: Jul 03, 2024 15:00:00 | B143: 100150 | C143: 99400 | D143: 184 | E143: 99900 | F143: 99000 | G143: 591 | H143: =+B143/E143-1 -> 0.0025025025 | I143: =+G143/G142-1 -> 0.16568047
A144: Jul 04, 2024 15:00:00 | B144: 99550 | C144: 100150 | D144: 187 | E144: 99000 | F144: 100750 | G144: 662 | H144: =+B144/E144-1 -> 0.0055555556 | I144: =+G144/G143-1 -> 0.12013536
... A355: Jun 16, 2025 15:00:00 | B355: 60000 | C355: 59980 | D355: 18 | E355: 59980 | F355: 60000 | G355: 0 | H355: =+B355/E355-1 -> 0.00033344448 | I355: =+G355/G354-1 -> -1

Sheet lc2507
A1: Date | B1: Latest | C1: Prev.Close | D1: Volume | E1: Prev.Settle | F1: Open | G1: Open Interest | H1: Var % | I1: O.I %
A132: Jul 15, 2024 15:00:00 | B132: 95850 | C132: 98400 | D132: 24 | E132: 98400 | F132: 97350 | G132: 12
A133: Jul 17, 2024 15:00:00 | B133: 95500 | C133: 97350 | D133: 63 | E133: 96450 | F133: 98100 | G133: 52 | H133: =+B133/E133-1 -> -0.009849663 | I133: =+G133/G132-1 -> 3.3333333
A134: Jul 18, 2024 15:00:00 | B134: 94750 | C134: 95500 | D134: 324 | E134: 96050 | F134: 95700 | G134: 241 | H134: =+B134/E134-1 -> -0.013534617 | I134: =+G134/G133-1 -> 3.6346154
A135: Jul 19, 2024 15:00:00 | B135: 95700 | C135: 94750 | D135: 82 | E135: 93400 | F135: 94750 | G135: 257 | H135: =+B135/E135-1 -> 0.024625268 | I135: =+G135/G134-1 -> 0.066390041
A136: Jul 22, 2024 15:00:00 | B136: 96100 | C136: 95700 | D136: 53 | E136: 95450 | F136: 95400 | G136: 271 | H136: =+B136/E136-1 -> 0.0068098481 | I136: =+G136/G135-1 -> 0.054474708
A137: Jul 23, 2024 15:00:00 | B137: 94650 | C137: 96100 | D137: 189 | E137: 96000 | F137: 96950 | G137: 376 | H137: =+B137/E137-1 -> -0.0140625 | I137: =+G137/G136-1 -> 0.38745387
A138: Jul 24, 2024 15:00:00 | B138: 93650 | C138: 94650 | D138: 245 | E138: 94850 | F138: 94400 | G138: 530 | H138: =+B138/E138-1 -> -0.012651555 | I138: =+G138/G137-1 -> 0.40957447
A139: Jul 25, 2024 15:00:00 | B139: 93950 | C139: 93650 | D139: 54 | E139: 93400 | F139: 92950 | G139: 548 | H139: =+B139/E139-1 -> 0.005888651 | I139: =+G139/G138-1 -> 0.033962264
A140: Jul 26, 2024 15:00:00 | B140: 94050 | C140: 93950 | D140: 173 | E140: 93050 | F140: 94750 | G140: 573 | H140: =+B140/E140-1 -> 0.01074691 | I140: =+G140/G139-1 -> 0.045620438
A141: Jul 29, 2024 15:00:00 | B141: 92100 | C141: 94050 | D141: 154 | E141: 94450 | F141: 94050 | G141: 615 | H141: =+B141/E141-1 -> -0.024880889 | I141: =+G141/G140-1 -> 0.073298429
A142: Jul 30, 2024 15:00:00 | B142: 88650 | C142: 92100 | D142: 300 | E142: 92650 | F142: 92900 | G142: 721 | H142: =+B142/E142-1 -> -0.043173233 | I142: =+G142/G141-1 -> 0.17235772
A143: Jul 31, 2024 15:00:00 | B143: 89700 | C143: 88650 | D143: 292 | E143: 89450 | F143: 89000 | G143: 869 | H143: =+B143/E143-1 -> 0.0027948575 | I143: =+G143/G142-1 -> 0.20527046
A144: Aug 01, 2024 15:00:00 | B144: 88250 | C144: 89700 | D144: 280 | E144: 89900 | F144: 90550 | G144: 1014 | H144: =+B144/E144-1 -> -0.018353726 | I144: =+G144/G143-1 -> 0.16685846
... A356: Jul 14, 2025 15:00:00 | B356: 66200 | C356: 62920 | D356: 137 | E356: 64020 | F356: 64020 | G356: 0 | H356: =+B356/E356-1 -> 0.034051859 | I356: =+G356/G355-1 -> -1

Sheet Contrato 2507
A1: Date | B1: Latest | C1: Prev.Close | D1: Volume | E1: Prev.Settle | F1: Open | G1: Open Interest | H1: Var % | I1: O.I %
A132: Jul 15, 2024 15:00:00 | B132: 95850 | C132: 98400 | D132: 24 | E132: 98400 | F132: 97350 | G132: 12
A133: Jul 17, 2024 15:00:00 | B133: 95500 | C133: 97350 | D133: 63 | E133: 96450 | F133: 98100 | G133: 52 | H133: =+B133/E133-1 -> -0.009849663 | I133: =+G133/G132-1 -> 3.3333333
A134: Jul 18, 2024 15:00:00 | B134: 94750 | C134: 95500 | D134: 324 | E134: 96050 | F134: 95700 | G134: 241 | H134: =+B134/E134-1 -> -0.013534617 | I134: =+G134/G133-1 -> 3.6346154
A135: Jul 19, 2024 15:00:00 | B135: 95700 | C135: 94750 | D135: 82 | E135: 93400 | F135: 94750 | G135: 257 | H135: =+B135/E135-1 -> 0.024625268 | I135: =+G135/G134-1 -> 0.066390041
A136: Jul 22, 2024 15:00:00 | B136: 96100 | C136: 95700 | D136: 53 | E136: 95450 | F136: 95400 | G136: 271 | H136: =+B136/E136-1 -> 0.0068098481 | I136: =+G136/G135-1 -> 0.054474708
A137: Jul 23, 2024 15:00:00 | B137: 94650 | C137: 96100 | D137: 189 | E137: 96000 | F137: 96950 | G137: 376 | H137: =+B137/E137-1 -> -0.0140625 | I137: =+G137/G136-1 -> 0.38745387
A138: Jul 24, 2024 15:00:00 | B138: 93650 | C138: 94650 | D138: 245 | E138: 94850 | F138: 94400 | G138: 530 | H138: =+B138/E138-1 -> -0.012651555 | I138: =+G138/G137-1 -> 0.40957447
A139: Jul 25, 2024 15:00:00 | B139: 93950 | C139: 93650 | D139: 54 | E139: 93400 | F139: 92950 | G139: 548 | H139: =+B139/E139-1 -> 0.005888651 | I139: =+G139/G138-1 -> 0.033962264
A140: Jul 26, 2024 15:00:00 | B140: 94050 | C140: 93950 | D140: 173 | E140: 93050 | F140: 94750 | G140: 573 | H140: =+B140/E140-1 -> 0.01074691 | I140: =+G140/G139-1 -> 0.045620438
A141: Jul 29, 2024 15:00:00 | B141: 92100 | C141: 94050 | D141: 154 | E141: 94450 | F141: 94050 | G141: 615 | H141: =+B141/E141-1 -> -0.024880889 | I141: =+G141/G140-1 -> 0.073298429
A142: Jul 30, 2024 15:00:00 | B142: 88650 | C142: 92100 | D142: 300 | E142: 92650 | F142: 92900 | G142: 721 | H142: =+B142/E142-1 -> -0.043173233 | I142: =+G142/G141-1 -> 0.17235772
A143: Jul 31, 2024 15:00:00 | B143: 89700 | C143: 88650 | D143: 292 | E143: 89450 | F143: 89000 | G143: 869 | H143: =+B143/E143-1 -> 0.0027948575 | I143: =+G143/G142-1 -> 0.20527046
A144: Aug 01, 2024 15:00:00 | B144: 88250 | C144: 89700 | D144: 280 | E144: 89900 | F144: 90550 | G144: 1014 | H144: =+B144/E144-1 -> -0.018353726 | I144: =+G144/G143-1 -> 0.16685846
... A251: Jan 15, 2025 15:00:00 | B251: 80200 | C251: 79260 | D251: 8180 | E251: 79500 | F251: 79080 | G251: 19557 | H251: =+B251/E251-1 -> 0.0088050314 | I251: =+G251/G250-1 -> 0.029695151
A252: Jan 16, 2025 15:00:00 | B252: 80020 | C252: 80200 | D252: 5363 | E252: 80300 | F252: 80480 | G252: 19912 | H252: -0.003486924 | I252: 0.018152068
A253: Jan 17, 2025 15:00:00 | B253: 80780 | C253: 80020 | D253: 6191 | E253: 80000 | F253: 80500 | G253: 20178 | H253: 0.00975 | I253: 0.013358779
A254: Jan 20, 2025 15:00:00 | B254: 80740 | C254: 80780 | D254: 6378 | E254: 80740 | F254: 80580 | G254: 20228 | H254: 0 | I254: 0.0024779463
A255: Jan 21, 2025 15:00:00 | B255: 78700 | C255: 80740 | D255: 8740 | E255: 80560 | F255: 80820 | G255: 21227 | H255: -0.023088381 | I255: 0.049386988
A256: Jan 22, 2025 15:00:00 | B256: 79300 | C256: 78700 | D256: 3161 | E256: 79280 | F256: 78700 | G256: 20929 | H256: 0.00025227043 | I256: -0.014038724
A257: Jan 23, 2025 15:00:00 | B257: 79660 | C257: 79300 | D257: 4359 | E257: 79140 | F257: 79600 | G257: 21038 | H257: 0.0065706343 | I257: 0.0052080845
A258: Jan 24, 2025 15:00:00 | B258: 79620 | C258: 79660 | D258: 3472 | E258: 79600 | F258: 79460 | G258: 20973 | H258: 0.00025125628 | I258: -0.0030896473
A259: Jan 27, 2025 15:00:00 | B259: 79600 | C259: 79620 | D259: 3668 | E259: 79380 | F259: 79500 | G259: 20898 | H259: 0.002771479 | I259: -0.0035760263
A260: Feb 06, 2025 15:00:00 | B260: 77800 | C260: 78320 | D260: 4695 | E260: 78540 | F260: 78520 | G260: 22439 | H260: =+B260/E260-1 -> -0.0094219506 | I260: =+G260/G259-1 -> 0.073739114
A261: Feb 07, 2025 15:00:00 | B261: 78140 | C261: 77800 | D261: 4636 | E261: 77880 | F261: 77900 | G261: 22765 | H261: 0.0033384694 | I261: 0.014528277
A262: Feb 10, 2025 15:00:00 | B262: 78920 | C262: 78140 | D262: 6178 | E262: 78360 | F262: 77900 | G262: 23228 | H262: 0.0071465033 | I262: 0.020338239
A263: Feb 11, 2025 15:00:00 | B263: 77680 | C263: 78920 | D263: 6377 | E263: 78720 | F263: 79000 | G263: 24061 | H263: -0.013211382 | I263: 0.035861891
A264: Feb 12, 2025 15:00:00 | B264: 77920 | C264: 77680 | D264: 3910 | E264: 77980 | F264: 77980 | G264: 23911 | H264: -0.00076942806 | I264: -0.0062341549
A265: Feb 13, 2025 15:00:00 | B265: 77760 | C265: 77920 | D265: 4965 | E265: 78020 | F265: 78140 | G265: 24754 | H265: -0.0033324789 | I265: 0.03525574
A266: Feb 14, 2025 15:00:00 | B266: 77180 | C266: 77760 | D266: 5556 | E266: 77900 | F266: 77600 | G266: 25820 | H266: =+B266/E266-1 -> -0.0092426187 | I266: =+G266/G265-1 -> 0.043063747
A267: Feb 17, 2025 15:00:00 | B267: 77560 | C267: 77180 | D267: 5048 | E267: 77420 | F267: 77460 | G267: 26117 | H267: =+B267/E267-1 -> 0.0018083183 | I267: =+G267/G266-1 -> 0.011502711
A268: Feb 18, 2025 15:00:00 | B268: 77440 | C268: 77560 | D268: 3431 | E268: 77380 | F268: 77800 | G268: 26139 | H268: 0.00077539416 | I268: 0.00084236321
A269: Feb 19, 2025 15:00:00 | B269: 77620 | C269: 77440 | D269: 3506 | E269: 77580 | F269: 77480 | G269: 26089 | H269: =+B269/E269-1 -> 0.0005155968 | I269: =+G269/G268-1 -> -0.0019128505
A270: Feb 20, 2025 15:00:00 | B270: 77520 | C270: 77620 | D270: 3867 | E270: 77780 | F270: 77960 | G270: 26578 | H270: -0.0033427616 | I270: 0.018743532
A271: Feb 21, 2025 15:00:00 | B271: 77100 | C271: 77520 | D271: 5325 | E271: 77640 | F271: 77600 | G271: 27051 | H271: -0.0069551777 | I271: 0.017796674
A272: Mar 04, 2025 15:00:00 | B272: 75740 | C272: 75940 | D272: 6779 | E272: 76020 | F272: 76020 | G272: 34324 | H272: -0.0036832413 | I272: 0.26886252
A273: Mar 05, 2025 15:00:00 | B273: 75700 | C273: 75740 | D273: 7922 | E273: 75780 | F273: 75880 | G273: 33527 | H273: -0.0010556875 | I273: -0.023219904
A274: Mar 06, 2025 15:00:00 | B274: 77000 | C274: 75700 | D274: 8547 | E274: 75740 | F274: 75700 | G274: 34312 | H274: =+B274/E274-1 -> 0.01663586 | I274: =+G274/G273-1 -> 0.023413965
A275: Mar 07, 2025 15:00:00 | B275: 76520 | C275: 77000 | D275: 10370 | E275: 76360 | F275: 77000 | G275: 35178 | H275: 0.0020953379 | I275: 0.025238983
A276: Mar 10, 2025 15:00:00 | B276: 76040 | C276: 76520 | D276: 10233 | E276: 76840 | F276: 76560 | G276: 35707 | H276: -0.010411244 | I276: 0.015037808
A277: Mar 11, 2025 15:00:00 | B277: 76240 | C277: 76040 | D277: 5989 | E277: 76440 | F277: 76040 | G277: 36097 | H277: =+B277/E277-1 -> -0.0026164312 | I277: =+G277/G276-1 -> 0.010922228
A278: Mar 12, 2025 15:00:00 | B278: 75900 | C278: 76240 | D278: 6776 | E278: 76000 | F278: 76280 | G278: 36319 | H278: -0.0013157895 | I278: 0.0061500956
A279: Mar 13, 2025 15:00:00 | B279: 75580 | C279: 75900 | D279: 4459 | E279: 76100 | F279: 76000 | G279: 36921 | H279: =+B279/E279-1 -> -0.0068331143 | I279: =+G279/G278-1 -> 0.016575346
A280: Mar 14, 2025 15:00:00 | B280: 75780 | C280: 75580 | D280: 7593 | E280: 75700 | F280: 75700 | G280: 38516 | H280: 0.0010568032 | I280: 0.043200347
A281: Mar 17, 2025 15:00:00 | B281: 76460 | C281: 75780 | D281: 12253 | E281: 75920 | F281: 75760 | G281: 41758 | H281: 0.0071127503 | I281: 0.084172811
A282: Mar 18, 2025 15:00:00 | B282: 75700 | C282: 76460 | D282: 13925 | E282: 76320 | F282: 76460 | G282: 44803 | H282: -0.0081236897 | I282: 0.072920159
A283: Mar 19, 2025 15:00:00 | B283: 75480 | C283: 75700 | D283: 7874 | E283: 76120 | F283: 75580 | G283: 45786 | H283: -0.0084077772 | I283: 0.021940495
A284: Mar 20, 2025 15:00:00 | B284: 73700 | C284: 75480 | D284: 32581 | E284: 75620 | F284: 75500 | G284: 53085 | H284: -0.025390108 | I284: 0.15941554
A285: Mar 21, 2025 15:00:00 | B285: 73580 | C285: 73700 | D285: 20457 | E285: 74100 | F285: 73500 | G285: 54920 | H285: -0.0070175439 | I285: 0.034567204
A286: Mar 24, 2025 15:00:00 | B286: 73960 | C286: 73580 | D286: 11643 | E286: 73460 | F286: 73580 | G286: 54476 | H286: 0.0068064253 | I286: -0.0080844865
A287: Mar 25, 2025 15:00:00 | B287: 73940 | C287: 73960 | D287: 13392 | E287: 73840 | F287: 73960 | G287: 56458 | H287: 0.0013542795 | I287: 0.036382994
A288: Mar 26, 2025 15:00:00 | B288: 74520 | C288: 73940 | D288: 19258 | E288: 74200 | F288: 74140 | G288: 58611 | H288: 0.0043126685 | I288: 0.038134542
A289: Mar 27, 2025 15:00:00 | B289: 74480 | C289: 74520 | D289: 17141 | E289: 74220 | F289: 74440 | G289: 62204 | H289: 0.0035030989 | I289: 0.061302486
A290: Mar 28, 2025 15:00:00 | B290: 74320 | C290: 74480 | D290: 20420 | E290: 74500 | F290: 74360 | G290: 66734 | H290: -0.0024161074 | I290: 0.072824899
A291: Apr 01, 2025 15:00:00 | B291: 74500 | C291: 74360 | D291: 14318 | E291: 74220 | F291: 74420 | G291: 69858 | H291: 0.003772568 | I291: 0.046812719
... A324: May 27, 2025 15:00:00 | B324: 60920 | C324: 60100 | D324: 392469 | E324: 60400 | F324: 59940 | G324: 293695 | H324: 0.0086092715 | I324: -0.10039758
A325: May 28, 2025 15:00:00 | B325: 60380 | C325: 60920 | D325: 388140 | E325: 60740 | F325: 61200 | G325: 283607 | H325: =+B325/E325-1 -> -0.0059269015 | I325: =+G325/G324-1 -> -0.034348559
A326: May 29, 2025 15:00:00 | B326: 58860 | C326: 60380 | D326: 386145 | E326: 60200 | F326: 60260 | G326: 287506 | H326: =+B326/E326-1 -> -0.022259136 | I326: =+G326/G325-1 -> 0.013747898
A327: May 30, 2025 15:00:00 | B327: 59800 | C327: 58860 | D327: 429284 | E327: 59080 | F327: 58800 | G327: 261009 | H327: =+B327/E327-1 -> 0.012186865 | I327: =+G327/G326-1 -> -0.092161555
A328: Jun 03, 2025 15:00:00 | B328: 59940 | C328: 59800 | D328: 305161 | E328: 59740 | F328: 59800 | G328: 259658 | H328: 0.0033478406 | I328: -0.0051760667
A329: Jun 05, 2025 15:00:00 | B329: 60100 | C329: 61080 | D329: 244592 | E329: 60360 | F329: 60500 | G329: 231588 | H329: =+B329/E329-1 -> -0.0043074884 | I329: =+G329/G328-1 -> -0.10810374
A330: Jun 06, 2025 15:00:00 | B330: 60440 | C330: 60100 | D330: 256782 | E330: 60300 | F330: 60720 | G330: 218416 | H330: 0.0023217247 | I330: -0.056876868
A331: Jun 09, 2025 15:00:00 | B331: 60700 | C331: 60440 | D331: 165113 | E331: 60800 | F331: 60280 | G331: 212689 | H331: -0.0016447368 | I331: -0.026220607
A332: Jun 10, 2025 15:00:00 | B332: 60760 | C332: 60700 | D332: 204780 | E332: 60660 | F332: 60360 | G332: 194731 | H332: 0.0016485328 | I332: -0.084433139
A333: Jun 12, 2025 15:00:00 | B333: 60440 | C333: 61680 | D333: 169708 | E333: 61400 | F333: 61400 | G333: 162882 | H333: =+B333/E333-1 -> -0.015635179 | I333: =+G333/G332-1 -> -0.16355383
A334: Jun 13, 2025 15:00:00 | B334: 59940 | C334: 60440 | D334: 169471 | E334: 60780 | F334: 60620 | G334: 147432 | H334: -0.013820336 | I334: -0.094853943
A335: Jun 16, 2025 15:00:00 | B335: 60240 | C335: 59940 | D335: 84735 | E335: 60320 | F335: 60340 | G335: 126023 | H335: -0.0013262599 | I335: -0.14521271
A336: Jun 17, 2025 15:00:00 | B336: 60220 | C336: 60240 | D336: 48813 | E336: 60100 | F336: 60220 | G336: 109826 | H336: 0.0019966722 | I336: -0.12852416
A337: Jun 18, 2025 15:00:00 | B337: 60480 | C337: 60220 | D337: 35622 | E337: 60260 | F337: 60280 | G337: 99266 | H337: 0.0036508463 | I337: -0.096152095
A338: Jun 19, 2025 15:00:00 | B338: 60420 | C338: 60480 | D338: 34003 | E338: 60500 | F338: 59800 | G338: 89039 | H338: -0.001322314 | I338: -0.10302621
A339: Jun 23, 2025 15:00:00 | B339: 59720 | C339: 59820 | D339: 26690 | E339: 60200 | F339: 60220 | G339: 74077 | H339: -0.0079734219 | I339: -0.16803872
A340: Jun 24, 2025 15:00:00 | B340: 61020 | C340: 59720 | D340: 55221 | E340: 59820 | F340: 60000 | G340: 60078 | H340: 0.020060181 | I340: -0.18897904
A341: Jun 25, 2025 15:00:00 | B341: 61180 | C341: 61020 | D341: 28735 | E341: 60560 | F341: 61200 | G341: 47834 | H341: 0.010237781 | I341: -0.20380172
A342: Jun 26, 2025 15:00:00 | B342: 61580 | C342: 61180 | D342: 31290 | E342: 61180 | F342: 60580 | G342: 36281 | H342: 0.0065380843 | I342: -0.24152277
A343: Jun 27, 2025 15:00:00 | B343: 63240 | C343: 61580 | D343: 29486 | E343: 61380 | F343: 62380 | G343: 25365 | H343: 0.03030303 | I343: -0.30087374
A344: Jun 30, 2025 15:00:00 | B344: 62420 | C344: 63240 | D344: 18099 | E344: 62620 | F344: 64040 | G344: 16019 | H344: -0.0031938678 | I344: -0.36846048
A345: Jul 01, 2025 15:00:00 | B345: 62980 | C345: 62420 | D345: 955 | E345: 62880 | F345: 63120 | G345: 10845 | H345: 0.0015903308 | I345: -0.32299145
... A354: Jul 14, 2025 15:00:00 | B354: 66200 | C354: 62920 | D354: 137 | E354: 64020 | F354: 64020 | G354: 0 | H354: 0.034051859 | I354: -1

Sheet lc2508
A1: Date | B1: Latest | C1: Prev.Close | D1: Volume | E1: Prev.Settle | F1: Open | G1: Open Interest | H1: Var % | I1: O.I %
A174: Aug 15, 2024 15:00:00 | B174: 81350 | C174: 81350 | D174: 40 | E174: 81350 | F174: 80050 | G174: 29 | H174: 0 | I174: 0
A175: Aug 16, 2024 15:00:00 | B175: 82500 | C175: 81350 | D175: 120 | E175: 80700 | F175: 82500 | G175: 118 | H175: =+B175/E175-1 -> 0.022304833 | I175: =+G175/G174-1 -> 3.0689655
A176: Aug 19, 2024 15:00:00 | B176: 82600 | C176: 82500 | D176: 55 | E176: 82450 | F176: 82500 | G176: 155 | H176: =+B176/E176-1 -> 0.0018192844 | I176: =+G176/G175-1 -> 0.31355932
A177: Aug 20, 2024 15:00:00 | B177: 83850 | C177: 82600 | D177: 60 | E177: 82650 | F177: 82800 | G177: 164 | H177: =+B177/E177-1 -> 0.014519056 | I177: =+G177/G176-1 -> 0.058064516
A178: Aug 21, 2024 15:00:00 | B178: 86000 | C178: 83850 | D178: 110 | E178: 82850 | F178: 83500 | G178: 182 | H178: =+B178/E178-1 -> 0.038020519 | I178: =+G178/G177-1 -> 0.1097561
A179: Aug 22, 2024 15:00:00 | B179: 83800 | C179: 86000 | D179: 104 | E179: 85500 | F179: 85900 | G179: 212 | H179: =+B179/E179-1 -> -0.019883041 | I179: =+G179/G178-1 -> 0.16483516
A180: Aug 23, 2024 15:00:00 | B180: 82450 | C180: 83800 | D180: 96 | E180: 85000 | F180: 83300 | G180: 237 | H180: =+B180/E180-1 -> -0.03 | I180: =+G180/G179-1 -> 0.11792453
A181: Aug 26, 2024 15:00:00 | B181: 82700 | C181: 82450 | D181: 59 | E181: 83050 | F181: 83850 | G181: 239 | H181: =+B181/E181-1 -> -0.0042143287 | I181: =+G181/G180-1 -> 0.0084388186
A182: Aug 27, 2024 15:00:00 | B182: 84050 | C182: 82700 | D182: 173 | E182: 83200 | F182: 82700 | G182: 320 | H182: =+B182/E182-1 -> 0.010216346 | I182: =+G182/G181-1 -> 0.33891213
A183: Aug 28, 2024 15:00:00 | B183: 84100 | C183: 84050 | D183: 81 | E183: 84050 | F183: 84050 | G183: 319 | H183: =+B183/E183-1 -> 0.000594884 | I183: =+G183/G182-1 -> -0.003125
A184: Aug 29, 2024 15:00:00 | B184: 84750 | C184: 84100 | D184: 146 | E184: 84200 | F184: 83950 | G184: 369 | H184: =+B184/E184-1 -> 0.0065320665 | I184: =+G184/G183-1 -> 0.15673981
A185: Aug 30, 2024 15:00:00 | B185: 85950 | C185: 84750 | D185: 265 | E185: 84400 | F185: 85250 | G185: 528 | H185: =+B185/E185-1 -> 0.018364929 | I185: =+G185/G184-1 -> 0.43089431
A186: Sep 02, 2024 15:00:00 | B186: 83200 | C186: 85950 | D186: 111 | E186: 85950 | F186: 85000 | G186: 525 | H186: =+B186/E186-1 -> -0.031995346 | I186: =+G186/G185-1 -> -0.0056818182
... A399: Aug 13, 2025 15:00:00 | B399: 82620 | C399: 86140 | D399: 44 | E399: 82100 | F399: 82620 | G399: 73 | H399: =+B399/E399-1 -> 0.0063337393 | I399: =+G399/G398-1 -> 0

Sheet lc2509
A1: Date | B1: Latest | C1: Prev.Close | D1: Volume | E1: Prev.Settle | F1: Open | G1: Open Interest | H1: Var % | I1: O.I %
A196: Sep 18, 2024 15:00:00 | B196: 81400 | C196: 82050 | D196: 9 | E196: 82050 | F196: 82000 | G196: 728500 | H196: 6
A197: Sep 19, 2024 15:00:00 | B197: 82350 | C197: 81400 | D197: 98 | E197: 80900 | F197: 82600 | G197: 35 | H197: =+B197/E197-1 -> 0.017923362 | I197: =+G197/G196-1 -> -0.99995196
A198: Sep 20, 2024 15:00:00 | B198: 81850 | C198: 82350 | D198: 18 | E198: 80400 | F198: 81400 | G198: 34 | H198: =+B198/E198-1 -> 0.018034826 | I198: =+G198/G197-1 -> -0.028571429
A199: Sep 23, 2024 15:00:00 | B199: 80600 | C199: 81850 | D199: 39 | E199: 81900 | F199: 79000 | G199: 47 | H199: =+B199/E199-1 -> -0.015873016 | I199: =+G199/G198-1 -> 0.38235294
A200: Sep 24, 2024 15:00:00 | B200: 81650 | C200: 80600 | D200: 10 | E200: 80800 | F200: 81150 | G200: 815450 | H200: =+B200/E200-1 -> 0.010519802 | I200: =+G200/G199-1 -> 17349
A201: Sep 25, 2024 15:00:00 | B201: 81750 | C201: 81650 | D201: 168 | E201: 81500 | F201: 83850 | G201: 133 | H201: =+B201/E201-1 -> 0.0030674847 | I201: =+G201/G200-1 -> -0.9998369
A202: Sep 26, 2024 15:00:00 | B202: 83000 | C202: 81750 | D202: 28 | E202: 83850 | F202: 81750 | G202: 147 | H202: =+B202/E202-1 -> -0.01013715 | I202: =+G202/G201-1 -> 0.10526316
A203: Sep 27, 2024 15:00:00 | B203: 83800 | C203: 83000 | D203: 268 | E203: 82200 | F203: 83600 | G203: 336 | H203: =+B203/E203-1 -> 0.01946472 | I203: =+G203/G202-1 -> 1.2857143
A204: Sep 30, 2024 15:00:00 | B204: 86500 | C204: 83800 | D204: 347 | E204: 84000 | F204: 85000 | G204: 535 | H204: =+B204/E204-1 -> 0.029761905 | I204: =+G204/G203-1 -> 0.5922619
A205: Oct 08, 2024 15:00:00 | B205: 83800 | C205: 86500 | D205: 612 | E205: 85150 | F205: 86900 | G205: 905 | H205: =+B205/E205-1 -> -0.015854375 | I205: =+G205/G204-1 -> 0.69158879
A206: Oct 09, 2024 15:00:00 | B206: 84200 | C206: 83800 | D206: 389 | E206: 87950 | F206: 83450 | G206: 1077 | H206: =+B206/E206-1 -> -0.042637862 | I206: =+G206/G205-1 -> 0.19005525
A207: Oct 10, 2024 15:00:00 | B207: 82500 | C207: 84200 | D207: 144 | E207: 84300 | F207: 85050 | G207: 1103 | H207: =+B207/E207-1 -> -0.021352313 | I207: =+G207/G206-1 -> 0.024141133
A208: Oct 11, 2024 15:00:00 | B208: 83550 | C208: 82500 | D208: 121 | E208: 83950 | F208: 83300 | G208: 1137 | H208: =+B208/E208-1 -> -0.0047647409 | I208: =+G208/G207-1 -> 0.030825023
... A384: Jul 24, 2025 15:00:00 | B384: 76680 | C384: 69380 | D384: 1770283 | E384: 71520 | F384: 70180 | G384: 436727 | H384: =+B384/E384-1 -> 0.072147651 | I384: =+G384/G383-1 -> 0.14570878
A385: Jul 25, 2025 15:00:00 | B385: 80520 | C385: 76680 | D385: 1203424 | E385: 74560 | F385: 77500 | G385: 491088 | H385: =+B385/F385-1 -> 0.038967742 | I385: =+G385/G384-1 -> 0.12447364
A386: Jul 28, 2025 15:00:00 | B386: 73120 | C386: 80520 | D386: 1005395 | E386: 79460 | F386: 73200 | G386: 378472 | H386: =+B386/E386-1 -> -0.079788573 | I386: =+G386/G385-1 -> -0.22931939
A387: Jul 29, 2025 15:00:00 | B387: 70840 | C387: 73120 | D387: 744160 | E387: 75280 | F387: 70160 | G387: 300620 | H387: =+B387/E387-1 -> -0.058979809 | I387: =+G387/G386-1 -> -0.20570082
A388: Jul 30, 2025 15:00:00 | B388: 70600 | C388: 70840 | D388: 792909 | E388: 70300 | F388: 72980 | G388: 272753 | H388: =+B388/E388-1 -> 0.0042674253 | I388: =+G388/G387-1 -> -0.092698423
A389: Jul 31, 2025 15:00:00 | B389: 68280 | C389: 70600 | D389: 521849 | E389: 71620 | F389: 68540 | G389: 229368 | H389: =+B389/E389-1 -> -0.046635018 | I389: =+G389/G388-1 -> -0.15906333
A390: Aug 01, 2025 15:00:00 | B390: 68920 | C390: 68280 | D390: 340670 | E390: 67840 | F390: 69080 | G390: 216103 | H390: =+B390/E390-1 -> 0.015919811 | I390: =+G390/G389-1 -> -0.057832828
A391: Aug 04, 2025 15:00:00 | B391: 68920 | C391: 68920 | D391: 247898 | E391: 68860 | F391: 69280 | G391: 207770 | H391: =+B391/E391-1 -> 0.00087133314 | I391: =+G391/G390-1 -> -0.038560316
A392: Aug 05, 2025 15:00:00 | B392: 67680 | C392: 68920 | D392: 173147 | E392: 69520 | F392: 69160 | G392: 175266 | H392: =+B392/E392-1 -> -0.026467204 | I392: =+G392/G391-1 -> -0.15644222
A393: Aug 06, 2025 15:00:00 | B393: 69260 | C393: 67680 | D393: 103705 | E393: 68400 | F393: 67680 | G393: 161898 | H393: =+B393/E393-1 -> 0.012573099 | I393: =+G393/G392-1 -> -0.076272637
A394: Aug 07, 2025 15:00:00 | B394: 71920 | C394: 69260 | D394: 209645 | E394: 68300 | F394: 69600 | G394: 160551 | H394: =+B394/E394-1 -> 0.053001464 | I394: =+G394/G393-1 -> -0.0083200534
A395: Aug 08, 2025 15:00:00 | B395: 76640 | C395: 71920 | D395: 145134 | E395: 71080 | F395: 72340 | G395: 149489 | H395: =+B395/E395-1 -> 0.078221722 | I395: =+G395/G394-1 -> -0.068900225
A396: Aug 11, 2025 15:00:00 | B396: 80560 | C396: 76640 | D396: 16374 | E396: 74600 | F396: 80560 | G396: 148084 | H396: =+B396/E396-1 -> 0.079892761 | I396: =+G396/G395-1 -> -0.0093986849
A397: Aug 12, 2025 15:00:00 | B397: 82560 | C397: 80560 | D397: 162667 | E397: 80540 | F397: 89380 | G397: 117650 | H397: =+B397/E397-1 -> 0.025080705 | I397: =+G397/G396-1 -> -0.20551849
... A414: Sep 05, 2025 15:00:00 | B414: 73880 | C414: 73000 | D414: 50 | E414: 73300 | F414: 73300 | G414: 3467 | H414: =+B414/E414-1 -> 0.0079126876 | I414: =+G414/G413-1 -> -0.10367115

Sheet Contrato 2509
A1: Date | B1: Latest | C1: Prev.Close | D1: Volume | E1: Prev.Settle | F1: Open | G1: Open Interest | H1: Var % | I1: O.I %
A196: Sep 18, 2024 15:00:00 | B196: 81400 | C196: 82050 | D196: 9 | E196: 82050 | F196: 82000 | G196: 728500 | H196: 6
A197: Sep 19, 2024 15:00:00 | B197: 82350 | C197: 81400 | D197: 98 | E197: 80900 | F197: 82600 | G197: 35 | H197: 0.017923362 | I197: -0.99995196
A198: Sep 20, 2024 15:00:00 | B198: 81850 | C198: 82350 | D198: 18 | E198: 80400 | F198: 81400 | G198: 34 | H198: 0.018034826 | I198: -0.028571429
A199: Sep 23, 2024 15:00:00 | B199: 80600 | C199: 81850 | D199: 39 | E199: 81900 | F199: 79000 | G199: 47 | H199: -0.015873016 | I199: 0.38235294
A200: Sep 24, 2024 15:00:00 | B200: 81650 | C200: 80600 | D200: 10 | E200: 80800 | F200: 81150 | G200: 815450 | H200: 0.010519802 | I200: 17349
A201: Sep 25, 2024 15:00:00 | B201: 81750 | C201: 81650 | D201: 168 | E201: 81500 | F201: 83850 | G201: 133 | H201: 0.0030674847 | I201: -0.9998369
A202: Sep 26, 2024 15:00:00 | B202: 83000 | C202: 81750 | D202: 28 | E202: 83850 | F202: 81750 | G202: 147 | H202: -0.01013715 | I202: 0.10526316
A203: Sep 27, 2024 15:00:00 | B203: 83800 | C203: 83000 | D203: 268 | E203: 82200 | F203: 83600 | G203: 336 | H203: 0.01946472 | I203: 1.2857143
A204: Sep 30, 2024 15:00:00 | B204: 86500 | C204: 83800 | D204: 347 | E204: 84000 | F204: 85000 | G204: 535 | H204: 0.029761905 | I204: 0.5922619
